Workbook

Sheet README
A1: MIRROR X · PRELIMINARY · MX-3777d2e495a9
A2: Статус | B2: PRELIMINARY — НЕ ГОТОВО К СДАЧЕ
A3: Snapshot | B3: MX-3777d2e495a9
A4: Срез | B4: 2026-10-29
A5: Правило цен | B5: Regular unadjusted close 2026-11-02; сейчас недоступно
A6: Единицы | B6: USD millions; shares millions; DCF result USD/share
A7: Факты | B7: Годовые факты из официальных документов; нужна сверка кварталов
A8: Допущения | B8: Все драйверы в DCF — аналитические предположения, не прогноз эмитента
A9: Расчёты | B9: Excel formulas + cached results; automatic recalc on open
A10: Источники | B10: SOURCES / COMPANY_FACTS
A11: Ограничение цен | B11: Общий набор UNDATED; не используется как текущая цена
A12: 12m target | B12: EV0*(1+WACC)-FCFF1-netDebt, затем / shares; долг/акции фиксированы
A13: PayPal | B13: BNPL требует нормализации; клиентские средства исключены из cash
A14: Риски | B14: Не является персональной рекомендацией. Buy не подтверждён.

Sheet UNIVERSE_SCREENING
A1: MIRROR X · PRELIMINARY · MX-3777d2e495a9
A2: Ticker | B2: Company | C2: Industry | D2: Price UNDATED | E2: Market cap USD | F2: P/E | G2: EBITDA USD | H2: Score | I2: Status | J2: Source
A3: MMM | B3: 3M | C3: Industrial Conglomerates | D3: 172.8 | E3: 89116835840 | F3: 25.6 | G3: 6497999872 | I3: UNDATED | J3: https://github.com/datasets/s-and-p-500-companies-financials/blob/main/data/constituents-financials.csv
A4: AOS | B4: A. O. Smith | C4: Building Products | D4: 60.86 | E4: 8271395840 | F4: 16.952646 | G4: 783699968 | H4: 81 | I4: UNDATED | J4: https://github.com/datasets/s-and-p-500-companies-financials/blob/main/data/constituents-financials.csv
A5: ABT | B5: Abbott Laboratories | C5: Health Care Equipment | D5: 102.64 | E5: 178779701248 | F5: 38.298508 | G5: 11953999872 | H5: 45 | I5: UNDATED | J5: https://github.com/datasets/s-and-p-500-companies-financials/blob/main/data/constituents-financials.csv
A6: ABBV | B6: AbbVie | C6: Biotechnology | D6: 285.99 | E6: 505377849344 | F6: 80.78813 | G6: 30762999808 | H6: 22 | I6: UNDATED | J6: https://github.com/datasets/s-and-p-500-companies-financials/blob/main/data/constituents-financials.csv
A7: ACN | B7: Accenture | C7: IT Consulting & Other Services | D7: 243.4 | E7: 148946698240 | F7: 17.336182 | G7: 13419352064 | H7: 54 | I7: UNDATED | J7: https://github.com/datasets/s-and-p-500-companies-financials/blob/main/data/constituents-financials.csv
A8: ADBE | B8: Adobe Inc. | C8: Application Software | D8: 249.76 | E8: 97206591488 | F8: 13.86785 | G8: 9916999680 | H8: 95 | I8: UNDATED | J8: https://github.com/datasets/s-and-p-500-companies-financials/blob/main/data/constituents-financials.csv
A9: AMD | B9: Advanced Micro Devices | C9: Semiconductors | D9: 578.44 | E9: 944288825344 | F9: 147.56122 | G9: 9562000384 | H9: 4 | I9: UNDATED | J9: https://github.com/datasets/s-and-p-500-companies-financials/blob/main/data/constituents-financials.csv
A10: AES | B10: AES Corporation | C10: Independent Power Producers & Energy Traders | D10: 14.98 | E10: 10683102208 | F10: 5.6315784 | G10: 4070000128 | I10: UNDATED | J10: https://github.com/datasets/s-and-p-500-companies-financials/blob/main/data/constituents-financials.csv
A11: AFL | B11: Aflac | C11: Life & Health Insurance | D11: 121.75 | E11: 61038546944 | F11: 13.119613 | G11: 6064999936 | I11: UNDATED | J11: https://github.com/datasets/s-and-p-500-companies-financials/blob/main/data/constituents-financials.csv
A12: A | B12: Agilent Technologies | C12: Life Sciences Tools & Services | D12: 181.48 | E12: 51164450816 | F12: 35.034748 | G12: 2080000000 | H12: 67 | I12: UNDATED | J12: https://github.com/datasets/s-and-p-500-companies-financials/blob/main/data/constituents-financials.csv
A13: APD | B13: Air Products | C13: Industrial Gases | D13: 307.2 | E13: 68408999936 | G13: 4652199936 | I13: UNDATED | J13: https://github.com/datasets/s-and-p-500-companies-financials/blob/main/data/constituents-financials.csv
A14: ABNB | B14: Airbnb | C14: Hotels, Resorts & Cruise Lines | D14: 166.045 | E14: 99425361920 | F14: 38.43634 | G14: 2760999936 | H14: 21 | I14: UNDATED | J14: https://github.com/datasets/s-and-p-500-companies-financials/blob/main/data/constituents-financials.csv
A15: AKAM | B15: Akamai Technologies | C15: Internet Services & Infrastructure | D15: 98.1 | E15: 14098598912 | F15: 36.066177 | G15: 1079897984 | I15: UNDATED | J15: https://github.com/datasets/s-and-p-500-companies-financials/blob/main/data/constituents-financials.csv
A16: ALB | B16: Albemarle Corporation | C16: Specialty Chemicals | D16: 96.96 | E16: 11441770496 | F16: 372.9231 | G16: 1482468992 | H16: 36 | I16: UNDATED | J16: https://github.com/datasets/s-and-p-500-companies-financials/blob/main/data/constituents-financials.csv
A17: ARE | B17: Alexandria Real Estate Equities | C17: Office REITs | D17: 39.91 | E17: 6950751232 | G17: 1698887936 | I17: UNDATED | J17: https://github.com/datasets/s-and-p-500-companies-financials/blob/main/data/constituents-financials.csv
A18: ALGN | B18: Align Technology | C18: Health Care Supplies | D18: 153.62 | E18: 10913142784 | F18: 26.440619 | G18: 925662016 | I18: UNDATED | J18: https://github.com/datasets/s-and-p-500-companies-financials/blob/main/data/constituents-financials.csv
A19: ALLE | B19: Allegion | C19: Building Products | D19: 180.66 | E19: 15362745344 | F19: 22.47015 | G19: 1099000064 | H19: 59 | I19: UNDATED | J19: https://github.com/datasets/s-and-p-500-companies-financials/blob/main/data/constituents-financials.csv
A20: LNT | B20: Alliant Energy | C20: Electric Utilities | D20: 69.37 | E20: 17986580480 | F20: 21.543478 | G20: 1828999936 | H20: 38 | I20: UNDATED | J20: https://github.com/datasets/s-and-p-500-companies-financials/blob/main/data/constituents-financials.csv
A21: ALL | B21: Allstate | C21: Property & Casualty Insurance | D21: 250.2 | E21: 63265058816 | F21: 5.0060024 | G21: 17116000256 | I21: UNDATED | J21: https://github.com/datasets/s-and-p-500-companies-financials/blob/main/data/constituents-financials.csv
A22: GOOGL | B22: Alphabet Inc. (Class A) | C22: Interactive Media & Services | D22: 324.89 | E22: 3973383716864 | F22: 16.083664 | G22: 173164003328 | I22: UNDATED | J22: https://github.com/datasets/s-and-p-500-companies-financials/blob/main/data/constituents-financials.csv
A23: GOOG | B23: Alphabet Inc. (Class C) | C23: Interactive Media & Services | D23: 321.89 | E23: 3936694042624 | F23: 15.895803 | G23: 173164003328 | I23: UNDATED | J23: https://github.com/datasets/s-and-p-500-companies-financials/blob/main/data/constituents-financials.csv
A24: MO | B24: Altria | C24: Tobacco | D24: 72.99 | E24: 121874604032 | F24: 15.463984 | G24: 12769999872 | I24: UNDATED | J24: https://github.com/datasets/s-and-p-500-companies-financials/blob/main/data/constituents-financials.csv
A25: AMZN | B25: Amazon | C25: Broadline Retail | D25: 254.6 | E25: 2746195378176 | F25: 20.482702 | G25: 168911994880 | I25: UNDATED | J25: https://github.com/datasets/s-and-p-500-companies-financials/blob/main/data/constituents-financials.csv
A26: AMCR | B26: Amcor | C26: Paper & Plastic Packaging Products & Materials | D26: 45.66 | E26: 21092440064 | F26: 19.184874 | G26: 3536000000 | I26: UNDATED | J26: https://github.com/datasets/s-and-p-500-companies-financials/blob/main/data/constituents-financials.csv
A27: AMTM | B27: Amentum | C27: Diversified Support Services | D27: 21.69 | E27: 5303344128 | F27: 26.132532 | G27: 1006000000 | I27: UNDATED | J27: https://github.com/datasets/s-and-p-500-companies-financials/blob/main/data/constituents-financials.csv
A28: AEE | B28: Ameren | C28: Multi-Utilities | D28: 108 | E28: 29899071488 | F28: 19.148937 | G28: 3910000128 | H28: 57 | I28: UNDATED | J28: https://github.com/datasets/s-and-p-500-companies-financials/blob/main/data/constituents-financials.csv
A29: AEP | B29: American Electric Power | C29: Electric Utilities | D29: 128.2 | E29: 69791744000 | F29: 22.21837 | G29: 9029000192 | H29: 33 | I29: UNDATED | J29: https://github.com/datasets/s-and-p-500-companies-financials/blob/main/data/constituents-financials.csv
A30: AXP | B30: American Express | C30: Consumer Finance | D30: 317.94 | E30: 213195309056 | F30: 17.624168 | I30: UNDATED | J30: https://github.com/datasets/s-and-p-500-companies-financials/blob/main/data/constituents-financials.csv
A31: AIG | B31: American International Group | C31: Multi-line Insurance | D31: 79.88 | E31: 41768706048 | F31: 14.576642 | G31: 8145999872 | I31: UNDATED | J31: https://github.com/datasets/s-and-p-500-companies-financials/blob/main/data/constituents-financials.csv
A32: AMT | B32: American Tower | C32: Telecom Tower REITs | D32: 183.75 | E32: 85620162560 | F32: 25.880281 | G32: 7025900032 | I32: UNDATED | J32: https://github.com/datasets/s-and-p-500-companies-financials/blob/main/data/constituents-financials.csv
A33: AWK | B33: American Water Works | C33: Water Utilities | D33: 139.79 | E33: 27780325376 | F33: 24.43881 | G33: 2912999936 | I33: UNDATED | J33: https://github.com/datasets/s-and-p-500-companies-financials/blob/main/data/constituents-financials.csv
A34: AMP | B34: Ameriprise Financial | C34: Asset Management & Custody Banks | D34: 489.8 | E34: 43298320384 | F34: 11.825206 | I34: UNDATED | J34: https://github.com/datasets/s-and-p-500-companies-financials/blob/main/data/constituents-financials.csv
A35: AME | B35: Ametek | C35: Electrical Components & Equipment | D35: 248.13 | E35: 56872144896 | F35: 36.276318 | G35: 2500681984 | H35: 74 | I35: UNDATED | J35: https://github.com/datasets/s-and-p-500-companies-financials/blob/main/data/constituents-financials.csv
A36: AMGN | B36: Amgen | C36: Biotechnology | D36: 451.83 | E36: 244273741824 | F36: 27.822044 | G36: 17268000768 | H36: 58 | I36: UNDATED | J36: https://github.com/datasets/s-and-p-500-companies-financials/blob/main/data/constituents-financials.csv
A37: APH | B37: Amphenol | C37: Electronic Components | D37: 80.96 | E37: 199644676096 | F37: 39.11111 | G37: 9463700480 | I37: UNDATED | J37: https://github.com/datasets/s-and-p-500-companies-financials/blob/main/data/constituents-financials.csv
A38: ADI | B38: Analog Devices | C38: Semiconductors | D38: 428.27 | E38: 207524855808 | F38: 50.50354 | G38: 6922700800 | H38: 29 | I38: UNDATED | J38: https://github.com/datasets/s-and-p-500-companies-financials/blob/main/data/constituents-financials.csv
A39: ANSS | B39: Ansys | C39: Application Software | I39: UNDATED | J39: https://github.com/datasets/s-and-p-500-companies-financials/blob/main/data/constituents-financials.csv
A40: AON | B40: Aon | C40: Insurance Brokers | D40: 315.72 | E40: 66972246016 | F40: 17.40463 | G40: 5900000256 | I40: UNDATED | J40: https://github.com/datasets/s-and-p-500-companies-financials/blob/main/data/constituents-financials.csv
A41: APA | B41: APA Corporation | C41: Oil & Gas Exploration & Production | D41: 51.11 | E41: 17906466816 | F41: 10.805497 | G41: 5720000000 | H41: 93 | I41: UNDATED | J41: https://github.com/datasets/s-and-p-500-companies-financials/blob/main/data/constituents-financials.csv
A42: AAPL | B42: Apple Inc. | C42: Technology Hardware, Storage & Peripherals | D42: 343.83 | E42: 5017916932096 | F42: 39.795135 | G42: 167959003136 | H42: 19 | I42: UNDATED | J42: https://github.com/datasets/s-and-p-500-companies-financials/blob/main/data/constituents-financials.csv
A43: AMAT | B43: Applied Materials | C43: Semiconductor Materials & Equipment | D43: 416 | E43: 330136551424 | F43: 34.15435 | G43: 10154999808 | H43: 62 | I43: UNDATED | J43: https://github.com/datasets/s-and-p-500-companies-financials/blob/main/data/constituents-financials.csv
A44: APTV | B44: Aptiv | C44: Automotive Parts & Equipment | D44: 44.08 | E44: 9328233472 | F44: 43.643566 | G44: 3232999936 | I44: UNDATED | J44: https://github.com/datasets/s-and-p-500-companies-financials/blob/main/data/constituents-financials.csv
A45: ACGL | B45: Arch Capital Group | C45: Property & Casualty Insurance | D45: 102.5 | E45: 34952499200 | F45: 8.206566 | G45: 5565000192 | I45: UNDATED | J45: https://github.com/datasets/s-and-p-500-companies-financials/blob/main/data/constituents-financials.csv
A46: ADM | B46: Archer Daniels Midland | C46: Agricultural Products & Services | D46: 77.23 | E46: 37221502976 | F46: 21.45278 | G46: 2995000064 | I46: UNDATED | J46: https://github.com/datasets/s-and-p-500-companies-financials/blob/main/data/constituents-financials.csv
A47: ANET | B47: Arista Networks | C47: Communications Equipment | D47: 186.72 | E47: 235495882752 | F47: 58.902206 | G47: 4639600128 | I47: UNDATED | J47: https://github.com/datasets/s-and-p-500-companies-financials/blob/main/data/constituents-financials.csv
A48: AJG | B48: Arthur J. Gallagher & Co. | C48: Insurance Brokers | D48: 260.42 | E48: 66756325376 | F48: 43.187397 | G48: 4288000000 | I48: UNDATED | J48: https://github.com/datasets/s-and-p-500-companies-financials/blob/main/data/constituents-financials.csv
A49: AIZ | B49: Assurant | C49: Multi-line Insurance | D49: 284.99 | E49: 14056779776 | F49: 13.708032 | G49: 1737100032 | I49: UNDATED | J49: https://github.com/datasets/s-and-p-500-companies-financials/blob/main/data/constituents-financials.csv
A50: T | B50: AT&T | C50: Integrated Telecommunication Services | D50: 20.7 | E50: 139445010432 | F50: 11.069519 | G50: 45940998144 | I50: UNDATED | J50: https://github.com/datasets/s-and-p-500-companies-financials/blob/main/data/constituents-financials.csv
A51: ATO | B51: Atmos Energy | C51: Gas Utilities | D51: 169.53 | E51: 28648630272 | F51: 20.206198 | G51: 2624299008 | I51: UNDATED | J51: https://github.com/datasets/s-and-p-500-companies-financials/blob/main/data/constituents-financials.csv
A52: ADSK | B52: Autodesk | C52: Application Software | D52: 242.38 | E52: 50657419264 | F52: 31.437096 | G52: 2286000128 | H52: 35 | I52: UNDATED | J52: https://github.com/datasets/s-and-p-500-companies-financials/blob/main/data/constituents-financials.csv
A53: ADP | B53: Automatic Data Processing | C53: Human Resource & Employment Services | D53: 285.37 | E53: 113078304768 | F53: 26.795305 | G53: 6411200000 | I53: UNDATED | J53: https://github.com/datasets/s-and-p-500-companies-financials/blob/main/data/constituents-financials.csv
A54: AZO | B54: AutoZone | C54: Automotive Retail | D54: 3156.76 | E54: 50805972992 | F54: 20.693281 | G54: 4279979008 | I54: UNDATED | J54: https://github.com/datasets/s-and-p-500-companies-financials/blob/main/data/constituents-financials.csv
A55: AVB | B55: AvalonBay Communities | C55: Multi-Family Residential REITs | D55: 184.06 | E55: 26283393024 | F55: 25.248285 | G55: 1857816064 | I55: UNDATED | J55: https://github.com/datasets/s-and-p-500-companies-financials/blob/main/data/constituents-financials.csv
A56: AVY | B56: Avery Dennison | C56: Paper & Plastic Packaging Products & Materials | D56: 180.7 | E56: 13821811712 | F56: 19.90088 | G56: 1496499968 | I56: UNDATED | J56: https://github.com/datasets/s-and-p-500-companies-financials/blob/main/data/constituents-financials.csv
A57: AXON | B57: Axon Enterprise | C57: Aerospace & Defense | D57: 423.17 | E57: 34377236480 | F57: 177.05858 | G57: 165106000 | H57: 4 | I57: UNDATED | J57: https://github.com/datasets/s-and-p-500-companies-financials/blob/main/data/constituents-financials.csv
A58: BKR | B58: Baker Hughes | C58: Oil & Gas Equipment & Services | D58: 54.66 | E58: 54259564544 | F58: 17.575563 | G58: 4839000064 | I58: UNDATED | J58: https://github.com/datasets/s-and-p-500-companies-financials/blob/main/data/constituents-financials.csv
A59: BALL | B59: Ball Corporation | C59: Metal, Glass & Plastic Containers | D59: 63.26 | E59: 16842754048 | F59: 18.02279 | G59: 2076000000 | I59: UNDATED | J59: https://github.com/datasets/s-and-p-500-companies-financials/blob/main/data/constituents-financials.csv
A60: BAC | B60: Bank of America | C60: Diversified Banks | D60: 50.85 | E60: 352019054592 | F60: 12.107143 | I60: UNDATED | J60: https://github.com/datasets/s-and-p-500-companies-financials/blob/main/data/constituents-financials.csv
A61: BAX | B61: Baxter International | C61: Health Care Equipment | D61: 25.46 | E61: 13162717184 | G61: 1884000000 | I61: UNDATED | J61: https://github.com/datasets/s-and-p-500-companies-financials/blob/main/data/constituents-financials.csv
A62: BDX | B62: Becton Dickinson | C62: Health Care Equipment | D62: 195.16 | E62: 53159010304 | F62: 45.386044 | G62: 6120999936 | H62: 50 | I62: UNDATED | J62: https://github.com/datasets/s-and-p-500-companies-financials/blob/main/data/constituents-financials.csv
A63: BRK.B | B63: Berkshire Hathaway | C63: Multi-Sector Holdings | I63: UNDATED | J63: https://github.com/datasets/s-and-p-500-companies-financials/blob/main/data/constituents-financials.csv
A64: BBY | B64: Best Buy | C64: Computer & Electronics Retail | D64: 96.96 | E64: 20335198208 | F64: 16.378378 | G64: 2617999872 | I64: UNDATED | J64: https://github.com/datasets/s-and-p-500-companies-financials/blob/main/data/constituents-financials.csv
A65: TECH | B65: Bio-Techne | C65: Life Sciences Tools & Services | D65: 72.69 | E65: 11399117824 | F65: 62.663795 | G65: 334105984 | H65: 16 | I65: UNDATED | J65: https://github.com/datasets/s-and-p-500-companies-financials/blob/main/data/constituents-financials.csv
A66: BIIB | B66: Biogen | C66: Biotechnology | D66: 244.05 | E66: 36059365376 | F66: 43.348133 | G66: 3359200000 | H66: 52 | I66: UNDATED | J66: https://github.com/datasets/s-and-p-500-companies-financials/blob/main/data/constituents-financials.csv
A67: BLK | B67: BlackRock | C67: Asset Management & Custody Banks | D67: 1157.88 | E67: 188127936512 | F67: 25.868633 | G67: 12005999616 | I67: UNDATED | J67: https://github.com/datasets/s-and-p-500-companies-financials/blob/main/data/constituents-financials.csv
A68: BX | B68: Blackstone Inc. | C68: Asset Management & Custody Banks | D68: 117.06 | E68: 139921555456 | F68: 26.07127 | I68: UNDATED | J68: https://github.com/datasets/s-and-p-500-companies-financials/blob/main/data/constituents-financials.csv
A69: BK | B69: BNY Mellon | C69: Asset Management & Custody Banks | I69: UNDATED | J69: https://github.com/datasets/s-and-p-500-companies-financials/blob/main/data/constituents-financials.csv
A70: BA | B70: Boeing | C70: Aerospace & Defense | D70: 167.14 | E70: 132450082816 | F70: 17.356178 | G70: 2348999936 | H70: 53 | I70: UNDATED | J70: https://github.com/datasets/s-and-p-500-companies-financials/blob/main/data/constituents-financials.csv
A71: BKNG | B71: Booking Holdings | C71: Hotels, Resorts & Cruise Lines | D71: 147.94 | E71: 114635522048 | F71: 16.641169 | G71: 10412999680 | H71: 69 | I71: UNDATED | J71: https://github.com/datasets/s-and-p-500-companies-financials/blob/main/data/constituents-financials.csv
A72: BWA | B72: BorgWarner | C72: Automotive Parts & Equipment | D72: 55.93 | E72: 11391058944 | F72: 27.82587 | G72: 2036000000 | I72: UNDATED | J72: https://github.com/datasets/s-and-p-500-companies-financials/blob/main/data/constituents-financials.csv
A73: BSX | B73: Boston Scientific | C73: Health Care Equipment | D73: 42.43 | E73: 61490810880 | F73: 18.2103 | G73: 5711000064 | H73: 85 | I73: UNDATED | J73: https://github.com/datasets/s-and-p-500-companies-financials/blob/main/data/constituents-financials.csv
A74: BMY | B74: Bristol Myers Squibb | C74: Pharmaceuticals | D74: 60.57 | E74: 123727224832 | F74: 13.550336 | G74: 18929999872 | H74: 82 | I74: UNDATED | J74: https://github.com/datasets/s-and-p-500-companies-financials/blob/main/data/constituents-financials.csv
A75: AVGO | B75: Broadcom | C75: Semiconductors | D75: 351.81 | E75: 1679410724864 | F75: 44.931034 | G75: 52259999744 | H75: 35 | I75: UNDATED | J75: https://github.com/datasets/s-and-p-500-companies-financials/blob/main/data/constituents-financials.csv
A76: BR | B76: Broadridge Financial Solutions | C76: Data Processing & Outsourced Services | D76: 176.97 | E76: 19979919360 | F76: 18.453598 | G76: 1808999936 | I76: UNDATED | J76: https://github.com/datasets/s-and-p-500-companies-financials/blob/main/data/constituents-financials.csv
A77: BRO | B77: Brown & Brown | C77: Insurance Brokers | D77: 65.88 | E77: 21851856896 | F77: 21.38961 | G77: 2352999936 | I77: UNDATED | J77: https://github.com/datasets/s-and-p-500-companies-financials/blob/main/data/constituents-financials.csv
A78: BF.B | B78: Brown–Forman | C78: Distillers & Vintners | I78: UNDATED | J78: https://github.com/datasets/s-and-p-500-companies-financials/blob/main/data/constituents-financials.csv
A79: BLDR | B79: Builders FirstSource | C79: Building Products | D79: 55.88 | E79: 6012490240 | F79: 61.406593 | G79: 1022512000 | H79: 41 | I79: UNDATED | J79: https://github.com/datasets/s-and-p-500-companies-financials/blob/main/data/constituents-financials.csv
A80: BG | B80: Bunge Global | C80: Agricultural Products & Services | D80: 100.8 | E80: 19365607424 | F80: 20.200403 | G80: 3126000128 | I80: UNDATED | J80: https://github.com/datasets/s-and-p-500-companies-financials/blob/main/data/constituents-financials.csv
A81: BXP | B81: BXP, Inc. | C81: Office REITs | D81: 61.48 | E81: 11120344064 | F81: 32.70213 | G81: 1617154048 | I81: UNDATED | J81: https://github.com/datasets/s-and-p-500-companies-financials/blob/main/data/constituents-financials.csv
A82: CHRW | B82: C.H. Robinson | C82: Air Freight & Logistics | D82: 127.6 | E82: 14733249536 | F82: 27.440859 | G82: 932641024 | I82: UNDATED | J82: https://github.com/datasets/s-and-p-500-companies-financials/blob/main/data/constituents-financials.csv
A83: CDNS | B83: Cadence Design Systems | C83: Application Software | D83: 342.46 | E83: 94455947264 | F83: 68.219124 | G83: 2232577024 | H83: 15 | I83: UNDATED | J83: https://github.com/datasets/s-and-p-500-companies-financials/blob/main/data/constituents-financials.csv
A84: CZR | B84: Caesars Entertainment | C84: Casinos & Gaming | D84: 28.57 | E84: 5821998080 | G84: 3459000064 | I84: UNDATED | J84: https://github.com/datasets/s-and-p-500-companies-financials/blob/main/data/constituents-financials.csv
A85: CPT | B85: Camden Property Trust | C85: Multi-Family Residential REITs | D85: 99.49 | E85: 10002660352 | F85: 33.498314 | G85: 893971008 | I85: UNDATED | J85: https://github.com/datasets/s-and-p-500-companies-financials/blob/main/data/constituents-financials.csv
A86: CPB | B86: Campbell Soup Company | C86: Packaged Foods & Meats | D86: 20.59 | E86: 6140652032 | F86: 15.838462 | G86: 1620000000 | H86: 86 | I86: UNDATED | J86: https://github.com/datasets/s-and-p-500-companies-financials/blob/main/data/constituents-financials.csv
A87: COF | B87: Capital One | C87: Consumer Finance | D87: 204.88 | E87: 125693886464 | F87: 13.158639 | I87: UNDATED | J87: https://github.com/datasets/s-and-p-500-companies-financials/blob/main/data/constituents-financials.csv
A88: CAH | B88: Cardinal Health | C88: Health Care Distributors | D88: 244.76 | E88: 56676462592 | F88: 33.853386 | G88: 4244000000 | I88: UNDATED | J88: https://github.com/datasets/s-and-p-500-companies-financials/blob/main/data/constituents-financials.csv
A89: KMX | B89: CarMax | C89: Automotive Retail | D89: 53.99 | E89: 7663492096 | F89: 25.587679 | G89: 1127090048 | I89: UNDATED | J89: https://github.com/datasets/s-and-p-500-companies-financials/blob/main/data/constituents-financials.csv
A90: CCL | B90: Carnival | C90: Hotels, Resorts & Cruise Lines | D90: 28.06 | E90: 37729759232 | F90: 12.2 | G90: 7292000256 | H90: 81 | I90: UNDATED | J90: https://github.com/datasets/s-and-p-500-companies-financials/blob/main/data/constituents-financials.csv
A91: CARR | B91: Carrier Global | C91: Building Products | D91: 56.27 | E91: 46736760832 | F91: 41.99254 | G91: 3092999936 | H91: 27 | I91: UNDATED | J91: https://github.com/datasets/s-and-p-500-companies-financials/blob/main/data/constituents-financials.csv
A92: CTLT | B92: Catalent | C92: Pharmaceuticals | I92: UNDATED | J92: https://github.com/datasets/s-and-p-500-companies-financials/blob/main/data/constituents-financials.csv
A93: CAT | B93: Caterpillar Inc. | C93: Construction Machinery & Heavy Transportation Equipment | D93: 713.38 | E93: 327922876416 | F93: 30.709429 | G93: 16250999808 | I93: UNDATED | J93: https://github.com/datasets/s-and-p-500-companies-financials/blob/main/data/constituents-financials.csv
A94: CBOE | B94: Cboe Global Markets | C94: Financial Exchanges & Data | D94: 320.42 | E94: 33461786624 | F94: 24.97428 | G94: 1930700032 | I94: UNDATED | J94: https://github.com/datasets/s-and-p-500-companies-financials/blob/main/data/constituents-financials.csv
A95: CBRE | B95: CBRE Group | C95: Real Estate Services | D95: 123.7 | E95: 35649875968 | F95: 26.042105 | G95: 2200000000 | I95: UNDATED | J95: https://github.com/datasets/s-and-p-500-companies-financials/blob/main/data/constituents-financials.csv
A96: CDW | B96: CDW | C96: Technology Distributors | D96: 162.66 | E96: 20335335424 | F96: 19.410501 | G96: 2010899968 | I96: UNDATED | J96: https://github.com/datasets/s-and-p-500-companies-financials/blob/main/data/constituents-financials.csv
A97: CE | B97: Celanese | C97: Specialty Chemicals | D97: 48.85 | E97: 5361234944 | G97: 1676999936 | I97: UNDATED | J97: https://github.com/datasets/s-and-p-500-companies-financials/blob/main/data/constituents-financials.csv
A98: COR | B98: Cencora | C98: Health Care Distributors | D98: 324.35 | E98: 61894791168 | F98: 24.151154 | G98: 5546476032 | I98: UNDATED | J98: https://github.com/datasets/s-and-p-500-companies-financials/blob/main/data/constituents-financials.csv
A99: CNC | B99: Centene Corporation | C99: Managed Health Care | D99: 67.05 | E99: 33194311680 | F99: 23.609158 | G99: 3123000064 | I99: UNDATED | J99: https://github.com/datasets/s-and-p-500-companies-financials/blob/main/data/constituents-financials.csv
A100: CNP | B100: CenterPoint Energy | C100: Multi-Utilities | D100: 41.59 | E100: 27569164288 | F100: 24.180233 | G100: 4088000000 | H100: 44 | I100: UNDATED | J100: https://github.com/datasets/s-and-p-500-companies-financials/blob/main/data/constituents-financials.csv
...

Sheet SOURCES
A1: MIRROR X · PRELIMINARY · MX-3777d2e495a9
A2: Ticker | B2: Source | C2: Period | D2: Published / signed | E2: Status
A3: UNIVERSE | B3: https://github.com/datasets/s-and-p-500-companies-financials/blob/main/data/constituents-financials.csv | C3: UNKNOWN | D3: UNKNOWN | E3: UNDATED
A4: ADBE | B4: https://www.adobe.com/cc-shared/assets/investor-relations/pdfs/adbe-2025-annual-report.pdf | C4: 2025-11-28 | D4: 2026-01-15 | E4: ANNUAL FACTS / NEEDS QUARTERLY UPDATE
A5: PYPL | B5: https://www.sec.gov/Archives/edgar/data/1633917/000163391726000024/pypl-20251231.htm | C5: 2025-12-31 | D5: 2026-02-03 | E5: ANNUAL FACTS / NEEDS QUARTERLY UPDATE
A6: NKE | B6: https://investors.nike.com/sec-filings/all-sec-filings/content/0000320187-26-000088/nke-20260531.htm | C6: 2026-05-31 | D6: 2026-07-15 | E6: ANNUAL FACTS / NEEDS QUARTERLY UPDATE
A7: MACRO | B7: https://www.federalreserve.gov/newsevents/pressreleases/monetary20261028a.htm | C7: 2026-10-28 | D7: 2026-10-28 | E7: Fed funds held 3.75–4.00%; not risk-free yield

Sheet COMPANY_FACTS
A1: MIRROR X · PRELIMINARY · MX-3777d2e495a9
A2: Ticker | B2: Period end | C2: Revenue | D2: Operating income | E2: Cash + ST inv. | F2: Debt | G2: Diluted shares | H2: Effective tax | I2: Source
A3: ADBE | B3: 2025-11-28 | C3: 23769 | D3: 8706 | E3: 6595 | F3: 6210 | G3: 427 | H3: 0.1836501 | I3: https://www.adobe.com/cc-shared/assets/investor-relations/pdfs/adbe-2025-annual-report.pdf
A4: PYPL | B4: 2025-12-31 | C4: 33172 | D4: 6065 | E4: 10422 | F4: 9987 | G4: 968 | H4: 0.16830896 | I4: https://www.sec.gov/Archives/edgar/data/1633917/000163391726000024/pypl-20251231.htm
A5: NKE | B5: 2026-05-31 | C5: 46398 | D5: 3797 | E5: 9027 | F5: 7942 | G5: 1481 | H5: 0.20307692 | I5: https://investors.nike.com/sec-filings/all-sec-filings/content/0000320187-26-000088/nke-20260531.htm

Sheet DCF_ADBE
A1: MIRROR X · PRELIMINARY · MX-3777d2e495a9
A2: Драйвер / единицы | B2: Значение | C2: Классификация
A3: Revenue (USD mn) | B3: 23769 | C3: Annual report
A4: Annual growth | B4: 0.07 | C4: Analyst assumption
A5: Operating margin | B5: 0.35 | C5: Analyst assumption
A6: Tax rate | B6: 0.2 | C6: Analyst assumption
A7: D&A / revenue | B7: 0.02 | C7: Analyst assumption
A8: CapEx / revenue | B8: 0.02 | C8: Analyst assumption
A9: NWC / revenue | B9: 0.03 | C9: Analyst assumption
A10: WACC | B10: 0.1 | C10: Scenario; not a measured CAPM WACC
A11: Terminal growth | B11: 0.025 | C11: Analyst assumption
A12: Diluted shares (mn) | B12: 427 | C12: Annual weighted average
A13: Net debt (USD mn) | B13: -385 | C13: Debt - cash - short-term investments
A16: Forecast / USD mn | B16: 1 | C16: 2 | D16: 3 | E16: 4 | F16: 5
A17: Revenue | B17: =$B$3*(1+$B$4) -> 25432.83 | C17: =B17*(1+$B$4) -> 27213.128 | D17: =C17*(1+$B$4) -> 29118.047 | E17: =D17*(1+$B$4) -> 31156.31 | F17: =E17*(1+$B$4) -> 33337.252
A18: EBIT | B18: =B17*$B$5 -> 8901.4905 | C18: =C17*$B$5 -> 9524.5948 | D18: =D17*$B$5 -> 10191.316 | E18: =E17*$B$5 -> 10904.709 | F18: =F17*$B$5 -> 11668.038
A19: NOPAT | B19: =B18*(1-$B$6) -> 7121.1924 | C19: =C18*(1-$B$6) -> 7619.6759 | D19: =D18*(1-$B$6) -> 8153.0532 | E19: =E18*(1-$B$6) -> 8723.7669 | F19: =F18*(1-$B$6) -> 9334.4306
A20: D&A | B20: =B17*$B$7 -> 508.6566 | C20: =C17*$B$7 -> 544.26256 | D20: =D17*$B$7 -> 582.36094 | E20: =E17*$B$7 -> 623.12621 | F20: =F17*$B$7 -> 666.74504
A21: CapEx | B21: =B17*$B$8 -> 508.6566 | C21: =C17*$B$8 -> 544.26256 | D21: =D17*$B$8 -> 582.36094 | E21: =E17*$B$8 -> 623.12621 | F21: =F17*$B$8 -> 666.74504
A22: Delta NWC | B22: =(B17-$B$3)*$B$9 -> 49.9149 | C22: =(C17-B17)*$B$9 -> 53.408943 | D22: =(D17-C17)*$B$9 -> 57.147569 | E22: =(E17-D17)*$B$9 -> 61.147899 | F22: =(F17-E17)*$B$9 -> 65.428252
A23: FCFF | B23: =B19+B20-B21-B22 -> 7071.2775 | C23: =C19+C20-C21-C22 -> 7566.2669 | D23: =D19+D20-D21-D22 -> 8095.9056 | E23: =E19+E20-E21-E22 -> 8662.619 | F23: =F19+F20-F21-F22 -> 9269.0023
A24: PV FCFF | B24: =B23/(1+$B$10)^1 -> 6428.4341 | C24: =C23/(1+$B$10)^2 -> 6253.1132 | D24: =D23/(1+$B$10)^3 -> 6082.5737 | E24: =E23/(1+$B$10)^4 -> 5916.6853 | F24: =F23/(1+$B$10)^5 -> 5755.3212
A27: FCFF year 6 | B27: =F17*(1+$B$11)*($B$5*(1-$B$6)+$B$7-$B$8)-F17*$B$11*$B$9 -> 9542.7884
A28: Terminal value | B28: =B27/($B$10-$B$11) -> 127237.18
A29: PV terminal | B29: =B28/(1+$B$10)^5 -> 79004.277
A30: Enterprise value | B30: =SUM(B24:F24)+B29 -> 109440.4
A31: Equity value | B31: =B30-$B$13 -> 109825.4
A32: Fair value / share | B32: =B31/$B$12 -> 257.20235
A33: 12m model target / share | B33: =(B30*(1+$B$10)-B23-$B$13)/$B$12 -> 266.27206
A34: Terminal share / EV | B34: =B29/B30 -> 0.72189314
A36: Source | B36: https://www.adobe.com/cc-shared/assets/investor-relations/pdfs/adbe-2025-annual-report.pdf
A37: Model anchor FY | B37: 2025-11-28
A38: Do not treat as 02 Nov target | B38: PRELIMINARY
A39: Model check | B39: =IF(AND(B10>B11,B12>0,B27>0),"PASS","FAIL") -> PASS

Sheet DCF_PYPL
A1: MIRROR X · PRELIMINARY · MX-3777d2e495a9
A2: Драйвер / единицы | B2: Значение | C2: Классификация
A3: Revenue (USD mn) | B3: 33172 | C3: Annual report
A4: Annual growth | B4: 0.04 | C4: Analyst assumption
A5: Operating margin | B5: 0.18 | C5: Analyst assumption
A6: Tax rate | B6: 0.21 | C6: Analyst assumption
A7: D&A / revenue | B7: 0.03 | C7: Analyst assumption
A8: CapEx / revenue | B8: 0.025 | C8: Analyst assumption
A9: NWC / revenue | B9: 0.02 | C9: Analyst assumption
A10: WACC | B10: 0.105 | C10: Scenario; not a measured CAPM WACC
A11: Terminal growth | B11: 0.02 | C11: Analyst assumption
A12: Diluted shares (mn) | B12: 968 | C12: Annual weighted average
A13: Net debt (USD mn) | B13: -435 | C13: Debt - cash - short-term investments
A16: Forecast / USD mn | B16: 1 | C16: 2 | D16: 3 | E16: 4 | F16: 5
A17: Revenue | B17: =$B$3*(1+$B$4) -> 34498.88 | C17: =B17*(1+$B$4) -> 35878.835 | D17: =C17*(1+$B$4) -> 37313.989 | E17: =D17*(1+$B$4) -> 38806.548 | F17: =E17*(1+$B$4) -> 40358.81
A18: EBIT | B18: =B17*$B$5 -> 6209.7984 | C18: =C17*$B$5 -> 6458.1903 | D18: =D17*$B$5 -> 6716.5179 | E18: =E17*$B$5 -> 6985.1787 | F18: =F17*$B$5 -> 7264.5858
A19: NOPAT | B19: =B18*(1-$B$6) -> 4905.7407 | C19: =C18*(1-$B$6) -> 5101.9704 | D19: =D18*(1-$B$6) -> 5306.0492 | E19: =E18*(1-$B$6) -> 5518.2911 | F19: =F18*(1-$B$6) -> 5739.0228
A20: D&A | B20: =B17*$B$7 -> 1034.9664 | C20: =C17*$B$7 -> 1076.3651 | D20: =D17*$B$7 -> 1119.4197 | E20: =E17*$B$7 -> 1164.1964 | F20: =F17*$B$7 -> 1210.7643
A21: CapEx | B21: =B17*$B$8 -> 862.472 | C21: =C17*$B$8 -> 896.97088 | D21: =D17*$B$8 -> 932.84972 | E21: =E17*$B$8 -> 970.1637 | F21: =F17*$B$8 -> 1008.9703
A22: Delta NWC | B22: =(B17-$B$3)*$B$9 -> 26.5376 | C22: =(C17-B17)*$B$9 -> 27.599104 | D22: =(D17-C17)*$B$9 -> 28.703068 | E22: =(E17-D17)*$B$9 -> 29.851191 | F22: =(F17-E17)*$B$9 -> 31.045239
A23: FCFF | B23: =B19+B20-B21-B22 -> 5051.6975 | C23: =C19+C20-C21-C22 -> 5253.7654 | D23: =D19+D20-D21-D22 -> 5463.9161 | E23: =E19+E20-E21-E22 -> 5682.4727 | F23: =F19+F20-F21-F22 -> 5909.7716
A24: PV FCFF | B24: =B23/(1+$B$10)^1 -> 4571.672 | C24: =C23/(1+$B$10)^2 -> 4302.7501 | D24: =D23/(1+$B$10)^3 -> 4049.6472 | E24: =E23/(1+$B$10)^4 -> 3811.4326 | F24: =F23/(1+$B$10)^5 -> 3587.2307
A27: FCFF year 6 | B27: =F17*(1+$B$11)*($B$5*(1-$B$6)+$B$7-$B$8)-F17*$B$11*$B$9 -> 6043.4897
A28: Terminal value | B28: =B27/($B$10-$B$11) -> 71099.878
A29: PV terminal | B29: =B28/(1+$B$10)^5 -> 43157.618
A30: Enterprise value | B30: =SUM(B24:F24)+B29 -> 63480.351
A31: Equity value | B31: =B30-$B$13 -> 63915.351
A32: Fair value / share | B32: =B31/$B$12 -> 66.028255
A33: 12m model target / share | B33: =(B30*(1+$B$10)-B23-$B$13)/$B$12 -> 67.695341
A34: Terminal share / EV | B34: =B29/B30 -> 0.6798579
A36: Source | B36: https://www.sec.gov/Archives/edgar/data/1633917/000163391726000024/pypl-20251231.htm
A37: Model anchor FY | B37: 2025-12-31
A38: Do not treat as 02 Nov target | B38: PRELIMINARY
A39: Model check | B39: =IF(AND(B10>B11,B12>0,B27>0),"PASS","FAIL") -> PASS

Sheet DCF_NKE
A1: MIRROR X · PRELIMINARY · MX-3777d2e495a9
A2: Драйвер / единицы | B2: Значение | C2: Классификация
A3: Revenue (USD mn) | B3: 46398 | C3: Annual report
A4: Annual growth | B4: 0.035 | C4: Analyst assumption
A5: Operating margin | B5: 0.1 | C5: Analyst assumption
A6: Tax rate | B6: 0.22 | C6: Analyst assumption
A7: D&A / revenue | B7: 0.017 | C7: Analyst assumption
A8: CapEx / revenue | B8: 0.025 | C8: Analyst assumption
A9: NWC / revenue | B9: 0.1 | C9: Analyst assumption
A10: WACC | B10: 0.1 | C10: Scenario; not a measured CAPM WACC
A11: Terminal growth | B11: 0.02 | C11: Analyst assumption
A12: Diluted shares (mn) | B12: 1481 | C12: Annual weighted average
A13: Net debt (USD mn) | B13: -1085 | C13: Debt - cash - short-term investments
A16: Forecast / USD mn | B16: 1 | C16: 2 | D16: 3 | E16: 4 | F16: 5
A17: Revenue | B17: =$B$3*(1+$B$4) -> 48021.93 | C17: =B17*(1+$B$4) -> 49702.698 | D17: =C17*(1+$B$4) -> 51442.292 | E17: =D17*(1+$B$4) -> 53242.772 | F17: =E17*(1+$B$4) -> 55106.269
A18: EBIT | B18: =B17*$B$5 -> 4802.193 | C18: =C17*$B$5 -> 4970.2698 | D18: =D17*$B$5 -> 5144.2292 | E18: =E17*$B$5 -> 5324.2772 | F18: =F17*$B$5 -> 5510.6269
A19: NOPAT | B19: =B18*(1-$B$6) -> 3745.7105 | C19: =C18*(1-$B$6) -> 3876.8104 | D19: =D18*(1-$B$6) -> 4012.4988 | E19: =E18*(1-$B$6) -> 4152.9362 | F19: =F18*(1-$B$6) -> 4298.289
A20: D&A | B20: =B17*$B$7 -> 816.37281 | C20: =C17*$B$7 -> 844.94586 | D20: =D17*$B$7 -> 874.51896 | E20: =E17*$B$7 -> 905.12713 | F20: =F17*$B$7 -> 936.80658
A21: CapEx | B21: =B17*$B$8 -> 1200.5482 | C21: =C17*$B$8 -> 1242.5674 | D21: =D17*$B$8 -> 1286.0573 | E21: =E17*$B$8 -> 1331.0693 | F21: =F17*$B$8 -> 1377.6567
A22: Delta NWC | B22: =(B17-$B$3)*$B$9 -> 162.393 | C22: =(C17-B17)*$B$9 -> 168.07675 | D22: =(D17-C17)*$B$9 -> 173.95944 | E22: =(E17-D17)*$B$9 -> 180.04802 | F22: =(F17-E17)*$B$9 -> 186.3497
A23: FCFF | B23: =B19+B20-B21-B22 -> 3199.1421 | C23: =C19+C20-C21-C22 -> 3311.1121 | D23: =D19+D20-D21-D22 -> 3427.001 | E23: =E19+E20-E21-E22 -> 3546.946 | F23: =F19+F20-F21-F22 -> 3671.0891
A24: PV FCFF | B24: =B23/(1+$B$10)^1 -> 2908.311 | C24: =C23/(1+$B$10)^2 -> 2736.4563 | D24: =D23/(1+$B$10)^3 -> 2574.7566 | E24: =E23/(1+$B$10)^4 -> 2422.6119 | F24: =F23/(1+$B$10)^5 -> 2279.4575
A27: FCFF year 6 | B27: =F17*(1+$B$11)*($B$5*(1-$B$6)+$B$7-$B$8)-F17*$B$11*$B$9 -> 3824.3751
A28: Terminal value | B28: =B27/($B$10-$B$11) -> 47804.689
A29: PV terminal | B29: =B28/(1+$B$10)^5 -> 29682.95
A30: Enterprise value | B30: =SUM(B24:F24)+B29 -> 42604.544
A31: Equity value | B31: =B30-$B$13 -> 43689.544
A32: Fair value / share | B32: =B31/$B$12 -> 29.500029
A33: 12m model target / share | B33: =(B30*(1+$B$10)-B23-$B$13)/$B$12 -> 30.216648
A34: Terminal share / EV | B34: =B29/B30 -> 0.69670856
A36: Source | B36: https://investors.nike.com/sec-filings/all-sec-filings/content/0000320187-26-000088/nke-20260531.htm
A37: Model anchor FY | B37: 2026-05-31
A38: Do not treat as 02 Nov target | B38: PRELIMINARY
A39: Model check | B39: =IF(AND(B10>B11,B12>0,B27>0),"PASS","FAIL") -> PASS

Sheet SENSITIVITY
A1: MIRROR X · PRELIMINARY · MX-3777d2e495a9
A2: Ticker | B2: WACC / g | C2: -0.01 | D2: -0.005 | E2: 0 | F2: 0.005 | G2: 0.01
A3: ADBE | B3: 0.09 | C3: =((('DCF_ADBE'!$B$3*(1+'DCF_ADBE'!$B$4)^1*('DCF_ADBE'!$B$5*(1-'DCF_ADBE'!$B$6)+'DCF_ADBE'!$B$7-'DCF_ADBE'!$B$8)-'DCF_ADBE'!$B$3*(1+'DCF_ADBE'!$B$4)^0*'DCF_ADBE'!$B$4*'DCF_ADBE'!$B$9)/(1+0.09000000000000001)^1+('DCF_ADBE'!$B$3*(1+'DCF_ADBE'!$B$4)^2*('DCF_ADBE'!$B$5*(1-'DCF_ADBE'!$B$6)+'DCF_ADBE'!$B$7-'DCF_ADBE'!$B$8)-'DCF_ADBE'!$B$3*(1+'DCF_ADBE'!$B$4)^1*'DCF_ADBE'!$B$4*'DCF_ADBE'!$B$9)/(1+0.09000000000000001)^2+('DCF_ADBE'!$B$3*(1+'DCF_ADBE'!$B$4)^3*('DCF_ADBE'!$B$5*(1-'DCF_ADBE'!$B$6)+'DCF_ADBE'!$B$7-'DCF_ADBE'!$B$8)-'DCF_ADBE'!$B$3*(1+'DCF_ADBE'!$B$4)^2*'DCF_ADBE'!$B$4*'DCF_ADBE'!$B$9)/(1+0.09000000000000001)^3+('DCF_ADBE'!$B$3*(1+'DCF_ADBE'!$B$4)^4*('DCF_ADBE'!$B$5*(1-'DCF_ADBE'!$B$6)+'DCF_ADBE'!$B$7-'DCF_ADBE'!$B$8)-'DCF_ADBE'!$B$3*(1+'DCF_ADBE'!$B$4)^3*'DCF_ADBE'!$B$4*'DCF_ADBE'!$B$9)/(1+0.09000000000000001)^4+('DCF_ADBE'!$B$3*(1+'DCF_ADBE'!$B$4)^5*('DCF_ADBE'!$B$5*(1-'DCF_ADBE'!$B$6)+'DCF_ADBE'!$B$7-'DCF_ADBE'!$B$8)-'DCF_ADBE'!$B$3*(1+'DCF_ADBE'!$B$4)^4*'DCF_ADBE'!$B$4*'DCF_ADBE'!$B$9)/(1+0.09000000000000001)^5+('DCF_ADBE'!$B$3*(1+'DCF_ADBE'!$B$4)^5*(1+0.015000000000000001)*('DCF_ADBE'!$B$5*(1-'DCF_ADBE'!$B$6)+'DCF_ADBE'!$B$7-'DCF_ADBE'!$B$8)-'DCF_ADBE'!$B$3*(1+'DCF_ADBE'!$B$4)^5*0.015000000000000001*'DCF_ADBE'!$B$9)/(0.09000000000000001-0.015000000000000001)/(1+0.09000000000000001)^5-'DCF_ADBE'!$B$13)/'DCF_ADBE'!$B$12) -> 266.10433 | D3: =((('DCF_ADBE'!$B$3*(1+'DCF_ADBE'!$B$4)^1*('DCF_ADBE'!$B$5*(1-'DCF_ADBE'!$B$6)+'DCF_ADBE'!$B$7-'DCF_ADBE'!$B$8)-'DCF_ADBE'!$B$3*(1+'DCF_ADBE'!$B$4)^0*'DCF_ADBE'!$B$4*'DCF_ADBE'!$B$9)/(1+0.09000000000000001)^1+('DCF_ADBE'!$B$3*(1+'DCF_ADBE'!$B$4)^2*('DCF_ADBE'!$B$5*(1-'DCF_ADBE'!$B$6)+'DCF_ADBE'!$B$7-'DCF_ADBE'!$B$8)-'DCF_ADBE'!$B$3*(1+'DCF_ADBE'!$B$4)^1*'DCF_ADBE'!$B$4*'DCF_ADBE'!$B$9)/(1+0.09000000000000001)^2+('DCF_ADBE'!$B$3*(1+'DCF_ADBE'!$B$4)^3*('DCF_ADBE'!$B$5*(1-'DCF_ADBE'!$B$6)+'DCF_ADBE'!$B$7-'DCF_ADBE'!$B$8)-'DCF_ADBE'!$B$3*(1+'DCF_ADBE'!$B$4)^2*'DCF_ADBE'!$B$4*'DCF_ADBE'!$B$9)/(1+0.09000000000000001)^3+('DCF_ADBE'!$B$3*(1+'DCF_ADBE'!$B$4)^4*('DCF_ADBE'!$B$5*(1-'DCF_ADBE'!$B$6)+'DCF_ADBE'!$B$7-'DCF_ADBE'!$B$8)-'DCF_ADBE'!$B$3*(1+'DCF_ADBE'!$B$4)^3*'DCF_ADBE'!$B$4*'DCF_ADBE'!$B$9)/(1+0.09000000000000001)^4+('DCF_ADBE'!$B$3*(1+'DCF_ADBE'!$B$4)^5*('DCF_ADBE'!$B$5*(1-'DCF_ADBE'!$B$6)+'DCF_ADBE'!$B$7-'DCF_ADBE'!$B$8)-'DCF_ADBE'!$B$3*(1+'DCF_ADBE'!$B$4)^4*'DCF_ADBE'!$B$4*'DCF_ADBE'!$B$9)/(1+0.09000000000000001)^5+('DCF_ADBE'!$B$3*(1+'DCF_ADBE'!$B$4)^5*(1+0.02)*('DCF_ADBE'!$B$5*(1-'DCF_ADBE'!$B$6)+'DCF_ADBE'!$B$7-'DCF_ADBE'!$B$8)-'DCF_ADBE'!$B$3*(1+'DCF_ADBE'!$B$4)^5*0.02*'DCF_ADBE'!$B$9)/(0.09000000000000001-0.02)/(1+0.09000000000000001)^5-'DCF_ADBE'!$B$13)/'DCF_ADBE'!$B$12) -> 280.72292 | E3: =((('DCF_ADBE'!$B$3*(1+'DCF_ADBE'!$B$4)^1*('DCF_ADBE'!$B$5*(1-'DCF_ADBE'!$B$6)+'DCF_ADBE'!$B$7-'DCF_ADBE'!$B$8)-'DCF_ADBE'!$B$3*(1+'DCF_ADBE'!$B$4)^0*'DCF_ADBE'!$B$4*'DCF_ADBE'!$B$9)/(1+0.09000000000000001)^1+('DCF_ADBE'!$B$3*(1+'DCF_ADBE'!$B$4)^2*('DCF_ADBE'!$B$5*(1-'DCF_ADBE'!$B$6)+'DCF_ADBE'!$B$7-'DCF_ADBE'!$B$8)-'DCF_ADBE'!$B$3*(1+'DCF_ADBE'!$B$4)^1*'DCF_ADBE'!$B$4*'DCF_ADBE'!$B$9)/(1+0.09000000000000001)^2+('DCF_ADBE'!$B$3*(1+'DCF_ADBE'!$B$4)^3*('DCF_ADBE'!$B$5*(1-'DCF_ADBE'!$B$6)+'DCF_ADBE'!$B$7-'DCF_ADBE'!$B$8)-'DCF_ADBE'!$B$3*(1+'DCF_ADBE'!$B$4)^2*'DCF_ADBE'!$B$4*'DCF_ADBE'!$B$9)/(1+0.09000000000000001)^3+('DCF_ADBE'!$B$3*(1+'DCF_ADBE'!$B$4)^4*('DCF_ADBE'!$B$5*(1-'DCF_ADBE'!$B$6)+'DCF_ADBE'!$B$7-'DCF_ADBE'!$B$8)-'DCF_ADBE'!$B$3*(1+'DCF_ADBE'!$B$4)^3*'DCF_ADBE'!$B$4*'DCF_ADBE'!$B$9)/(1+0.09000000000000001)^4+('DCF_ADBE'!$B$3*(1+'DCF_ADBE'!$B$4)^5*('DCF_ADBE'!$B$5*(1-'DCF_ADBE'!$B$6)+'DCF_ADBE'!$B$7-'DCF_ADBE'!$B$8)-'DCF_ADBE'!$B$3*(1+'DCF_ADBE'!$B$4)^4*'DCF_ADBE'!$B$4*'DCF_ADBE'!$B$9)/(1+0.09000000000000001)^5+('DCF_ADBE'!$B$3*(1+'DCF_ADBE'!$B$4)^5*(1+0.025)*('DCF_ADBE'!$B$5*(1-'DCF_ADBE'!$B$6)+'DCF_ADBE'!$B$7-'DCF_ADBE'!$B$8)-'DCF_ADBE'!$B$3*(1+'DCF_ADBE'!$B$4)^5*0.025*'DCF_ADBE'!$B$9)/(0.09000000000000001-0.025)/(1+0.09000000000000001)^5-'DCF_ADBE'!$B$13)/'DCF_ADBE'!$B$12) -> 297.59053 | F3: =((('DCF_ADBE'!$B$3*(1+'DCF_ADBE'!$B$4)^1*('DCF_ADBE'!$B$5*(1-'DCF_ADBE'!$B$6)+'DCF_ADBE'!$B$7-'DCF_ADBE'!$B$8)-'DCF_ADBE'!$B$3*(1+'DCF_ADBE'!$B$4)^0*'DCF_ADBE'!$B$4*'DCF_ADBE'!$B$9)/(1+0.09000000000000001)^1+('DCF_ADBE'!$B$3*(1+'DCF_ADBE'!$B$4)^2*('DCF_ADBE'!$B$5*(1-'DCF_ADBE'!$B$6)+'DCF_ADBE'!$B$7-'DCF_ADBE'!$B$8)-'DCF_ADBE'!$B$3*(1+'DCF_ADBE'!$B$4)^1*'DCF_ADBE'!$B$4*'DCF_ADBE'!$B$9)/(1+0.09000000000000001)^2+('DCF_ADBE'!$B$3*(1+'DCF_ADBE'!$B$4)^3*('DCF_ADBE'!$B$5*(1-'DCF_ADBE'!$B$6)+'DCF_ADBE'!$B$7-'DCF_ADBE'!$B$8)-'DCF_ADBE'!$B$3*(1+'DCF_ADBE'!$B$4)^2*'DCF_ADBE'!$B$4*'DCF_ADBE'!$B$9)/(1+0.09000000000000001)^3+('DCF_ADBE'!$B$3*(1+'DCF_ADBE'!$B$4)^4*('DCF_ADBE'!$B$5*(1-'DCF_ADBE'!$B$6)+'DCF_ADBE'!$B$7-'DCF_ADBE'!$B$8)-'DCF_ADBE'!$B$3*(1+'DCF_ADBE'!$B$4)^3*'DCF_ADBE'!$B$4*'DCF_ADBE'!$B$9)/(1+0.09000000000000001)^4+('DCF_ADBE'!$B$3*(1+'DCF_ADBE'!$B$4)^5*('DCF_ADBE'!$B$5*(1-'DCF_ADBE'!$B$6)+'DCF_ADBE'!$B$7-'DCF_ADBE'!$B$8)-'DCF_ADBE'!$B$3*(1+'DCF_ADBE'!$B$4)^4*'DCF_ADBE'!$B$4*'DCF_ADBE'!$B$9)/(1+0.09000000000000001)^5+('DCF_ADBE'!$B$3*(1+'DCF_ADBE'!$B$4)^5*(1+0.030000000000000002)*('DCF_ADBE'!$B$5*(1-'DCF_ADBE'!$B$6)+'DCF_ADBE'!$B$7-'DCF_ADBE'!$B$8)-'DCF_ADBE'!$B$3*(1+'DCF_ADBE'!$B$4)^5*0.030000000000000002*'DCF_ADBE'!$B$9)/(0.09000000000000001-0.030000000000000002)/(1+0.09000000000000001)^5-'DCF_ADBE'!$B$13)/'DCF_ADBE'!$B$12) -> 317.2694 | G3: =((('DCF_ADBE'!$B$3*(1+'DCF_ADBE'!$B$4)^1*('DCF_ADBE'!$B$5*(1-'DCF_ADBE'!$B$6)+'DCF_ADBE'!$B$7-'DCF_ADBE'!$B$8)-'DCF_ADBE'!$B$3*(1+'DCF_ADBE'!$B$4)^0*'DCF_ADBE'!$B$4*'DCF_ADBE'!$B$9)/(1+0.09000000000000001)^1+('DCF_ADBE'!$B$3*(1+'DCF_ADBE'!$B$4)^2*('DCF_ADBE'!$B$5*(1-'DCF_ADBE'!$B$6)+'DCF_ADBE'!$B$7-'DCF_ADBE'!$B$8)-'DCF_ADBE'!$B$3*(1+'DCF_ADBE'!$B$4)^1*'DCF_ADBE'!$B$4*'DCF_ADBE'!$B$9)/(1+0.09000000000000001)^2+('DCF_ADBE'!$B$3*(1+'DCF_ADBE'!$B$4)^3*('DCF_ADBE'!$B$5*(1-'DCF_ADBE'!$B$6)+'DCF_ADBE'!$B$7-'DCF_ADBE'!$B$8)-'DCF_ADBE'!$B$3*(1+'DCF_ADBE'!$B$4)^2*'DCF_ADBE'!$B$4*'DCF_ADBE'!$B$9)/(1+0.09000000000000001)^3+('DCF_ADBE'!$B$3*(1+'DCF_ADBE'!$B$4)^4*('DCF_ADBE'!$B$5*(1-'DCF_ADBE'!$B$6)+'DCF_ADBE'!$B$7-'DCF_ADBE'!$B$8)-'DCF_ADBE'!$B$3*(1+'DCF_ADBE'!$B$4)^3*'DCF_ADBE'!$B$4*'DCF_ADBE'!$B$9)/(1+0.09000000000000001)^4+('DCF_ADBE'!$B$3*(1+'DCF_ADBE'!$B$4)^5*('DCF_ADBE'!$B$5*(1-'DCF_ADBE'!$B$6)+'DCF_ADBE'!$B$7-'DCF_ADBE'!$B$8)-'DCF_ADBE'!$B$3*(1+'DCF_ADBE'!$B$4)^4*'DCF_ADBE'!$B$4*'DCF_ADBE'!$B$9)/(1+0.09000000000000001)^5+('DCF_ADBE'!$B$3*(1+'DCF_ADBE'!$B$4)^5*(1+0.035)*('DCF_ADBE'!$B$5*(1-'DCF_ADBE'!$B$6)+'DCF_ADBE'!$B$7-'DCF_ADBE'!$B$8)-'DCF_ADBE'!$B$3*(1+'DCF_ADBE'!$B$4)^5*0.035*'DCF_ADBE'!$B$9)/(0.09000000000000001-0.035)/(1+0.09000000000000001)^5-'DCF_ADBE'!$B$13)/'DCF_ADBE'!$B$12) -> 340.52625
A4: ADBE | B4: 0.095 | C4: =((('DCF_ADBE'!$B$3*(1+'DCF_ADBE'!$B$4)^1*('DCF_ADBE'!$B$5*(1-'DCF_ADBE'!$B$6)+'DCF_ADBE'!$B$7-'DCF_ADBE'!$B$8)-'DCF_ADBE'!$B$3*(1+'DCF_ADBE'!$B$4)^0*'DCF_ADBE'!$B$4*'DCF_ADBE'!$B$9)/(1+0.095)^1+('DCF_ADBE'!$B$3*(1+'DCF_ADBE'!$B$4)^2*('DCF_ADBE'!$B$5*(1-'DCF_ADBE'!$B$6)+'DCF_ADBE'!$B$7-'DCF_ADBE'!$B$8)-'DCF_ADBE'!$B$3*(1+'DCF_ADBE'!$B$4)^1*'DCF_ADBE'!$B$4*'DCF_ADBE'!$B$9)/(1+0.095)^2+('DCF_ADBE'!$B$3*(1+'DCF_ADBE'!$B$4)^3*('DCF_ADBE'!$B$5*(1-'DCF_ADBE'!$B$6)+'DCF_ADBE'!$B$7-'DCF_ADBE'!$B$8)-'DCF_ADBE'!$B$3*(1+'DCF_ADBE'!$B$4)^2*'DCF_ADBE'!$B$4*'DCF_ADBE'!$B$9)/(1+0.095)^3+('DCF_ADBE'!$B$3*(1+'DCF_ADBE'!$B$4)^4*('DCF_ADBE'!$B$5*(1-'DCF_ADBE'!$B$6)+'DCF_ADBE'!$B$7-'DCF_ADBE'!$B$8)-'DCF_ADBE'!$B$3*(1+'DCF_ADBE'!$B$4)^3*'DCF_ADBE'!$B$4*'DCF_ADBE'!$B$9)/(1+0.095)^4+('DCF_ADBE'!$B$3*(1+'DCF_ADBE'!$B$4)^5*('DCF_ADBE'!$B$5*(1-'DCF_ADBE'!$B$6)+'DCF_ADBE'!$B$7-'DCF_ADBE'!$B$8)-'DCF_ADBE'!$B$3*(1+'DCF_ADBE'!$B$4)^4*'DCF_ADBE'!$B$4*'DCF_ADBE'!$B$9)/(1+0.095)^5+('DCF_ADBE'!$B$3*(1+'DCF_ADBE'!$B$4)^5*(1+0.015000000000000001)*('DCF_ADBE'!$B$5*(1-'DCF_ADBE'!$B$6)+'DCF_ADBE'!$B$7-'DCF_ADBE'!$B$8)-'DCF_ADBE'!$B$3*(1+'DCF_ADBE'!$B$4)^5*0.015000000000000001*'DCF_ADBE'!$B$9)/(0.095-0.015000000000000001)/(1+0.095)^5-'DCF_ADBE'!$B$13)/'DCF_ADBE'!$B$12) -> 249.04942 | D4: =((('DCF_ADBE'!$B$3*(1+'DCF_ADBE'!$B$4)^1*('DCF_ADBE'!$B$5*(1-'DCF_ADBE'!$B$6)+'DCF_ADBE'!$B$7-'DCF_ADBE'!$B$8)-'DCF_ADBE'!$B$3*(1+'DCF_ADBE'!$B$4)^0*'DCF_ADBE'!$B$4*'DCF_ADBE'!$B$9)/(1+0.095)^1+('DCF_ADBE'!$B$3*(1+'DCF_ADBE'!$B$4)^2*('DCF_ADBE'!$B$5*(1-'DCF_ADBE'!$B$6)+'DCF_ADBE'!$B$7-'DCF_ADBE'!$B$8)-'DCF_ADBE'!$B$3*(1+'DCF_ADBE'!$B$4)^1*'DCF_ADBE'!$B$4*'DCF_ADBE'!$B$9)/(1+0.095)^2+('DCF_ADBE'!$B$3*(1+'DCF_ADBE'!$B$4)^3*('DCF_ADBE'!$B$5*(1-'DCF_ADBE'!$B$6)+'DCF_ADBE'!$B$7-'DCF_ADBE'!$B$8)-'DCF_ADBE'!$B$3*(1+'DCF_ADBE'!$B$4)^2*'DCF_ADBE'!$B$4*'DCF_ADBE'!$B$9)/(1+0.095)^3+('DCF_ADBE'!$B$3*(1+'DCF_ADBE'!$B$4)^4*('DCF_ADBE'!$B$5*(1-'DCF_ADBE'!$B$6)+'DCF_ADBE'!$B$7-'DCF_ADBE'!$B$8)-'DCF_ADBE'!$B$3*(1+'DCF_ADBE'!$B$4)^3*'DCF_ADBE'!$B$4*'DCF_ADBE'!$B$9)/(1+0.095)^4+('DCF_ADBE'!$B$3*(1+'DCF_ADBE'!$B$4)^5*('DCF_ADBE'!$B$5*(1-'DCF_ADBE'!$B$6)+'DCF_ADBE'!$B$7-'DCF_ADBE'!$B$8)-'DCF_ADBE'!$B$3*(1+'DCF_ADBE'!$B$4)^4*'DCF_ADBE'!$B$4*'DCF_ADBE'!$B$9)/(1+0.095)^5+('DCF_ADBE'!$B$3*(1+'DCF_ADBE'!$B$4)^5*(1+0.02)*('DCF_ADBE'!$B$5*(1-'DCF_ADBE'!$B$6)+'DCF_ADBE'!$B$7-'DCF_ADBE'!$B$8)-'DCF_ADBE'!$B$3*(1+'DCF_ADBE'!$B$4)^5*0.02*'DCF_ADBE'!$B$9)/(0.095-0.02)/(1+0.095)^5-'DCF_ADBE'!$B$13)/'DCF_ADBE'!$B$12) -> 261.60297 | E4: =((('DCF_ADBE'!$B$3*(1+'DCF_ADBE'!$B$4)^1*('DCF_ADBE'!$B$5*(1-'DCF_ADBE'!$B$6)+'DCF_ADBE'!$B$7-'DCF_ADBE'!$B$8)-'DCF_ADBE'!$B$3*(1+'DCF_ADBE'!$B$4)^0*'DCF_ADBE'!$B$4*'DCF_ADBE'!$B$9)/(1+0.095)^1+('DCF_ADBE'!$B$3*(1+'DCF_ADBE'!$B$4)^2*('DCF_ADBE'!$B$5*(1-'DCF_ADBE'!$B$6)+'DCF_ADBE'!$B$7-'DCF_ADBE'!$B$8)-'DCF_ADBE'!$B$3*(1+'DCF_ADBE'!$B$4)^1*'DCF_ADBE'!$B$4*'DCF_ADBE'!$B$9)/(1+0.095)^2+('DCF_ADBE'!$B$3*(1+'DCF_ADBE'!$B$4)^3*('DCF_ADBE'!$B$5*(1-'DCF_ADBE'!$B$6)+'DCF_ADBE'!$B$7-'DCF_ADBE'!$B$8)-'DCF_ADBE'!$B$3*(1+'DCF_ADBE'!$B$4)^2*'DCF_ADBE'!$B$4*'DCF_ADBE'!$B$9)/(1+0.095)^3+('DCF_ADBE'!$B$3*(1+'DCF_ADBE'!$B$4)^4*('DCF_ADBE'!$B$5*(1-'DCF_ADBE'!$B$6)+'DCF_ADBE'!$B$7-'DCF_ADBE'!$B$8)-'DCF_ADBE'!$B$3*(1+'DCF_ADBE'!$B$4)^3*'DCF_ADBE'!$B$4*'DCF_ADBE'!$B$9)/(1+0.095)^4+('DCF_ADBE'!$B$3*(1+'DCF_ADBE'!$B$4)^5*('DCF_ADBE'!$B$5*(1-'DCF_ADBE'!$B$6)+'DCF_ADBE'!$B$7-'DCF_ADBE'!$B$8)-'DCF_ADBE'!$B$3*(1+'DCF_ADBE'!$B$4)^4*'DCF_ADBE'!$B$4*'DCF_ADBE'!$B$9)/(1+0.095)^5+('DCF_ADBE'!$B$3*(1+'DCF_ADBE'!$B$4)^5*(1+0.025)*('DCF_ADBE'!$B$5*(1-'DCF_ADBE'!$B$6)+'DCF_ADBE'!$B$7-'DCF_ADBE'!$B$8)-'DCF_ADBE'!$B$3*(1+'DCF_ADBE'!$B$4)^5*0.025*'DCF_ADBE'!$B$9)/(0.095-0.025)/(1+0.095)^5-'DCF_ADBE'!$B$13)/'DCF_ADBE'!$B$12) -> 275.94988 | F4: =((('DCF_ADBE'!$B$3*(1+'DCF_ADBE'!$B$4)^1*('DCF_ADBE'!$B$5*(1-'DCF_ADBE'!$B$6)+'DCF_ADBE'!$B$7-'DCF_ADBE'!$B$8)-'DCF_ADBE'!$B$3*(1+'DCF_ADBE'!$B$4)^0*'DCF_ADBE'!$B$4*'DCF_ADBE'!$B$9)/(1+0.095)^1+('DCF_ADBE'!$B$3*(1+'DCF_ADBE'!$B$4)^2*('DCF_ADBE'!$B$5*(1-'DCF_ADBE'!$B$6)+'DCF_ADBE'!$B$7-'DCF_ADBE'!$B$8)-'DCF_ADBE'!$B$3*(1+'DCF_ADBE'!$B$4)^1*'DCF_ADBE'!$B$4*'DCF_ADBE'!$B$9)/(1+0.095)^2+('DCF_ADBE'!$B$3*(1+'DCF_ADBE'!$B$4)^3*('DCF_ADBE'!$B$5*(1-'DCF_ADBE'!$B$6)+'DCF_ADBE'!$B$7-'DCF_ADBE'!$B$8)-'DCF_ADBE'!$B$3*(1+'DCF_ADBE'!$B$4)^2*'DCF_ADBE'!$B$4*'DCF_ADBE'!$B$9)/(1+0.095)^3+('DCF_ADBE'!$B$3*(1+'DCF_ADBE'!$B$4)^4*('DCF_ADBE'!$B$5*(1-'DCF_ADBE'!$B$6)+'DCF_ADBE'!$B$7-'DCF_ADBE'!$B$8)-'DCF_ADBE'!$B$3*(1+'DCF_ADBE'!$B$4)^3*'DCF_ADBE'!$B$4*'DCF_ADBE'!$B$9)/(1+0.095)^4+('DCF_ADBE'!$B$3*(1+'DCF_ADBE'!$B$4)^5*('DCF_ADBE'!$B$5*(1-'DCF_ADBE'!$B$6)+'DCF_ADBE'!$B$7-'DCF_ADBE'!$B$8)-'DCF_ADBE'!$B$3*(1+'DCF_ADBE'!$B$4)^4*'DCF_ADBE'!$B$4*'DCF_ADBE'!$B$9)/(1+0.095)^5+('DCF_ADBE'!$B$3*(1+'DCF_ADBE'!$B$4)^5*(1+0.030000000000000002)*('DCF_ADBE'!$B$5*(1-'DCF_ADBE'!$B$6)+'DCF_ADBE'!$B$7-'DCF_ADBE'!$B$8)-'DCF_ADBE'!$B$3*(1+'DCF_ADBE'!$B$4)^5*0.030000000000000002*'DCF_ADBE'!$B$9)/(0.095-0.030000000000000002)/(1+0.095)^5-'DCF_ADBE'!$B$13)/'DCF_ADBE'!$B$12) -> 292.504 | G4: =((('DCF_ADBE'!$B$3*(1+'DCF_ADBE'!$B$4)^1*('DCF_ADBE'!$B$5*(1-'DCF_ADBE'!$B$6)+'DCF_ADBE'!$B$7-'DCF_ADBE'!$B$8)-'DCF_ADBE'!$B$3*(1+'DCF_ADBE'!$B$4)^0*'DCF_ADBE'!$B$4*'DCF_ADBE'!$B$9)/(1+0.095)^1+('DCF_ADBE'!$B$3*(1+'DCF_ADBE'!$B$4)^2*('DCF_ADBE'!$B$5*(1-'DCF_ADBE'!$B$6)+'DCF_ADBE'!$B$7-'DCF_ADBE'!$B$8)-'DCF_ADBE'!$B$3*(1+'DCF_ADBE'!$B$4)^1*'DCF_ADBE'!$B$4*'DCF_ADBE'!$B$9)/(1+0.095)^2+('DCF_ADBE'!$B$3*(1+'DCF_ADBE'!$B$4)^3*('DCF_ADBE'!$B$5*(1-'DCF_ADBE'!$B$6)+'DCF_ADBE'!$B$7-'DCF_ADBE'!$B$8)-'DCF_ADBE'!$B$3*(1+'DCF_ADBE'!$B$4)^2*'DCF_ADBE'!$B$4*'DCF_ADBE'!$B$9)/(1+0.095)^3+('DCF_ADBE'!$B$3*(1+'DCF_ADBE'!$B$4)^4*('DCF_ADBE'!$B$5*(1-'DCF_ADBE'!$B$6)+'DCF_ADBE'!$B$7-'DCF_ADBE'!$B$8)-'DCF_ADBE'!$B$3*(1+'DCF_ADBE'!$B$4)^3*'DCF_ADBE'!$B$4*'DCF_ADBE'!$B$9)/(1+0.095)^4+('DCF_ADBE'!$B$3*(1+'DCF_ADBE'!$B$4)^5*('DCF_ADBE'!$B$5*(1-'DCF_ADBE'!$B$6)+'DCF_ADBE'!$B$7-'DCF_ADBE'!$B$8)-'DCF_ADBE'!$B$3*(1+'DCF_ADBE'!$B$4)^4*'DCF_ADBE'!$B$4*'DCF_ADBE'!$B$9)/(1+0.095)^5+('DCF_ADBE'!$B$3*(1+'DCF_ADBE'!$B$4)^5*(1+0.035)*('DCF_ADBE'!$B$5*(1-'DCF_ADBE'!$B$6)+'DCF_ADBE'!$B$7-'DCF_ADBE'!$B$8)-'DCF_ADBE'!$B$3*(1+'DCF_ADBE'!$B$4)^5*0.035*'DCF_ADBE'!$B$9)/(0.095-0.035)/(1+0.095)^5-'DCF_ADBE'!$B$13)/'DCF_ADBE'!$B$12) -> 311.81715
A5: ADBE | B5: 0.1 | C5: =((('DCF_ADBE'!$B$3*(1+'DCF_ADBE'!$B$4)^1*('DCF_ADBE'!$B$5*(1-'DCF_ADBE'!$B$6)+'DCF_ADBE'!$B$7-'DCF_ADBE'!$B$8)-'DCF_ADBE'!$B$3*(1+'DCF_ADBE'!$B$4)^0*'DCF_ADBE'!$B$4*'DCF_ADBE'!$B$9)/(1+0.1)^1+('DCF_ADBE'!$B$3*(1+'DCF_ADBE'!$B$4)^2*('DCF_ADBE'!$B$5*(1-'DCF_ADBE'!$B$6)+'DCF_ADBE'!$B$7-'DCF_ADBE'!$B$8)-'DCF_ADBE'!$B$3*(1+'DCF_ADBE'!$B$4)^1*'DCF_ADBE'!$B$4*'DCF_ADBE'!$B$9)/(1+0.1)^2+('DCF_ADBE'!$B$3*(1+'DCF_ADBE'!$B$4)^3*('DCF_ADBE'!$B$5*(1-'DCF_ADBE'!$B$6)+'DCF_ADBE'!$B$7-'DCF_ADBE'!$B$8)-'DCF_ADBE'!$B$3*(1+'DCF_ADBE'!$B$4)^2*'DCF_ADBE'!$B$4*'DCF_ADBE'!$B$9)/(1+0.1)^3+('DCF_ADBE'!$B$3*(1+'DCF_ADBE'!$B$4)^4*('DCF_ADBE'!$B$5*(1-'DCF_ADBE'!$B$6)+'DCF_ADBE'!$B$7-'DCF_ADBE'!$B$8)-'DCF_ADBE'!$B$3*(1+'DCF_ADBE'!$B$4)^3*'DCF_ADBE'!$B$4*'DCF_ADBE'!$B$9)/(1+0.1)^4+('DCF_ADBE'!$B$3*(1+'DCF_ADBE'!$B$4)^5*('DCF_ADBE'!$B$5*(1-'DCF_ADBE'!$B$6)+'DCF_ADBE'!$B$7-'DCF_ADBE'!$B$8)-'DCF_ADBE'!$B$3*(1+'DCF_ADBE'!$B$4)^4*'DCF_ADBE'!$B$4*'DCF_ADBE'!$B$9)/(1+0.1)^5+('DCF_ADBE'!$B$3*(1+'DCF_ADBE'!$B$4)^5*(1+0.015000000000000001)*('DCF_ADBE'!$B$5*(1-'DCF_ADBE'!$B$6)+'DCF_ADBE'!$B$7-'DCF_ADBE'!$B$8)-'DCF_ADBE'!$B$3*(1+'DCF_ADBE'!$B$4)^5*0.015000000000000001*'DCF_ADBE'!$B$9)/(0.1-0.015000000000000001)/(1+0.1)^5-'DCF_ADBE'!$B$13)/'DCF_ADBE'!$B$12) -> 234.00929 | D5: =((('DCF_ADBE'!$B$3*(1+'DCF_ADBE'!$B$4)^1*('DCF_ADBE'!$B$5*(1-'DCF_ADBE'!$B$6)+'DCF_ADBE'!$B$7-'DCF_ADBE'!$B$8)-'DCF_ADBE'!$B$3*(1+'DCF_ADBE'!$B$4)^0*'DCF_ADBE'!$B$4*'DCF_ADBE'!$B$9)/(1+0.1)^1+('DCF_ADBE'!$B$3*(1+'DCF_ADBE'!$B$4)^2*('DCF_ADBE'!$B$5*(1-'DCF_ADBE'!$B$6)+'DCF_ADBE'!$B$7-'DCF_ADBE'!$B$8)-'DCF_ADBE'!$B$3*(1+'DCF_ADBE'!$B$4)^1*'DCF_ADBE'!$B$4*'DCF_ADBE'!$B$9)/(1+0.1)^2+('DCF_ADBE'!$B$3*(1+'DCF_ADBE'!$B$4)^3*('DCF_ADBE'!$B$5*(1-'DCF_ADBE'!$B$6)+'DCF_ADBE'!$B$7-'DCF_ADBE'!$B$8)-'DCF_ADBE'!$B$3*(1+'DCF_ADBE'!$B$4)^2*'DCF_ADBE'!$B$4*'DCF_ADBE'!$B$9)/(1+0.1)^3+('DCF_ADBE'!$B$3*(1+'DCF_ADBE'!$B$4)^4*('DCF_ADBE'!$B$5*(1-'DCF_ADBE'!$B$6)+'DCF_ADBE'!$B$7-'DCF_ADBE'!$B$8)-'DCF_ADBE'!$B$3*(1+'DCF_ADBE'!$B$4)^3*'DCF_ADBE'!$B$4*'DCF_ADBE'!$B$9)/(1+0.1)^4+('DCF_ADBE'!$B$3*(1+'DCF_ADBE'!$B$4)^5*('DCF_ADBE'!$B$5*(1-'DCF_ADBE'!$B$6)+'DCF_ADBE'!$B$7-'DCF_ADBE'!$B$8)-'DCF_ADBE'!$B$3*(1+'DCF_ADBE'!$B$4)^4*'DCF_ADBE'!$B$4*'DCF_ADBE'!$B$9)/(1+0.1)^5+('DCF_ADBE'!$B$3*(1+'DCF_ADBE'!$B$4)^5*(1+0.02)*('DCF_ADBE'!$B$5*(1-'DCF_ADBE'!$B$6)+'DCF_ADBE'!$B$7-'DCF_ADBE'!$B$8)-'DCF_ADBE'!$B$3*(1+'DCF_ADBE'!$B$4)^5*0.02*'DCF_ADBE'!$B$9)/(0.1-0.02)/(1+0.1)^5-'DCF_ADBE'!$B$13)/'DCF_ADBE'!$B$12) -> 244.88104 | E5: =((('DCF_ADBE'!$B$3*(1+'DCF_ADBE'!$B$4)^1*('DCF_ADBE'!$B$5*(1-'DCF_ADBE'!$B$6)+'DCF_ADBE'!$B$7-'DCF_ADBE'!$B$8)-'DCF_ADBE'!$B$3*(1+'DCF_ADBE'!$B$4)^0*'DCF_ADBE'!$B$4*'DCF_ADBE'!$B$9)/(1+0.1)^1+('DCF_ADBE'!$B$3*(1+'DCF_ADBE'!$B$4)^2*('DCF_ADBE'!$B$5*(1-'DCF_ADBE'!$B$6)+'DCF_ADBE'!$B$7-'DCF_ADBE'!$B$8)-'DCF_ADBE'!$B$3*(1+'DCF_ADBE'!$B$4)^1*'DCF_ADBE'!$B$4*'DCF_ADBE'!$B$9)/(1+0.1)^2+('DCF_ADBE'!$B$3*(1+'DCF_ADBE'!$B$4)^3*('DCF_ADBE'!$B$5*(1-'DCF_ADBE'!$B$6)+'DCF_ADBE'!$B$7-'DCF_ADBE'!$B$8)-'DCF_ADBE'!$B$3*(1+'DCF_ADBE'!$B$4)^2*'DCF_ADBE'!$B$4*'DCF_ADBE'!$B$9)/(1+0.1)^3+('DCF_ADBE'!$B$3*(1+'DCF_ADBE'!$B$4)^4*('DCF_ADBE'!$B$5*(1-'DCF_ADBE'!$B$6)+'DCF_ADBE'!$B$7-'DCF_ADBE'!$B$8)-'DCF_ADBE'!$B$3*(1+'DCF_ADBE'!$B$4)^3*'DCF_ADBE'!$B$4*'DCF_ADBE'!$B$9)/(1+0.1)^4+('DCF_ADBE'!$B$3*(1+'DCF_ADBE'!$B$4)^5*('DCF_ADBE'!$B$5*(1-'DCF_ADBE'!$B$6)+'DCF_ADBE'!$B$7-'DCF_ADBE'!$B$8)-'DCF_ADBE'!$B$3*(1+'DCF_ADBE'!$B$4)^4*'DCF_ADBE'!$B$4*'DCF_ADBE'!$B$9)/(1+0.1)^5+('DCF_ADBE'!$B$3*(1+'DCF_ADBE'!$B$4)^5*(1+0.025)*('DCF_ADBE'!$B$5*(1-'DCF_ADBE'!$B$6)+'DCF_ADBE'!$B$7-'DCF_ADBE'!$B$8)-'DCF_ADBE'!$B$3*(1+'DCF_ADBE'!$B$4)^5*0.025*'DCF_ADBE'!$B$9)/(0.1-0.025)/(1+0.1)^5-'DCF_ADBE'!$B$13)/'DCF_ADBE'!$B$12) -> 257.20235 | F5: =((('DCF_ADBE'!$B$3*(1+'DCF_ADBE'!$B$4)^1*('DCF_ADBE'!$B$5*(1-'DCF_ADBE'!$B$6)+'DCF_ADBE'!$B$7-'DCF_ADBE'!$B$8)-'DCF_ADBE'!$B$3*(1+'DCF_ADBE'!$B$4)^0*'DCF_ADBE'!$B$4*'DCF_ADBE'!$B$9)/(1+0.1)^1+('DCF_ADBE'!$B$3*(1+'DCF_ADBE'!$B$4)^2*('DCF_ADBE'!$B$5*(1-'DCF_ADBE'!$B$6)+'DCF_ADBE'!$B$7-'DCF_ADBE'!$B$8)-'DCF_ADBE'!$B$3*(1+'DCF_ADBE'!$B$4)^1*'DCF_ADBE'!$B$4*'DCF_ADBE'!$B$9)/(1+0.1)^2+('DCF_ADBE'!$B$3*(1+'DCF_ADBE'!$B$4)^3*('DCF_ADBE'!$B$5*(1-'DCF_ADBE'!$B$6)+'DCF_ADBE'!$B$7-'DCF_ADBE'!$B$8)-'DCF_ADBE'!$B$3*(1+'DCF_ADBE'!$B$4)^2*'DCF_ADBE'!$B$4*'DCF_ADBE'!$B$9)/(1+0.1)^3+('DCF_ADBE'!$B$3*(1+'DCF_ADBE'!$B$4)^4*('DCF_ADBE'!$B$5*(1-'DCF_ADBE'!$B$6)+'DCF_ADBE'!$B$7-'DCF_ADBE'!$B$8)-'DCF_ADBE'!$B$3*(1+'DCF_ADBE'!$B$4)^3*'DCF_ADBE'!$B$4*'DCF_ADBE'!$B$9)/(1+0.1)^4+('DCF_ADBE'!$B$3*(1+'DCF_ADBE'!$B$4)^5*('DCF_ADBE'!$B$5*(1-'DCF_ADBE'!$B$6)+'DCF_ADBE'!$B$7-'DCF_ADBE'!$B$8)-'DCF_ADBE'!$B$3*(1+'DCF_ADBE'!$B$4)^4*'DCF_ADBE'!$B$4*'DCF_ADBE'!$B$9)/(1+0.1)^5+('DCF_ADBE'!$B$3*(1+'DCF_ADBE'!$B$4)^5*(1+0.030000000000000002)*('DCF_ADBE'!$B$5*(1-'DCF_ADBE'!$B$6)+'DCF_ADBE'!$B$7-'DCF_ADBE'!$B$8)-'DCF_ADBE'!$B$3*(1+'DCF_ADBE'!$B$4)^5*0.030000000000000002*'DCF_ADBE'!$B$9)/(0.1-0.030000000000000002)/(1+0.1)^5-'DCF_ADBE'!$B$13)/'DCF_ADBE'!$B$12) -> 271.28386 | G5: =((('DCF_ADBE'!$B$3*(1+'DCF_ADBE'!$B$4)^1*('DCF_ADBE'!$B$5*(1-'DCF_ADBE'!$B$6)+'DCF_ADBE'!$B$7-'DCF_ADBE'!$B$8)-'DCF_ADBE'!$B$3*(1+'DCF_ADBE'!$B$4)^0*'DCF_ADBE'!$B$4*'DCF_ADBE'!$B$9)/(1+0.1)^1+('DCF_ADBE'!$B$3*(1+'DCF_ADBE'!$B$4)^2*('DCF_ADBE'!$B$5*(1-'DCF_ADBE'!$B$6)+'DCF_ADBE'!$B$7-'DCF_ADBE'!$B$8)-'DCF_ADBE'!$B$3*(1+'DCF_ADBE'!$B$4)^1*'DCF_ADBE'!$B$4*'DCF_ADBE'!$B$9)/(1+0.1)^2+('DCF_ADBE'!$B$3*(1+'DCF_ADBE'!$B$4)^3*('DCF_ADBE'!$B$5*(1-'DCF_ADBE'!$B$6)+'DCF_ADBE'!$B$7-'DCF_ADBE'!$B$8)-'DCF_ADBE'!$B$3*(1+'DCF_ADBE'!$B$4)^2*'DCF_ADBE'!$B$4*'DCF_ADBE'!$B$9)/(1+0.1)^3+('DCF_ADBE'!$B$3*(1+'DCF_ADBE'!$B$4)^4*('DCF_ADBE'!$B$5*(1-'DCF_ADBE'!$B$6)+'DCF_ADBE'!$B$7-'DCF_ADBE'!$B$8)-'DCF_ADBE'!$B$3*(1+'DCF_ADBE'!$B$4)^3*'DCF_ADBE'!$B$4*'DCF_ADBE'!$B$9)/(1+0.1)^4+('DCF_ADBE'!$B$3*(1+'DCF_ADBE'!$B$4)^5*('DCF_ADBE'!$B$5*(1-'DCF_ADBE'!$B$6)+'DCF_ADBE'!$B$7-'DCF_ADBE'!$B$8)-'DCF_ADBE'!$B$3*(1+'DCF_ADBE'!$B$4)^4*'DCF_ADBE'!$B$4*'DCF_ADBE'!$B$9)/(1+0.1)^5+('DCF_ADBE'!$B$3*(1+'DCF_ADBE'!$B$4)^5*(1+0.035)*('DCF_ADBE'!$B$5*(1-'DCF_ADBE'!$B$6)+'DCF_ADBE'!$B$7-'DCF_ADBE'!$B$8)-'DCF_ADBE'!$B$3*(1+'DCF_ADBE'!$B$4)^5*0.035*'DCF_ADBE'!$B$9)/(0.1-0.035)/(1+0.1)^5-'DCF_ADBE'!$B$13)/'DCF_ADBE'!$B$12) -> 287.53175
A6: ADBE | B6: 0.105 | C6: =((('DCF_ADBE'!$B$3*(1+'DCF_ADBE'!$B$4)^1*('DCF_ADBE'!$B$5*(1-'DCF_ADBE'!$B$6)+'DCF_ADBE'!$B$7-'DCF_ADBE'!$B$8)-'DCF_ADBE'!$B$3*(1+'DCF_ADBE'!$B$4)^0*'DCF_ADBE'!$B$4*'DCF_ADBE'!$B$9)/(1+0.10500000000000001)^1+('DCF_ADBE'!$B$3*(1+'DCF_ADBE'!$B$4)^2*('DCF_ADBE'!$B$5*(1-'DCF_ADBE'!$B$6)+'DCF_ADBE'!$B$7-'DCF_ADBE'!$B$8)-'DCF_ADBE'!$B$3*(1+'DCF_ADBE'!$B$4)^1*'DCF_ADBE'!$B$4*'DCF_ADBE'!$B$9)/(1+0.10500000000000001)^2+('DCF_ADBE'!$B$3*(1+'DCF_ADBE'!$B$4)^3*('DCF_ADBE'!$B$5*(1-'DCF_ADBE'!$B$6)+'DCF_ADBE'!$B$7-'DCF_ADBE'!$B$8)-'DCF_ADBE'!$B$3*(1+'DCF_ADBE'!$B$4)^2*'DCF_ADBE'!$B$4*'DCF_ADBE'!$B$9)/(1+0.10500000000000001)^3+('DCF_ADBE'!$B$3*(1+'DCF_ADBE'!$B$4)^4*('DCF_ADBE'!$B$5*(1-'DCF_ADBE'!$B$6)+'DCF_ADBE'!$B$7-'DCF_ADBE'!$B$8)-'DCF_ADBE'!$B$3*(1+'DCF_ADBE'!$B$4)^3*'DCF_ADBE'!$B$4*'DCF_ADBE'!$B$9)/(1+0.10500000000000001)^4+('DCF_ADBE'!$B$3*(1+'DCF_ADBE'!$B$4)^5*('DCF_ADBE'!$B$5*(1-'DCF_ADBE'!$B$6)+'DCF_ADBE'!$B$7-'DCF_ADBE'!$B$8)-'DCF_ADBE'!$B$3*(1+'DCF_ADBE'!$B$4)^4*'DCF_ADBE'!$B$4*'DCF_ADBE'!$B$9)/(1+0.10500000000000001)^5+('DCF_ADBE'!$B$3*(1+'DCF_ADBE'!$B$4)^5*(1+0.015000000000000001)*('DCF_ADBE'!$B$5*(1-'DCF_ADBE'!$B$6)+'DCF_ADBE'!$B$7-'DCF_ADBE'!$B$8)-'DCF_ADBE'!$B$3*(1+'DCF_ADBE'!$B$4)^5*0.015000000000000001*'DCF_ADBE'!$B$9)/(0.10500000000000001-0.015000000000000001)/(1+0.10500000000000001)^5-'DCF_ADBE'!$B$13)/'DCF_ADBE'!$B$12) -> 220.64794 | D6: =((('DCF_ADBE'!$B$3*(1+'DCF_ADBE'!$B$4)^1*('DCF_ADBE'!$B$5*(1-'DCF_ADBE'!$B$6)+'DCF_ADBE'!$B$7-'DCF_ADBE'!$B$8)-'DCF_ADBE'!$B$3*(1+'DCF_ADBE'!$B$4)^0*'DCF_ADBE'!$B$4*'DCF_ADBE'!$B$9)/(1+0.10500000000000001)^1+('DCF_ADBE'!$B$3*(1+'DCF_ADBE'!$B$4)^2*('DCF_ADBE'!$B$5*(1-'DCF_ADBE'!$B$6)+'DCF_ADBE'!$B$7-'DCF_ADBE'!$B$8)-'DCF_ADBE'!$B$3*(1+'DCF_ADBE'!$B$4)^1*'DCF_ADBE'!$B$4*'DCF_ADBE'!$B$9)/(1+0.10500000000000001)^2+('DCF_ADBE'!$B$3*(1+'DCF_ADBE'!$B$4)^3*('DCF_ADBE'!$B$5*(1-'DCF_ADBE'!$B$6)+'DCF_ADBE'!$B$7-'DCF_ADBE'!$B$8)-'DCF_ADBE'!$B$3*(1+'DCF_ADBE'!$B$4)^2*'DCF_ADBE'!$B$4*'DCF_ADBE'!$B$9)/(1+0.10500000000000001)^3+('DCF_ADBE'!$B$3*(1+'DCF_ADBE'!$B$4)^4*('DCF_ADBE'!$B$5*(1-'DCF_ADBE'!$B$6)+'DCF_ADBE'!$B$7-'DCF_ADBE'!$B$8)-'DCF_ADBE'!$B$3*(1+'DCF_ADBE'!$B$4)^3*'DCF_ADBE'!$B$4*'DCF_ADBE'!$B$9)/(1+0.10500000000000001)^4+('DCF_ADBE'!$B$3*(1+'DCF_ADBE'!$B$4)^5*('DCF_ADBE'!$B$5*(1-'DCF_ADBE'!$B$6)+'DCF_ADBE'!$B$7-'DCF_ADBE'!$B$8)-'DCF_ADBE'!$B$3*(1+'DCF_ADBE'!$B$4)^4*'DCF_ADBE'!$B$4*'DCF_ADBE'!$B$9)/(1+0.10500000000000001)^5+('DCF_ADBE'!$B$3*(1+'DCF_ADBE'!$B$4)^5*(1+0.02)*('DCF_ADBE'!$B$5*(1-'DCF_ADBE'!$B$6)+'DCF_ADBE'!$B$7-'DCF_ADBE'!$B$8)-'DCF_ADBE'!$B$3*(1+'DCF_ADBE'!$B$4)^5*0.02*'DCF_ADBE'!$B$9)/(0.10500000000000001-0.02)/(1+0.10500000000000001)^5-'DCF_ADBE'!$B$13)/'DCF_ADBE'!$B$12) -> 230.13377 | E6: =((('DCF_ADBE'!$B$3*(1+'DCF_ADBE'!$B$4)^1*('DCF_ADBE'!$B$5*(1-'DCF_ADBE'!$B$6)+'DCF_ADBE'!$B$7-'DCF_ADBE'!$B$8)-'DCF_ADBE'!$B$3*(1+'DCF_ADBE'!$B$4)^0*'DCF_ADBE'!$B$4*'DCF_ADBE'!$B$9)/(1+0.10500000000000001)^1+('DCF_ADBE'!$B$3*(1+'DCF_ADBE'!$B$4)^2*('DCF_ADBE'!$B$5*(1-'DCF_ADBE'!$B$6)+'DCF_ADBE'!$B$7-'DCF_ADBE'!$B$8)-'DCF_ADBE'!$B$3*(1+'DCF_ADBE'!$B$4)^1*'DCF_ADBE'!$B$4*'DCF_ADBE'!$B$9)/(1+0.10500000000000001)^2+('DCF_ADBE'!$B$3*(1+'DCF_ADBE'!$B$4)^3*('DCF_ADBE'!$B$5*(1-'DCF_ADBE'!$B$6)+'DCF_ADBE'!$B$7-'DCF_ADBE'!$B$8)-'DCF_ADBE'!$B$3*(1+'DCF_ADBE'!$B$4)^2*'DCF_ADBE'!$B$4*'DCF_ADBE'!$B$9)/(1+0.10500000000000001)^3+('DCF_ADBE'!$B$3*(1+'DCF_ADBE'!$B$4)^4*('DCF_ADBE'!$B$5*(1-'DCF_ADBE'!$B$6)+'DCF_ADBE'!$B$7-'DCF_ADBE'!$B$8)-'DCF_ADBE'!$B$3*(1+'DCF_ADBE'!$B$4)^3*'DCF_ADBE'!$B$4*'DCF_ADBE'!$B$9)/(1+0.10500000000000001)^4+('DCF_ADBE'!$B$3*(1+'DCF_ADBE'!$B$4)^5*('DCF_ADBE'!$B$5*(1-'DCF_ADBE'!$B$6)+'DCF_ADBE'!$B$7-'DCF_ADBE'!$B$8)-'DCF_ADBE'!$B$3*(1+'DCF_ADBE'!$B$4)^4*'DCF_ADBE'!$B$4*'DCF_ADBE'!$B$9)/(1+0.10500000000000001)^5+('DCF_ADBE'!$B$3*(1+'DCF_ADBE'!$B$4)^5*(1+0.025)*('DCF_ADBE'!$B$5*(1-'DCF_ADBE'!$B$6)+'DCF_ADBE'!$B$7-'DCF_ADBE'!$B$8)-'DCF_ADBE'!$B$3*(1+'DCF_ADBE'!$B$4)^5*0.025*'DCF_ADBE'!$B$9)/(0.10500000000000001-0.025)/(1+0.10500000000000001)^5-'DCF_ADBE'!$B$13)/'DCF_ADBE'!$B$12) -> 240.80532 | F6: =((('DCF_ADBE'!$B$3*(1+'DCF_ADBE'!$B$4)^1*('DCF_ADBE'!$B$5*(1-'DCF_ADBE'!$B$6)+'DCF_ADBE'!$B$7-'DCF_ADBE'!$B$8)-'DCF_ADBE'!$B$3*(1+'DCF_ADBE'!$B$4)^0*'DCF_ADBE'!$B$4*'DCF_ADBE'!$B$9)/(1+0.10500000000000001)^1+('DCF_ADBE'!$B$3*(1+'DCF_ADBE'!$B$4)^2*('DCF_ADBE'!$B$5*(1-'DCF_ADBE'!$B$6)+'DCF_ADBE'!$B$7-'DCF_ADBE'!$B$8)-'DCF_ADBE'!$B$3*(1+'DCF_ADBE'!$B$4)^1*'DCF_ADBE'!$B$4*'DCF_ADBE'!$B$9)/(1+0.10500000000000001)^2+('DCF_ADBE'!$B$3*(1+'DCF_ADBE'!$B$4)^3*('DCF_ADBE'!$B$5*(1-'DCF_ADBE'!$B$6)+'DCF_ADBE'!$B$7-'DCF_ADBE'!$B$8)-'DCF_ADBE'!$B$3*(1+'DCF_ADBE'!$B$4)^2*'DCF_ADBE'!$B$4*'DCF_ADBE'!$B$9)/(1+0.10500000000000001)^3+('DCF_ADBE'!$B$3*(1+'DCF_ADBE'!$B$4)^4*('DCF_ADBE'!$B$5*(1-'DCF_ADBE'!$B$6)+'DCF_ADBE'!$B$7-'DCF_ADBE'!$B$8)-'DCF_ADBE'!$B$3*(1+'DCF_ADBE'!$B$4)^3*'DCF_ADBE'!$B$4*'DCF_ADBE'!$B$9)/(1+0.10500000000000001)^4+('DCF_ADBE'!$B$3*(1+'DCF_ADBE'!$B$4)^5*('DCF_ADBE'!$B$5*(1-'DCF_ADBE'!$B$6)+'DCF_ADBE'!$B$7-'DCF_ADBE'!$B$8)-'DCF_ADBE'!$B$3*(1+'DCF_ADBE'!$B$4)^4*'DCF_ADBE'!$B$4*'DCF_ADBE'!$B$9)/(1+0.10500000000000001)^5+('DCF_ADBE'!$B$3*(1+'DCF_ADBE'!$B$4)^5*(1+0.030000000000000002)*('DCF_ADBE'!$B$5*(1-'DCF_ADBE'!$B$6)+'DCF_ADBE'!$B$7-'DCF_ADBE'!$B$8)-'DCF_ADBE'!$B$3*(1+'DCF_ADBE'!$B$4)^5*0.030000000000000002*'DCF_ADBE'!$B$9)/(0.10500000000000001-0.030000000000000002)/(1+0.10500000000000001)^5-'DCF_ADBE'!$B$13)/'DCF_ADBE'!$B$12) -> 252.89975 | G6: =((('DCF_ADBE'!$B$3*(1+'DCF_ADBE'!$B$4)^1*('DCF_ADBE'!$B$5*(1-'DCF_ADBE'!$B$6)+'DCF_ADBE'!$B$7-'DCF_ADBE'!$B$8)-'DCF_ADBE'!$B$3*(1+'DCF_ADBE'!$B$4)^0*'DCF_ADBE'!$B$4*'DCF_ADBE'!$B$9)/(1+0.10500000000000001)^1+('DCF_ADBE'!$B$3*(1+'DCF_ADBE'!$B$4)^2*('DCF_ADBE'!$B$5*(1-'DCF_ADBE'!$B$6)+'DCF_ADBE'!$B$7-'DCF_ADBE'!$B$8)-'DCF_ADBE'!$B$3*(1+'DCF_ADBE'!$B$4)^1*'DCF_ADBE'!$B$4*'DCF_ADBE'!$B$9)/(1+0.10500000000000001)^2+('DCF_ADBE'!$B$3*(1+'DCF_ADBE'!$B$4)^3*('DCF_ADBE'!$B$5*(1-'DCF_ADBE'!$B$6)+'DCF_ADBE'!$B$7-'DCF_ADBE'!$B$8)-'DCF_ADBE'!$B$3*(1+'DCF_ADBE'!$B$4)^2*'DCF_ADBE'!$B$4*'DCF_ADBE'!$B$9)/(1+0.10500000000000001)^3+('DCF_ADBE'!$B$3*(1+'DCF_ADBE'!$B$4)^4*('DCF_ADBE'!$B$5*(1-'DCF_ADBE'!$B$6)+'DCF_ADBE'!$B$7-'DCF_ADBE'!$B$8)-'DCF_ADBE'!$B$3*(1+'DCF_ADBE'!$B$4)^3*'DCF_ADBE'!$B$4*'DCF_ADBE'!$B$9)/(1+0.10500000000000001)^4+('DCF_ADBE'!$B$3*(1+'DCF_ADBE'!$B$4)^5*('DCF_ADBE'!$B$5*(1-'DCF_ADBE'!$B$6)+'DCF_ADBE'!$B$7-'DCF_ADBE'!$B$8)-'DCF_ADBE'!$B$3*(1+'DCF_ADBE'!$B$4)^4*'DCF_ADBE'!$B$4*'DCF_ADBE'!$B$9)/(1+0.10500000000000001)^5+('DCF_ADBE'!$B$3*(1+'DCF_ADBE'!$B$4)^5*(1+0.035)*('DCF_ADBE'!$B$5*(1-'DCF_ADBE'!$B$6)+'DCF_ADBE'!$B$7-'DCF_ADBE'!$B$8)-'DCF_ADBE'!$B$3*(1+'DCF_ADBE'!$B$4)^5*0.035*'DCF_ADBE'!$B$9)/(0.10500000000000001-0.035)/(1+0.10500000000000001)^5-'DCF_ADBE'!$B$13)/'DCF_ADBE'!$B$12) -> 266.72196
A7: ADBE | B7: 0.11 | C7: =((('DCF_ADBE'!$B$3*(1+'DCF_ADBE'!$B$4)^1*('DCF_ADBE'!$B$5*(1-'DCF_ADBE'!$B$6)+'DCF_ADBE'!$B$7-'DCF_ADBE'!$B$8)-'DCF_ADBE'!$B$3*(1+'DCF_ADBE'!$B$4)^0*'DCF_ADBE'!$B$4*'DCF_ADBE'!$B$9)/(1+0.11)^1+('DCF_ADBE'!$B$3*(1+'DCF_ADBE'!$B$4)^2*('DCF_ADBE'!$B$5*(1-'DCF_ADBE'!$B$6)+'DCF_ADBE'!$B$7-'DCF_ADBE'!$B$8)-'DCF_ADBE'!$B$3*(1+'DCF_ADBE'!$B$4)^1*'DCF_ADBE'!$B$4*'DCF_ADBE'!$B$9)/(1+0.11)^2+('DCF_ADBE'!$B$3*(1+'DCF_ADBE'!$B$4)^3*('DCF_ADBE'!$B$5*(1-'DCF_ADBE'!$B$6)+'DCF_ADBE'!$B$7-'DCF_ADBE'!$B$8)-'DCF_ADBE'!$B$3*(1+'DCF_ADBE'!$B$4)^2*'DCF_ADBE'!$B$4*'DCF_ADBE'!$B$9)/(1+0.11)^3+('DCF_ADBE'!$B$3*(1+'DCF_ADBE'!$B$4)^4*('DCF_ADBE'!$B$5*(1-'DCF_ADBE'!$B$6)+'DCF_ADBE'!$B$7-'DCF_ADBE'!$B$8)-'DCF_ADBE'!$B$3*(1+'DCF_ADBE'!$B$4)^3*'DCF_ADBE'!$B$4*'DCF_ADBE'!$B$9)/(1+0.11)^4+('DCF_ADBE'!$B$3*(1+'DCF_ADBE'!$B$4)^5*('DCF_ADBE'!$B$5*(1-'DCF_ADBE'!$B$6)+'DCF_ADBE'!$B$7-'DCF_ADBE'!$B$8)-'DCF_ADBE'!$B$3*(1+'DCF_ADBE'!$B$4)^4*'DCF_ADBE'!$B$4*'DCF_ADBE'!$B$9)/(1+0.11)^5+('DCF_ADBE'!$B$3*(1+'DCF_ADBE'!$B$4)^5*(1+0.015000000000000001)*('DCF_ADBE'!$B$5*(1-'DCF_ADBE'!$B$6)+'DCF_ADBE'!$B$7-'DCF_ADBE'!$B$8)-'DCF_ADBE'!$B$3*(1+'DCF_ADBE'!$B$4)^5*0.015000000000000001*'DCF_ADBE'!$B$9)/(0.11-0.015000000000000001)/(1+0.11)^5-'DCF_ADBE'!$B$13)/'DCF_ADBE'!$B$12) -> 208.70014 | D7: =((('DCF_ADBE'!$B$3*(1+'DCF_ADBE'!$B$4)^1*('DCF_ADBE'!$B$5*(1-'DCF_ADBE'!$B$6)+'DCF_ADBE'!$B$7-'DCF_ADBE'!$B$8)-'DCF_ADBE'!$B$3*(1+'DCF_ADBE'!$B$4)^0*'DCF_ADBE'!$B$4*'DCF_ADBE'!$B$9)/(1+0.11)^1+('DCF_ADBE'!$B$3*(1+'DCF_ADBE'!$B$4)^2*('DCF_ADBE'!$B$5*(1-'DCF_ADBE'!$B$6)+'DCF_ADBE'!$B$7-'DCF_ADBE'!$B$8)-'DCF_ADBE'!$B$3*(1+'DCF_ADBE'!$B$4)^1*'DCF_ADBE'!$B$4*'DCF_ADBE'!$B$9)/(1+0.11)^2+('DCF_ADBE'!$B$3*(1+'DCF_ADBE'!$B$4)^3*('DCF_ADBE'!$B$5*(1-'DCF_ADBE'!$B$6)+'DCF_ADBE'!$B$7-'DCF_ADBE'!$B$8)-'DCF_ADBE'!$B$3*(1+'DCF_ADBE'!$B$4)^2*'DCF_ADBE'!$B$4*'DCF_ADBE'!$B$9)/(1+0.11)^3+('DCF_ADBE'!$B$3*(1+'DCF_ADBE'!$B$4)^4*('DCF_ADBE'!$B$5*(1-'DCF_ADBE'!$B$6)+'DCF_ADBE'!$B$7-'DCF_ADBE'!$B$8)-'DCF_ADBE'!$B$3*(1+'DCF_ADBE'!$B$4)^3*'DCF_ADBE'!$B$4*'DCF_ADBE'!$B$9)/(1+0.11)^4+('DCF_ADBE'!$B$3*(1+'DCF_ADBE'!$B$4)^5*('DCF_ADBE'!$B$5*(1-'DCF_ADBE'!$B$6)+'DCF_ADBE'!$B$7-'DCF_ADBE'!$B$8)-'DCF_ADBE'!$B$3*(1+'DCF_ADBE'!$B$4)^4*'DCF_ADBE'!$B$4*'DCF_ADBE'!$B$9)/(1+0.11)^5+('DCF_ADBE'!$B$3*(1+'DCF_ADBE'!$B$4)^5*(1+0.02)*('DCF_ADBE'!$B$5*(1-'DCF_ADBE'!$B$6)+'DCF_ADBE'!$B$7-'DCF_ADBE'!$B$8)-'DCF_ADBE'!$B$3*(1+'DCF_ADBE'!$B$4)^5*0.02*'DCF_ADBE'!$B$9)/(0.11-0.02)/(1+0.11)^5-'DCF_ADBE'!$B$13)/'DCF_ADBE'!$B$12) -> 217.03188 | E7: =((('DCF_ADBE'!$B$3*(1+'DCF_ADBE'!$B$4)^1*('DCF_ADBE'!$B$5*(1-'DCF_ADBE'!$B$6)+'DCF_ADBE'!$B$7-'DCF_ADBE'!$B$8)-'DCF_ADBE'!$B$3*(1+'DCF_ADBE'!$B$4)^0*'DCF_ADBE'!$B$4*'DCF_ADBE'!$B$9)/(1+0.11)^1+('DCF_ADBE'!$B$3*(1+'DCF_ADBE'!$B$4)^2*('DCF_ADBE'!$B$5*(1-'DCF_ADBE'!$B$6)+'DCF_ADBE'!$B$7-'DCF_ADBE'!$B$8)-'DCF_ADBE'!$B$3*(1+'DCF_ADBE'!$B$4)^1*'DCF_ADBE'!$B$4*'DCF_ADBE'!$B$9)/(1+0.11)^2+('DCF_ADBE'!$B$3*(1+'DCF_ADBE'!$B$4)^3*('DCF_ADBE'!$B$5*(1-'DCF_ADBE'!$B$6)+'DCF_ADBE'!$B$7-'DCF_ADBE'!$B$8)-'DCF_ADBE'!$B$3*(1+'DCF_ADBE'!$B$4)^2*'DCF_ADBE'!$B$4*'DCF_ADBE'!$B$9)/(1+0.11)^3+('DCF_ADBE'!$B$3*(1+'DCF_ADBE'!$B$4)^4*('DCF_ADBE'!$B$5*(1-'DCF_ADBE'!$B$6)+'DCF_ADBE'!$B$7-'DCF_ADBE'!$B$8)-'DCF_ADBE'!$B$3*(1+'DCF_ADBE'!$B$4)^3*'DCF_ADBE'!$B$4*'DCF_ADBE'!$B$9)/(1+0.11)^4+('DCF_ADBE'!$B$3*(1+'DCF_ADBE'!$B$4)^5*('DCF_ADBE'!$B$5*(1-'DCF_ADBE'!$B$6)+'DCF_ADBE'!$B$7-'DCF_ADBE'!$B$8)-'DCF_ADBE'!$B$3*(1+'DCF_ADBE'!$B$4)^4*'DCF_ADBE'!$B$4*'DCF_ADBE'!$B$9)/(1+0.11)^5+('DCF_ADBE'!$B$3*(1+'DCF_ADBE'!$B$4)^5*(1+0.025)*('DCF_ADBE'!$B$5*(1-'DCF_ADBE'!$B$6)+'DCF_ADBE'!$B$7-'DCF_ADBE'!$B$8)-'DCF_ADBE'!$B$3*(1+'DCF_ADBE'!$B$4)^5*0.025*'DCF_ADBE'!$B$9)/(0.11-0.025)/(1+0.11)^5-'DCF_ADBE'!$B$13)/'DCF_ADBE'!$B$12) -> 226.34384 | F7: =((('DCF_ADBE'!$B$3*(1+'DCF_ADBE'!$B$4)^1*('DCF_ADBE'!$B$5*(1-'DCF_ADBE'!$B$6)+'DCF_ADBE'!$B$7-'DCF_ADBE'!$B$8)-'DCF_ADBE'!$B$3*(1+'DCF_ADBE'!$B$4)^0*'DCF_ADBE'!$B$4*'DCF_ADBE'!$B$9)/(1+0.11)^1+('DCF_ADBE'!$B$3*(1+'DCF_ADBE'!$B$4)^2*('DCF_ADBE'!$B$5*(1-'DCF_ADBE'!$B$6)+'DCF_ADBE'!$B$7-'DCF_ADBE'!$B$8)-'DCF_ADBE'!$B$3*(1+'DCF_ADBE'!$B$4)^1*'DCF_ADBE'!$B$4*'DCF_ADBE'!$B$9)/(1+0.11)^2+('DCF_ADBE'!$B$3*(1+'DCF_ADBE'!$B$4)^3*('DCF_ADBE'!$B$5*(1-'DCF_ADBE'!$B$6)+'DCF_ADBE'!$B$7-'DCF_ADBE'!$B$8)-'DCF_ADBE'!$B$3*(1+'DCF_ADBE'!$B$4)^2*'DCF_ADBE'!$B$4*'DCF_ADBE'!$B$9)/(1+0.11)^3+('DCF_ADBE'!$B$3*(1+'DCF_ADBE'!$B$4)^4*('DCF_ADBE'!$B$5*(1-'DCF_ADBE'!$B$6)+'DCF_ADBE'!$B$7-'DCF_ADBE'!$B$8)-'DCF_ADBE'!$B$3*(1+'DCF_ADBE'!$B$4)^3*'DCF_ADBE'!$B$4*'DCF_ADBE'!$B$9)/(1+0.11)^4+('DCF_ADBE'!$B$3*(1+'DCF_ADBE'!$B$4)^5*('DCF_ADBE'!$B$5*(1-'DCF_ADBE'!$B$6)+'DCF_ADBE'!$B$7-'DCF_ADBE'!$B$8)-'DCF_ADBE'!$B$3*(1+'DCF_ADBE'!$B$4)^4*'DCF_ADBE'!$B$4*'DCF_ADBE'!$B$9)/(1+0.11)^5+('DCF_ADBE'!$B$3*(1+'DCF_ADBE'!$B$4)^5*(1+0.030000000000000002)*('DCF_ADBE'!$B$5*(1-'DCF_ADBE'!$B$6)+'DCF_ADBE'!$B$7-'DCF_ADBE'!$B$8)-'DCF_ADBE'!$B$3*(1+'DCF_ADBE'!$B$4)^5*0.030000000000000002*'DCF_ADBE'!$B$9)/(0.11-0.030000000000000002)/(1+0.11)^5-'DCF_ADBE'!$B$13)/'DCF_ADBE'!$B$12) -> 236.81978 | G7: =((('DCF_ADBE'!$B$3*(1+'DCF_ADBE'!$B$4)^1*('DCF_ADBE'!$B$5*(1-'DCF_ADBE'!$B$6)+'DCF_ADBE'!$B$7-'DCF_ADBE'!$B$8)-'DCF_ADBE'!$B$3*(1+'DCF_ADBE'!$B$4)^0*'DCF_ADBE'!$B$4*'DCF_ADBE'!$B$9)/(1+0.11)^1+('DCF_ADBE'!$B$3*(1+'DCF_ADBE'!$B$4)^2*('DCF_ADBE'!$B$5*(1-'DCF_ADBE'!$B$6)+'DCF_ADBE'!$B$7-'DCF_ADBE'!$B$8)-'DCF_ADBE'!$B$3*(1+'DCF_ADBE'!$B$4)^1*'DCF_ADBE'!$B$4*'DCF_ADBE'!$B$9)/(1+0.11)^2+('DCF_ADBE'!$B$3*(1+'DCF_ADBE'!$B$4)^3*('DCF_ADBE'!$B$5*(1-'DCF_ADBE'!$B$6)+'DCF_ADBE'!$B$7-'DCF_ADBE'!$B$8)-'DCF_ADBE'!$B$3*(1+'DCF_ADBE'!$B$4)^2*'DCF_ADBE'!$B$4*'DCF_ADBE'!$B$9)/(1+0.11)^3+('DCF_ADBE'!$B$3*(1+'DCF_ADBE'!$B$4)^4*('DCF_ADBE'!$B$5*(1-'DCF_ADBE'!$B$6)+'DCF_ADBE'!$B$7-'DCF_ADBE'!$B$8)-'DCF_ADBE'!$B$3*(1+'DCF_ADBE'!$B$4)^3*'DCF_ADBE'!$B$4*'DCF_ADBE'!$B$9)/(1+0.11)^4+('DCF_ADBE'!$B$3*(1+'DCF_ADBE'!$B$4)^5*('DCF_ADBE'!$B$5*(1-'DCF_ADBE'!$B$6)+'DCF_ADBE'!$B$7-'DCF_ADBE'!$B$8)-'DCF_ADBE'!$B$3*(1+'DCF_ADBE'!$B$4)^4*'DCF_ADBE'!$B$4*'DCF_ADBE'!$B$9)/(1+0.11)^5+('DCF_ADBE'!$B$3*(1+'DCF_ADBE'!$B$4)^5*(1+0.035)*('DCF_ADBE'!$B$5*(1-'DCF_ADBE'!$B$6)+'DCF_ADBE'!$B$7-'DCF_ADBE'!$B$8)-'DCF_ADBE'!$B$3*(1+'DCF_ADBE'!$B$4)^5*0.035*'DCF_ADBE'!$B$9)/(0.11-0.035)/(1+0.11)^5-'DCF_ADBE'!$B$13)/'DCF_ADBE'!$B$12) -> 248.69252
A8: PYPL | B8: 0.095 | C8: =((('DCF_PYPL'!$B$3*(1+'DCF_PYPL'!$B$4)^1*('DCF_PYPL'!$B$5*(1-'DCF_PYPL'!$B$6)+'DCF_PYPL'!$B$7-'DCF_PYPL'!$B$8)-'DCF_PYPL'!$B$3*(1+'DCF_PYPL'!$B$4)^0*'DCF_PYPL'!$B$4*'DCF_PYPL'!$B$9)/(1+0.095)^1+('DCF_PYPL'!$B$3*(1+'DCF_PYPL'!$B$4)^2*('DCF_PYPL'!$B$5*(1-'DCF_PYPL'!$B$6)+'DCF_PYPL'!$B$7-'DCF_PYPL'!$B$8)-'DCF_PYPL'!$B$3*(1+'DCF_PYPL'!$B$4)^1*'DCF_PYPL'!$B$4*'DCF_PYPL'!$B$9)/(1+0.095)^2+('DCF_PYPL'!$B$3*(1+'DCF_PYPL'!$B$4)^3*('DCF_PYPL'!$B$5*(1-'DCF_PYPL'!$B$6)+'DCF_PYPL'!$B$7-'DCF_PYPL'!$B$8)-'DCF_PYPL'!$B$3*(1+'DCF_PYPL'!$B$4)^2*'DCF_PYPL'!$B$4*'DCF_PYPL'!$B$9)/(1+0.095)^3+('DCF_PYPL'!$B$3*(1+'DCF_PYPL'!$B$4)^4*('DCF_PYPL'!$B$5*(1-'DCF_PYPL'!$B$6)+'DCF_PYPL'!$B$7-'DCF_PYPL'!$B$8)-'DCF_PYPL'!$B$3*(1+'DCF_PYPL'!$B$4)^3*'DCF_PYPL'!$B$4*'DCF_PYPL'!$B$9)/(1+0.095)^4+('DCF_PYPL'!$B$3*(1+'DCF_PYPL'!$B$4)^5*('DCF_PYPL'!$B$5*(1-'DCF_PYPL'!$B$6)+'DCF_PYPL'!$B$7-'DCF_PYPL'!$B$8)-'DCF_PYPL'!$B$3*(1+'DCF_PYPL'!$B$4)^4*'DCF_PYPL'!$B$4*'DCF_PYPL'!$B$9)/(1+0.095)^5+('DCF_PYPL'!$B$3*(1+'DCF_PYPL'!$B$4)^5*(1+0.01)*('DCF_PYPL'!$B$5*(1-'DCF_PYPL'!$B$6)+'DCF_PYPL'!$B$7-'DCF_PYPL'!$B$8)-'DCF_PYPL'!$B$3*(1+'DCF_PYPL'!$B$4)^5*0.01*'DCF_PYPL'!$B$9)/(0.095-0.01)/(1+0.095)^5-'DCF_PYPL'!$B$13)/'DCF_PYPL'!$B$12) -> 68.263765 | D8: =((('DCF_PYPL'!$B$3*(1+'DCF_PYPL'!$B$4)^1*('DCF_PYPL'!$B$5*(1-'DCF_PYPL'!$B$6)+'DCF_PYPL'!$B$7-'DCF_PYPL'!$B$8)-'DCF_PYPL'!$B$3*(1+'DCF_PYPL'!$B$4)^0*'DCF_PYPL'!$B$4*'DCF_PYPL'!$B$9)/(1+0.095)^1+('DCF_PYPL'!$B$3*(1+'DCF_PYPL'!$B$4)^2*('DCF_PYPL'!$B$5*(1-'DCF_PYPL'!$B$6)+'DCF_PYPL'!$B$7-'DCF_PYPL'!$B$8)-'DCF_PYPL'!$B$3*(1+'DCF_PYPL'!$B$4)^1*'DCF_PYPL'!$B$4*'DCF_PYPL'!$B$9)/(1+0.095)^2+('DCF_PYPL'!$B$3*(1+'DCF_PYPL'!$B$4)^3*('DCF_PYPL'!$B$5*(1-'DCF_PYPL'!$B$6)+'DCF_PYPL'!$B$7-'DCF_PYPL'!$B$8)-'DCF_PYPL'!$B$3*(1+'DCF_PYPL'!$B$4)^2*'DCF_PYPL'!$B$4*'DCF_PYPL'!$B$9)/(1+0.095)^3+('DCF_PYPL'!$B$3*(1+'DCF_PYPL'!$B$4)^4*('DCF_PYPL'!$B$5*(1-'DCF_PYPL'!$B$6)+'DCF_PYPL'!$B$7-'DCF_PYPL'!$B$8)-'DCF_PYPL'!$B$3*(1+'DCF_PYPL'!$B$4)^3*'DCF_PYPL'!$B$4*'DCF_PYPL'!$B$9)/(1+0.095)^4+('DCF_PYPL'!$B$3*(1+'DCF_PYPL'!$B$4)^5*('DCF_PYPL'!$B$5*(1-'DCF_PYPL'!$B$6)+'DCF_PYPL'!$B$7-'DCF_PYPL'!$B$8)-'DCF_PYPL'!$B$3*(1+'DCF_PYPL'!$B$4)^4*'DCF_PYPL'!$B$4*'DCF_PYPL'!$B$9)/(1+0.095)^5+('DCF_PYPL'!$B$3*(1+'DCF_PYPL'!$B$4)^5*(1+0.015)*('DCF_PYPL'!$B$5*(1-'DCF_PYPL'!$B$6)+'DCF_PYPL'!$B$7-'DCF_PYPL'!$B$8)-'DCF_PYPL'!$B$3*(1+'DCF_PYPL'!$B$4)^5*0.015*'DCF_PYPL'!$B$9)/(0.095-0.015)/(1+0.095)^5-'DCF_PYPL'!$B$13)/'DCF_PYPL'!$B$12) -> 71.36565 | E8: =((('DCF_PYPL'!$B$3*(1+'DCF_PYPL'!$B$4)^1*('DCF_PYPL'!$B$5*(1-'DCF_PYPL'!$B$6)+'DCF_PYPL'!$B$7-'DCF_PYPL'!$B$8)-'DCF_PYPL'!$B$3*(1+'DCF_PYPL'!$B$4)^0*'DCF_PYPL'!$B$4*'DCF_PYPL'!$B$9)/(1+0.095)^1+('DCF_PYPL'!$B$3*(1+'DCF_PYPL'!$B$4)^2*('DCF_PYPL'!$B$5*(1-'DCF_PYPL'!$B$6)+'DCF_PYPL'!$B$7-'DCF_PYPL'!$B$8)-'DCF_PYPL'!$B$3*(1+'DCF_PYPL'!$B$4)^1*'DCF_PYPL'!$B$4*'DCF_PYPL'!$B$9)/(1+0.095)^2+('DCF_PYPL'!$B$3*(1+'DCF_PYPL'!$B$4)^3*('DCF_PYPL'!$B$5*(1-'DCF_PYPL'!$B$6)+'DCF_PYPL'!$B$7-'DCF_PYPL'!$B$8)-'DCF_PYPL'!$B$3*(1+'DCF_PYPL'!$B$4)^2*'DCF_PYPL'!$B$4*'DCF_PYPL'!$B$9)/(1+0.095)^3+('DCF_PYPL'!$B$3*(1+'DCF_PYPL'!$B$4)^4*('DCF_PYPL'!$B$5*(1-'DCF_PYPL'!$B$6)+'DCF_PYPL'!$B$7-'DCF_PYPL'!$B$8)-'DCF_PYPL'!$B$3*(1+'DCF_PYPL'!$B$4)^3*'DCF_PYPL'!$B$4*'DCF_PYPL'!$B$9)/(1+0.095)^4+('DCF_PYPL'!$B$3*(1+'DCF_PYPL'!$B$4)^5*('DCF_PYPL'!$B$5*(1-'DCF_PYPL'!$B$6)+'DCF_PYPL'!$B$7-'DCF_PYPL'!$B$8)-'DCF_PYPL'!$B$3*(1+'DCF_PYPL'!$B$4)^4*'DCF_PYPL'!$B$4*'DCF_PYPL'!$B$9)/(1+0.095)^5+('DCF_PYPL'!$B$3*(1+'DCF_PYPL'!$B$4)^5*(1+0.02)*('DCF_PYPL'!$B$5*(1-'DCF_PYPL'!$B$6)+'DCF_PYPL'!$B$7-'DCF_PYPL'!$B$8)-'DCF_PYPL'!$B$3*(1+'DCF_PYPL'!$B$4)^5*0.02*'DCF_PYPL'!$B$9)/(0.095-0.02)/(1+0.095)^5-'DCF_PYPL'!$B$13)/'DCF_PYPL'!$B$12) -> 74.881119 | F8: =((('DCF_PYPL'!$B$3*(1+'DCF_PYPL'!$B$4)^1*('DCF_PYPL'!$B$5*(1-'DCF_PYPL'!$B$6)+'DCF_PYPL'!$B$7-'DCF_PYPL'!$B$8)-'DCF_PYPL'!$B$3*(1+'DCF_PYPL'!$B$4)^0*'DCF_PYPL'!$B$4*'DCF_PYPL'!$B$9)/(1+0.095)^1+('DCF_PYPL'!$B$3*(1+'DCF_PYPL'!$B$4)^2*('DCF_PYPL'!$B$5*(1-'DCF_PYPL'!$B$6)+'DCF_PYPL'!$B$7-'DCF_PYPL'!$B$8)-'DCF_PYPL'!$B$3*(1+'DCF_PYPL'!$B$4)^1*'DCF_PYPL'!$B$4*'DCF_PYPL'!$B$9)/(1+0.095)^2+('DCF_PYPL'!$B$3*(1+'DCF_PYPL'!$B$4)^3*('DCF_PYPL'!$B$5*(1-'DCF_PYPL'!$B$6)+'DCF_PYPL'!$B$7-'DCF_PYPL'!$B$8)-'DCF_PYPL'!$B$3*(1+'DCF_PYPL'!$B$4)^2*'DCF_PYPL'!$B$4*'DCF_PYPL'!$B$9)/(1+0.095)^3+('DCF_PYPL'!$B$3*(1+'DCF_PYPL'!$B$4)^4*('DCF_PYPL'!$B$5*(1-'DCF_PYPL'!$B$6)+'DCF_PYPL'!$B$7-'DCF_PYPL'!$B$8)-'DCF_PYPL'!$B$3*(1+'DCF_PYPL'!$B$4)^3*'DCF_PYPL'!$B$4*'DCF_PYPL'!$B$9)/(1+0.095)^4+('DCF_PYPL'!$B$3*(1+'DCF_PYPL'!$B$4)^5*('DCF_PYPL'!$B$5*(1-'DCF_PYPL'!$B$6)+'DCF_PYPL'!$B$7-'DCF_PYPL'!$B$8)-'DCF_PYPL'!$B$3*(1+'DCF_PYPL'!$B$4)^4*'DCF_PYPL'!$B$4*'DCF_PYPL'!$B$9)/(1+0.095)^5+('DCF_PYPL'!$B$3*(1+'DCF_PYPL'!$B$4)^5*(1+0.025)*('DCF_PYPL'!$B$5*(1-'DCF_PYPL'!$B$6)+'DCF_PYPL'!$B$7-'DCF_PYPL'!$B$8)-'DCF_PYPL'!$B$3*(1+'DCF_PYPL'!$B$4)^5*0.025*'DCF_PYPL'!$B$9)/(0.095-0.025)/(1+0.095)^5-'DCF_PYPL'!$B$13)/'DCF_PYPL'!$B$12) -> 78.898798 | G8: =((('DCF_PYPL'!$B$3*(1+'DCF_PYPL'!$B$4)^1*('DCF_PYPL'!$B$5*(1-'DCF_PYPL'!$B$6)+'DCF_PYPL'!$B$7-'DCF_PYPL'!$B$8)-'DCF_PYPL'!$B$3*(1+'DCF_PYPL'!$B$4)^0*'DCF_PYPL'!$B$4*'DCF_PYPL'!$B$9)/(1+0.095)^1+('DCF_PYPL'!$B$3*(1+'DCF_PYPL'!$B$4)^2*('DCF_PYPL'!$B$5*(1-'DCF_PYPL'!$B$6)+'DCF_PYPL'!$B$7-'DCF_PYPL'!$B$8)-'DCF_PYPL'!$B$3*(1+'DCF_PYPL'!$B$4)^1*'DCF_PYPL'!$B$4*'DCF_PYPL'!$B$9)/(1+0.095)^2+('DCF_PYPL'!$B$3*(1+'DCF_PYPL'!$B$4)^3*('DCF_PYPL'!$B$5*(1-'DCF_PYPL'!$B$6)+'DCF_PYPL'!$B$7-'DCF_PYPL'!$B$8)-'DCF_PYPL'!$B$3*(1+'DCF_PYPL'!$B$4)^2*'DCF_PYPL'!$B$4*'DCF_PYPL'!$B$9)/(1+0.095)^3+('DCF_PYPL'!$B$3*(1+'DCF_PYPL'!$B$4)^4*('DCF_PYPL'!$B$5*(1-'DCF_PYPL'!$B$6)+'DCF_PYPL'!$B$7-'DCF_PYPL'!$B$8)-'DCF_PYPL'!$B$3*(1+'DCF_PYPL'!$B$4)^3*'DCF_PYPL'!$B$4*'DCF_PYPL'!$B$9)/(1+0.095)^4+('DCF_PYPL'!$B$3*(1+'DCF_PYPL'!$B$4)^5*('DCF_PYPL'!$B$5*(1-'DCF_PYPL'!$B$6)+'DCF_PYPL'!$B$7-'DCF_PYPL'!$B$8)-'DCF_PYPL'!$B$3*(1+'DCF_PYPL'!$B$4)^4*'DCF_PYPL'!$B$4*'DCF_PYPL'!$B$9)/(1+0.095)^5+('DCF_PYPL'!$B$3*(1+'DCF_PYPL'!$B$4)^5*(1+0.03)*('DCF_PYPL'!$B$5*(1-'DCF_PYPL'!$B$6)+'DCF_PYPL'!$B$7-'DCF_PYPL'!$B$8)-'DCF_PYPL'!$B$3*(1+'DCF_PYPL'!$B$4)^5*0.03*'DCF_PYPL'!$B$9)/(0.095-0.03)/(1+0.095)^5-'DCF_PYPL'!$B$13)/'DCF_PYPL'!$B$12) -> 83.534582
A9: PYPL | B9: 0.1 | C9: =((('DCF_PYPL'!$B$3*(1+'DCF_PYPL'!$B$4)^1*('DCF_PYPL'!$B$5*(1-'DCF_PYPL'!$B$6)+'DCF_PYPL'!$B$7-'DCF_PYPL'!$B$8)-'DCF_PYPL'!$B$3*(1+'DCF_PYPL'!$B$4)^0*'DCF_PYPL'!$B$4*'DCF_PYPL'!$B$9)/(1+0.09999999999999999)^1+('DCF_PYPL'!$B$3*(1+'DCF_PYPL'!$B$4)^2*('DCF_PYPL'!$B$5*(1-'DCF_PYPL'!$B$6)+'DCF_PYPL'!$B$7-'DCF_PYPL'!$B$8)-'DCF_PYPL'!$B$3*(1+'DCF_PYPL'!$B$4)^1*'DCF_PYPL'!$B$4*'DCF_PYPL'!$B$9)/(1+0.09999999999999999)^2+('DCF_PYPL'!$B$3*(1+'DCF_PYPL'!$B$4)^3*('DCF_PYPL'!$B$5*(1-'DCF_PYPL'!$B$6)+'DCF_PYPL'!$B$7-'DCF_PYPL'!$B$8)-'DCF_PYPL'!$B$3*(1+'DCF_PYPL'!$B$4)^2*'DCF_PYPL'!$B$4*'DCF_PYPL'!$B$9)/(1+0.09999999999999999)^3+('DCF_PYPL'!$B$3*(1+'DCF_PYPL'!$B$4)^4*('DCF_PYPL'!$B$5*(1-'DCF_PYPL'!$B$6)+'DCF_PYPL'!$B$7-'DCF_PYPL'!$B$8)-'DCF_PYPL'!$B$3*(1+'DCF_PYPL'!$B$4)^3*'DCF_PYPL'!$B$4*'DCF_PYPL'!$B$9)/(1+0.09999999999999999)^4+('DCF_PYPL'!$B$3*(1+'DCF_PYPL'!$B$4)^5*('DCF_PYPL'!$B$5*(1-'DCF_PYPL'!$B$6)+'DCF_PYPL'!$B$7-'DCF_PYPL'!$B$8)-'DCF_PYPL'!$B$3*(1+'DCF_PYPL'!$B$4)^4*'DCF_PYPL'!$B$4*'DCF_PYPL'!$B$9)/(1+0.09999999999999999)^5+('DCF_PYPL'!$B$3*(1+'DCF_PYPL'!$B$4)^5*(1+0.01)*('DCF_PYPL'!$B$5*(1-'DCF_PYPL'!$B$6)+'DCF_PYPL'!$B$7-'DCF_PYPL'!$B$8)-'DCF_PYPL'!$B$3*(1+'DCF_PYPL'!$B$4)^5*0.01*'DCF_PYPL'!$B$9)/(0.09999999999999999-0.01)/(1+0.09999999999999999)^5-'DCF_PYPL'!$B$13)/'DCF_PYPL'!$B$12) -> 64.427537 | D9: =((('DCF_PYPL'!$B$3*(1+'DCF_PYPL'!$B$4)^1*('DCF_PYPL'!$B$5*(1-'DCF_PYPL'!$B$6)+'DCF_PYPL'!$B$7-'DCF_PYPL'!$B$8)-'DCF_PYPL'!$B$3*(1+'DCF_PYPL'!$B$4)^0*'DCF_PYPL'!$B$4*'DCF_PYPL'!$B$9)/(1+0.09999999999999999)^1+('DCF_PYPL'!$B$3*(1+'DCF_PYPL'!$B$4)^2*('DCF_PYPL'!$B$5*(1-'DCF_PYPL'!$B$6)+'DCF_PYPL'!$B$7-'DCF_PYPL'!$B$8)-'DCF_PYPL'!$B$3*(1+'DCF_PYPL'!$B$4)^1*'DCF_PYPL'!$B$4*'DCF_PYPL'!$B$9)/(1+0.09999999999999999)^2+('DCF_PYPL'!$B$3*(1+'DCF_PYPL'!$B$4)^3*('DCF_PYPL'!$B$5*(1-'DCF_PYPL'!$B$6)+'DCF_PYPL'!$B$7-'DCF_PYPL'!$B$8)-'DCF_PYPL'!$B$3*(1+'DCF_PYPL'!$B$4)^2*'DCF_PYPL'!$B$4*'DCF_PYPL'!$B$9)/(1+0.09999999999999999)^3+('DCF_PYPL'!$B$3*(1+'DCF_PYPL'!$B$4)^4*('DCF_PYPL'!$B$5*(1-'DCF_PYPL'!$B$6)+'DCF_PYPL'!$B$7-'DCF_PYPL'!$B$8)-'DCF_PYPL'!$B$3*(1+'DCF_PYPL'!$B$4)^3*'DCF_PYPL'!$B$4*'DCF_PYPL'!$B$9)/(1+0.09999999999999999)^4+('DCF_PYPL'!$B$3*(1+'DCF_PYPL'!$B$4)^5*('DCF_PYPL'!$B$5*(1-'DCF_PYPL'!$B$6)+'DCF_PYPL'!$B$7-'DCF_PYPL'!$B$8)-'DCF_PYPL'!$B$3*(1+'DCF_PYPL'!$B$4)^4*'DCF_PYPL'!$B$4*'DCF_PYPL'!$B$9)/(1+0.09999999999999999)^5+('DCF_PYPL'!$B$3*(1+'DCF_PYPL'!$B$4)^5*(1+0.015)*('DCF_PYPL'!$B$5*(1-'DCF_PYPL'!$B$6)+'DCF_PYPL'!$B$7-'DCF_PYPL'!$B$8)-'DCF_PYPL'!$B$3*(1+'DCF_PYPL'!$B$4)^5*0.015*'DCF_PYPL'!$B$9)/(0.09999999999999999-0.015)/(1+0.09999999999999999)^5-'DCF_PYPL'!$B$13)/'DCF_PYPL'!$B$12) -> 67.133432 | E9: =((('DCF_PYPL'!$B$3*(1+'DCF_PYPL'!$B$4)^1*('DCF_PYPL'!$B$5*(1-'DCF_PYPL'!$B$6)+'DCF_PYPL'!$B$7-'DCF_PYPL'!$B$8)-'DCF_PYPL'!$B$3*(1+'DCF_PYPL'!$B$4)^0*'DCF_PYPL'!$B$4*'DCF_PYPL'!$B$9)/(1+0.09999999999999999)^1+('DCF_PYPL'!$B$3*(1+'DCF_PYPL'!$B$4)^2*('DCF_PYPL'!$B$5*(1-'DCF_PYPL'!$B$6)+'DCF_PYPL'!$B$7-'DCF_PYPL'!$B$8)-'DCF_PYPL'!$B$3*(1+'DCF_PYPL'!$B$4)^1*'DCF_PYPL'!$B$4*'DCF_PYPL'!$B$9)/(1+0.09999999999999999)^2+('DCF_PYPL'!$B$3*(1+'DCF_PYPL'!$B$4)^3*('DCF_PYPL'!$B$5*(1-'DCF_PYPL'!$B$6)+'DCF_PYPL'!$B$7-'DCF_PYPL'!$B$8)-'DCF_PYPL'!$B$3*(1+'DCF_PYPL'!$B$4)^2*'DCF_PYPL'!$B$4*'DCF_PYPL'!$B$9)/(1+0.09999999999999999)^3+('DCF_PYPL'!$B$3*(1+'DCF_PYPL'!$B$4)^4*('DCF_PYPL'!$B$5*(1-'DCF_PYPL'!$B$6)+'DCF_PYPL'!$B$7-'DCF_PYPL'!$B$8)-'DCF_PYPL'!$B$3*(1+'DCF_PYPL'!$B$4)^3*'DCF_PYPL'!$B$4*'DCF_PYPL'!$B$9)/(1+0.09999999999999999)^4+('DCF_PYPL'!$B$3*(1+'DCF_PYPL'!$B$4)^5*('DCF_PYPL'!$B$5*(1-'DCF_PYPL'!$B$6)+'DCF_PYPL'!$B$7-'DCF_PYPL'!$B$8)-'DCF_PYPL'!$B$3*(1+'DCF_PYPL'!$B$4)^4*'DCF_PYPL'!$B$4*'DCF_PYPL'!$B$9)/(1+0.09999999999999999)^5+('DCF_PYPL'!$B$3*(1+'DCF_PYPL'!$B$4)^5*(1+0.02)*('DCF_PYPL'!$B$5*(1-'DCF_PYPL'!$B$6)+'DCF_PYPL'!$B$7-'DCF_PYPL'!$B$8)-'DCF_PYPL'!$B$3*(1+'DCF_PYPL'!$B$4)^5*0.02*'DCF_PYPL'!$B$9)/(0.09999999999999999-0.02)/(1+0.09999999999999999)^5-'DCF_PYPL'!$B$13)/'DCF_PYPL'!$B$12) -> 70.177564 | F9: =((('DCF_PYPL'!$B$3*(1+'DCF_PYPL'!$B$4)^1*('DCF_PYPL'!$B$5*(1-'DCF_PYPL'!$B$6)+'DCF_PYPL'!$B$7-'DCF_PYPL'!$B$8)-'DCF_PYPL'!$B$3*(1+'DCF_PYPL'!$B$4)^0*'DCF_PYPL'!$B$4*'DCF_PYPL'!$B$9)/(1+0.09999999999999999)^1+('DCF_PYPL'!$B$3*(1+'DCF_PYPL'!$B$4)^2*('DCF_PYPL'!$B$5*(1-'DCF_PYPL'!$B$6)+'DCF_PYPL'!$B$7-'DCF_PYPL'!$B$8)-'DCF_PYPL'!$B$3*(1+'DCF_PYPL'!$B$4)^1*'DCF_PYPL'!$B$4*'DCF_PYPL'!$B$9)/(1+0.09999999999999999)^2+('DCF_PYPL'!$B$3*(1+'DCF_PYPL'!$B$4)^3*('DCF_PYPL'!$B$5*(1-'DCF_PYPL'!$B$6)+'DCF_PYPL'!$B$7-'DCF_PYPL'!$B$8)-'DCF_PYPL'!$B$3*(1+'DCF_PYPL'!$B$4)^2*'DCF_PYPL'!$B$4*'DCF_PYPL'!$B$9)/(1+0.09999999999999999)^3+('DCF_PYPL'!$B$3*(1+'DCF_PYPL'!$B$4)^4*('DCF_PYPL'!$B$5*(1-'DCF_PYPL'!$B$6)+'DCF_PYPL'!$B$7-'DCF_PYPL'!$B$8)-'DCF_PYPL'!$B$3*(1+'DCF_PYPL'!$B$4)^3*'DCF_PYPL'!$B$4*'DCF_PYPL'!$B$9)/(1+0.09999999999999999)^4+('DCF_PYPL'!$B$3*(1+'DCF_PYPL'!$B$4)^5*('DCF_PYPL'!$B$5*(1-'DCF_PYPL'!$B$6)+'DCF_PYPL'!$B$7-'DCF_PYPL'!$B$8)-'DCF_PYPL'!$B$3*(1+'DCF_PYPL'!$B$4)^4*'DCF_PYPL'!$B$4*'DCF_PYPL'!$B$9)/(1+0.09999999999999999)^5+('DCF_PYPL'!$B$3*(1+'DCF_PYPL'!$B$4)^5*(1+0.025)*('DCF_PYPL'!$B$5*(1-'DCF_PYPL'!$B$6)+'DCF_PYPL'!$B$7-'DCF_PYPL'!$B$8)-'DCF_PYPL'!$B$3*(1+'DCF_PYPL'!$B$4)^5*0.025*'DCF_PYPL'!$B$9)/(0.09999999999999999-0.025)/(1+0.09999999999999999)^5-'DCF_PYPL'!$B$13)/'DCF_PYPL'!$B$12) -> 73.62758 | G9: =((('DCF_PYPL'!$B$3*(1+'DCF_PYPL'!$B$4)^1*('DCF_PYPL'!$B$5*(1-'DCF_PYPL'!$B$6)+'DCF_PYPL'!$B$7-'DCF_PYPL'!$B$8)-'DCF_PYPL'!$B$3*(1+'DCF_PYPL'!$B$4)^0*'DCF_PYPL'!$B$4*'DCF_PYPL'!$B$9)/(1+0.09999999999999999)^1+('DCF_PYPL'!$B$3*(1+'DCF_PYPL'!$B$4)^2*('DCF_PYPL'!$B$5*(1-'DCF_PYPL'!$B$6)+'DCF_PYPL'!$B$7-'DCF_PYPL'!$B$8)-'DCF_PYPL'!$B$3*(1+'DCF_PYPL'!$B$4)^1*'DCF_PYPL'!$B$4*'DCF_PYPL'!$B$9)/(1+0.09999999999999999)^2+('DCF_PYPL'!$B$3*(1+'DCF_PYPL'!$B$4)^3*('DCF_PYPL'!$B$5*(1-'DCF_PYPL'!$B$6)+'DCF_PYPL'!$B$7-'DCF_PYPL'!$B$8)-'DCF_PYPL'!$B$3*(1+'DCF_PYPL'!$B$4)^2*'DCF_PYPL'!$B$4*'DCF_PYPL'!$B$9)/(1+0.09999999999999999)^3+('DCF_PYPL'!$B$3*(1+'DCF_PYPL'!$B$4)^4*('DCF_PYPL'!$B$5*(1-'DCF_PYPL'!$B$6)+'DCF_PYPL'!$B$7-'DCF_PYPL'!$B$8)-'DCF_PYPL'!$B$3*(1+'DCF_PYPL'!$B$4)^3*'DCF_PYPL'!$B$4*'DCF_PYPL'!$B$9)/(1+0.09999999999999999)^4+('DCF_PYPL'!$B$3*(1+'DCF_PYPL'!$B$4)^5*('DCF_PYPL'!$B$5*(1-'DCF_PYPL'!$B$6)+'DCF_PYPL'!$B$7-'DCF_PYPL'!$B$8)-'DCF_PYPL'!$B$3*(1+'DCF_PYPL'!$B$4)^4*'DCF_PYPL'!$B$4*'DCF_PYPL'!$B$9)/(1+0.09999999999999999)^5+('DCF_PYPL'!$B$3*(1+'DCF_PYPL'!$B$4)^5*(1+0.03)*('DCF_PYPL'!$B$5*(1-'DCF_PYPL'!$B$6)+'DCF_PYPL'!$B$7-'DCF_PYPL'!$B$8)-'DCF_PYPL'!$B$3*(1+'DCF_PYPL'!$B$4)^5*0.03*'DCF_PYPL'!$B$9)/(0.09999999999999999-0.03)/(1+0.09999999999999999)^5-'DCF_PYPL'!$B$13)/'DCF_PYPL'!$B$12) -> 77.570455
A10: PYPL | B10: 0.105 | C10: =((('DCF_PYPL'!$B$3*(1+'DCF_PYPL'!$B$4)^1*('DCF_PYPL'!$B$5*(1-'DCF_PYPL'!$B$6)+'DCF_PYPL'!$B$7-'DCF_PYPL'!$B$8)-'DCF_PYPL'!$B$3*(1+'DCF_PYPL'!$B$4)^0*'DCF_PYPL'!$B$4*'DCF_PYPL'!$B$9)/(1+0.105)^1+('DCF_PYPL'!$B$3*(1+'DCF_PYPL'!$B$4)^2*('DCF_PYPL'!$B$5*(1-'DCF_PYPL'!$B$6)+'DCF_PYPL'!$B$7-'DCF_PYPL'!$B$8)-'DCF_PYPL'!$B$3*(1+'DCF_PYPL'!$B$4)^1*'DCF_PYPL'!$B$4*'DCF_PYPL'!$B$9)/(1+0.105)^2+('DCF_PYPL'!$B$3*(1+'DCF_PYPL'!$B$4)^3*('DCF_PYPL'!$B$5*(1-'DCF_PYPL'!$B$6)+'DCF_PYPL'!$B$7-'DCF_PYPL'!$B$8)-'DCF_PYPL'!$B$3*(1+'DCF_PYPL'!$B$4)^2*'DCF_PYPL'!$B$4*'DCF_PYPL'!$B$9)/(1+0.105)^3+('DCF_PYPL'!$B$3*(1+'DCF_PYPL'!$B$4)^4*('DCF_PYPL'!$B$5*(1-'DCF_PYPL'!$B$6)+'DCF_PYPL'!$B$7-'DCF_PYPL'!$B$8)-'DCF_PYPL'!$B$3*(1+'DCF_PYPL'!$B$4)^3*'DCF_PYPL'!$B$4*'DCF_PYPL'!$B$9)/(1+0.105)^4+('DCF_PYPL'!$B$3*(1+'DCF_PYPL'!$B$4)^5*('DCF_PYPL'!$B$5*(1-'DCF_PYPL'!$B$6)+'DCF_PYPL'!$B$7-'DCF_PYPL'!$B$8)-'DCF_PYPL'!$B$3*(1+'DCF_PYPL'!$B$4)^4*'DCF_PYPL'!$B$4*'DCF_PYPL'!$B$9)/(1+0.105)^5+('DCF_PYPL'!$B$3*(1+'DCF_PYPL'!$B$4)^5*(1+0.01)*('DCF_PYPL'!$B$5*(1-'DCF_PYPL'!$B$6)+'DCF_PYPL'!$B$7-'DCF_PYPL'!$B$8)-'DCF_PYPL'!$B$3*(1+'DCF_PYPL'!$B$4)^5*0.01*'DCF_PYPL'!$B$9)/(0.105-0.01)/(1+0.105)^5-'DCF_PYPL'!$B$13)/'DCF_PYPL'!$B$12) -> 60.996313 | D10: =((('DCF_PYPL'!$B$3*(1+'DCF_PYPL'!$B$4)^1*('DCF_PYPL'!$B$5*(1-'DCF_PYPL'!$B$6)+'DCF_PYPL'!$B$7-'DCF_PYPL'!$B$8)-'DCF_PYPL'!$B$3*(1+'DCF_PYPL'!$B$4)^0*'DCF_PYPL'!$B$4*'DCF_PYPL'!$B$9)/(1+0.105)^1+('DCF_PYPL'!$B$3*(1+'DCF_PYPL'!$B$4)^2*('DCF_PYPL'!$B$5*(1-'DCF_PYPL'!$B$6)+'DCF_PYPL'!$B$7-'DCF_PYPL'!$B$8)-'DCF_PYPL'!$B$3*(1+'DCF_PYPL'!$B$4)^1*'DCF_PYPL'!$B$4*'DCF_PYPL'!$B$9)/(1+0.105)^2+('DCF_PYPL'!$B$3*(1+'DCF_PYPL'!$B$4)^3*('DCF_PYPL'!$B$5*(1-'DCF_PYPL'!$B$6)+'DCF_PYPL'!$B$7-'DCF_PYPL'!$B$8)-'DCF_PYPL'!$B$3*(1+'DCF_PYPL'!$B$4)^2*'DCF_PYPL'!$B$4*'DCF_PYPL'!$B$9)/(1+0.105)^3+('DCF_PYPL'!$B$3*(1+'DCF_PYPL'!$B$4)^4*('DCF_PYPL'!$B$5*(1-'DCF_PYPL'!$B$6)+'DCF_PYPL'!$B$7-'DCF_PYPL'!$B$8)-'DCF_PYPL'!$B$3*(1+'DCF_PYPL'!$B$4)^3*'DCF_PYPL'!$B$4*'DCF_PYPL'!$B$9)/(1+0.105)^4+('DCF_PYPL'!$B$3*(1+'DCF_PYPL'!$B$4)^5*('DCF_PYPL'!$B$5*(1-'DCF_PYPL'!$B$6)+'DCF_PYPL'!$B$7-'DCF_PYPL'!$B$8)-'DCF_PYPL'!$B$3*(1+'DCF_PYPL'!$B$4)^4*'DCF_PYPL'!$B$4*'DCF_PYPL'!$B$9)/(1+0.105)^5+('DCF_PYPL'!$B$3*(1+'DCF_PYPL'!$B$4)^5*(1+0.015)*('DCF_PYPL'!$B$5*(1-'DCF_PYPL'!$B$6)+'DCF_PYPL'!$B$7-'DCF_PYPL'!$B$8)-'DCF_PYPL'!$B$3*(1+'DCF_PYPL'!$B$4)^5*0.015*'DCF_PYPL'!$B$9)/(0.105-0.015)/(1+0.105)^5-'DCF_PYPL'!$B$13)/'DCF_PYPL'!$B$12) -> 63.372508 | E10: =((('DCF_PYPL'!$B$3*(1+'DCF_PYPL'!$B$4)^1*('DCF_PYPL'!$B$5*(1-'DCF_PYPL'!$B$6)+'DCF_PYPL'!$B$7-'DCF_PYPL'!$B$8)-'DCF_PYPL'!$B$3*(1+'DCF_PYPL'!$B$4)^0*'DCF_PYPL'!$B$4*'DCF_PYPL'!$B$9)/(1+0.105)^1+('DCF_PYPL'!$B$3*(1+'DCF_PYPL'!$B$4)^2*('DCF_PYPL'!$B$5*(1-'DCF_PYPL'!$B$6)+'DCF_PYPL'!$B$7-'DCF_PYPL'!$B$8)-'DCF_PYPL'!$B$3*(1+'DCF_PYPL'!$B$4)^1*'DCF_PYPL'!$B$4*'DCF_PYPL'!$B$9)/(1+0.105)^2+('DCF_PYPL'!$B$3*(1+'DCF_PYPL'!$B$4)^3*('DCF_PYPL'!$B$5*(1-'DCF_PYPL'!$B$6)+'DCF_PYPL'!$B$7-'DCF_PYPL'!$B$8)-'DCF_PYPL'!$B$3*(1+'DCF_PYPL'!$B$4)^2*'DCF_PYPL'!$B$4*'DCF_PYPL'!$B$9)/(1+0.105)^3+('DCF_PYPL'!$B$3*(1+'DCF_PYPL'!$B$4)^4*('DCF_PYPL'!$B$5*(1-'DCF_PYPL'!$B$6)+'DCF_PYPL'!$B$7-'DCF_PYPL'!$B$8)-'DCF_PYPL'!$B$3*(1+'DCF_PYPL'!$B$4)^3*'DCF_PYPL'!$B$4*'DCF_PYPL'!$B$9)/(1+0.105)^4+('DCF_PYPL'!$B$3*(1+'DCF_PYPL'!$B$4)^5*('DCF_PYPL'!$B$5*(1-'DCF_PYPL'!$B$6)+'DCF_PYPL'!$B$7-'DCF_PYPL'!$B$8)-'DCF_PYPL'!$B$3*(1+'DCF_PYPL'!$B$4)^4*'DCF_PYPL'!$B$4*'DCF_PYPL'!$B$9)/(1+0.105)^5+('DCF_PYPL'!$B$3*(1+'DCF_PYPL'!$B$4)^5*(1+0.02)*('DCF_PYPL'!$B$5*(1-'DCF_PYPL'!$B$6)+'DCF_PYPL'!$B$7-'DCF_PYPL'!$B$8)-'DCF_PYPL'!$B$3*(1+'DCF_PYPL'!$B$4)^5*0.02*'DCF_PYPL'!$B$9)/(0.105-0.02)/(1+0.105)^5-'DCF_PYPL'!$B$13)/'DCF_PYPL'!$B$12) -> 66.028255 | F10: =((('DCF_PYPL'!$B$3*(1+'DCF_PYPL'!$B$4)^1*('DCF_PYPL'!$B$5*(1-'DCF_PYPL'!$B$6)+'DCF_PYPL'!$B$7-'DCF_PYPL'!$B$8)-'DCF_PYPL'!$B$3*(1+'DCF_PYPL'!$B$4)^0*'DCF_PYPL'!$B$4*'DCF_PYPL'!$B$9)/(1+0.105)^1+('DCF_PYPL'!$B$3*(1+'DCF_PYPL'!$B$4)^2*('DCF_PYPL'!$B$5*(1-'DCF_PYPL'!$B$6)+'DCF_PYPL'!$B$7-'DCF_PYPL'!$B$8)-'DCF_PYPL'!$B$3*(1+'DCF_PYPL'!$B$4)^1*'DCF_PYPL'!$B$4*'DCF_PYPL'!$B$9)/(1+0.105)^2+('DCF_PYPL'!$B$3*(1+'DCF_PYPL'!$B$4)^3*('DCF_PYPL'!$B$5*(1-'DCF_PYPL'!$B$6)+'DCF_PYPL'!$B$7-'DCF_PYPL'!$B$8)-'DCF_PYPL'!$B$3*(1+'DCF_PYPL'!$B$4)^2*'DCF_PYPL'!$B$4*'DCF_PYPL'!$B$9)/(1+0.105)^3+('DCF_PYPL'!$B$3*(1+'DCF_PYPL'!$B$4)^4*('DCF_PYPL'!$B$5*(1-'DCF_PYPL'!$B$6)+'DCF_PYPL'!$B$7-'DCF_PYPL'!$B$8)-'DCF_PYPL'!$B$3*(1+'DCF_PYPL'!$B$4)^3*'DCF_PYPL'!$B$4*'DCF_PYPL'!$B$9)/(1+0.105)^4+('DCF_PYPL'!$B$3*(1+'DCF_PYPL'!$B$4)^5*('DCF_PYPL'!$B$5*(1-'DCF_PYPL'!$B$6)+'DCF_PYPL'!$B$7-'DCF_PYPL'!$B$8)-'DCF_PYPL'!$B$3*(1+'DCF_PYPL'!$B$4)^4*'DCF_PYPL'!$B$4*'DCF_PYPL'!$B$9)/(1+0.105)^5+('DCF_PYPL'!$B$3*(1+'DCF_PYPL'!$B$4)^5*(1+0.025)*('DCF_PYPL'!$B$5*(1-'DCF_PYPL'!$B$6)+'DCF_PYPL'!$B$7-'DCF_PYPL'!$B$8)-'DCF_PYPL'!$B$3*(1+'DCF_PYPL'!$B$4)^5*0.025*'DCF_PYPL'!$B$9)/(0.105-0.025)/(1+0.105)^5-'DCF_PYPL'!$B$13)/'DCF_PYPL'!$B$12) -> 69.01597 | G10: =((('DCF_PYPL'!$B$3*(1+'DCF_PYPL'!$B$4)^1*('DCF_PYPL'!$B$5*(1-'DCF_PYPL'!$B$6)+'DCF_PYPL'!$B$7-'DCF_PYPL'!$B$8)-'DCF_PYPL'!$B$3*(1+'DCF_PYPL'!$B$4)^0*'DCF_PYPL'!$B$4*'DCF_PYPL'!$B$9)/(1+0.105)^1+('DCF_PYPL'!$B$3*(1+'DCF_PYPL'!$B$4)^2*('DCF_PYPL'!$B$5*(1-'DCF_PYPL'!$B$6)+'DCF_PYPL'!$B$7-'DCF_PYPL'!$B$8)-'DCF_PYPL'!$B$3*(1+'DCF_PYPL'!$B$4)^1*'DCF_PYPL'!$B$4*'DCF_PYPL'!$B$9)/(1+0.105)^2+('DCF_PYPL'!$B$3*(1+'DCF_PYPL'!$B$4)^3*('DCF_PYPL'!$B$5*(1-'DCF_PYPL'!$B$6)+'DCF_PYPL'!$B$7-'DCF_PYPL'!$B$8)-'DCF_PYPL'!$B$3*(1+'DCF_PYPL'!$B$4)^2*'DCF_PYPL'!$B$4*'DCF_PYPL'!$B$9)/(1+0.105)^3+('DCF_PYPL'!$B$3*(1+'DCF_PYPL'!$B$4)^4*('DCF_PYPL'!$B$5*(1-'DCF_PYPL'!$B$6)+'DCF_PYPL'!$B$7-'DCF_PYPL'!$B$8)-'DCF_PYPL'!$B$3*(1+'DCF_PYPL'!$B$4)^3*'DCF_PYPL'!$B$4*'DCF_PYPL'!$B$9)/(1+0.105)^4+('DCF_PYPL'!$B$3*(1+'DCF_PYPL'!$B$4)^5*('DCF_PYPL'!$B$5*(1-'DCF_PYPL'!$B$6)+'DCF_PYPL'!$B$7-'DCF_PYPL'!$B$8)-'DCF_PYPL'!$B$3*(1+'DCF_PYPL'!$B$4)^4*'DCF_PYPL'!$B$4*'DCF_PYPL'!$B$9)/(1+0.105)^5+('DCF_PYPL'!$B$3*(1+'DCF_PYPL'!$B$4)^5*(1+0.03)*('DCF_PYPL'!$B$5*(1-'DCF_PYPL'!$B$6)+'DCF_PYPL'!$B$7-'DCF_PYPL'!$B$8)-'DCF_PYPL'!$B$3*(1+'DCF_PYPL'!$B$4)^5*0.03*'DCF_PYPL'!$B$9)/(0.105-0.03)/(1+0.105)^5-'DCF_PYPL'!$B$13)/'DCF_PYPL'!$B$12) -> 72.402048
A11: PYPL | B11: 0.11 | C11: =((('DCF_PYPL'!$B$3*(1+'DCF_PYPL'!$B$4)^1*('DCF_PYPL'!$B$5*(1-'DCF_PYPL'!$B$6)+'DCF_PYPL'!$B$7-'DCF_PYPL'!$B$8)-'DCF_PYPL'!$B$3*(1+'DCF_PYPL'!$B$4)^0*'DCF_PYPL'!$B$4*'DCF_PYPL'!$B$9)/(1+0.11)^1+('DCF_PYPL'!$B$3*(1+'DCF_PYPL'!$B$4)^2*('DCF_PYPL'!$B$5*(1-'DCF_PYPL'!$B$6)+'DCF_PYPL'!$B$7-'DCF_PYPL'!$B$8)-'DCF_PYPL'!$B$3*(1+'DCF_PYPL'!$B$4)^1*'DCF_PYPL'!$B$4*'DCF_PYPL'!$B$9)/(1+0.11)^2+('DCF_PYPL'!$B$3*(1+'DCF_PYPL'!$B$4)^3*('DCF_PYPL'!$B$5*(1-'DCF_PYPL'!$B$6)+'DCF_PYPL'!$B$7-'DCF_PYPL'!$B$8)-'DCF_PYPL'!$B$3*(1+'DCF_PYPL'!$B$4)^2*'DCF_PYPL'!$B$4*'DCF_PYPL'!$B$9)/(1+0.11)^3+('DCF_PYPL'!$B$3*(1+'DCF_PYPL'!$B$4)^4*('DCF_PYPL'!$B$5*(1-'DCF_PYPL'!$B$6)+'DCF_PYPL'!$B$7-'DCF_PYPL'!$B$8)-'DCF_PYPL'!$B$3*(1+'DCF_PYPL'!$B$4)^3*'DCF_PYPL'!$B$4*'DCF_PYPL'!$B$9)/(1+0.11)^4+('DCF_PYPL'!$B$3*(1+'DCF_PYPL'!$B$4)^5*('DCF_PYPL'!$B$5*(1-'DCF_PYPL'!$B$6)+'DCF_PYPL'!$B$7-'DCF_PYPL'!$B$8)-'DCF_PYPL'!$B$3*(1+'DCF_PYPL'!$B$4)^4*'DCF_PYPL'!$B$4*'DCF_PYPL'!$B$9)/(1+0.11)^5+('DCF_PYPL'!$B$3*(1+'DCF_PYPL'!$B$4)^5*(1+0.01)*('DCF_PYPL'!$B$5*(1-'DCF_PYPL'!$B$6)+'DCF_PYPL'!$B$7-'DCF_PYPL'!$B$8)-'DCF_PYPL'!$B$3*(1+'DCF_PYPL'!$B$4)^5*0.01*'DCF_PYPL'!$B$9)/(0.11-0.01)/(1+0.11)^5-'DCF_PYPL'!$B$13)/'DCF_PYPL'!$B$12) -> 57.909315 | D11: =((('DCF_PYPL'!$B$3*(1+'DCF_PYPL'!$B$4)^1*('DCF_PYPL'!$B$5*(1-'DCF_PYPL'!$B$6)+'DCF_PYPL'!$B$7-'DCF_PYPL'!$B$8)-'DCF_PYPL'!$B$3*(1+'DCF_PYPL'!$B$4)^0*'DCF_PYPL'!$B$4*'DCF_PYPL'!$B$9)/(1+0.11)^1+('DCF_PYPL'!$B$3*(1+'DCF_PYPL'!$B$4)^2*('DCF_PYPL'!$B$5*(1-'DCF_PYPL'!$B$6)+'DCF_PYPL'!$B$7-'DCF_PYPL'!$B$8)-'DCF_PYPL'!$B$3*(1+'DCF_PYPL'!$B$4)^1*'DCF_PYPL'!$B$4*'DCF_PYPL'!$B$9)/(1+0.11)^2+('DCF_PYPL'!$B$3*(1+'DCF_PYPL'!$B$4)^3*('DCF_PYPL'!$B$5*(1-'DCF_PYPL'!$B$6)+'DCF_PYPL'!$B$7-'DCF_PYPL'!$B$8)-'DCF_PYPL'!$B$3*(1+'DCF_PYPL'!$B$4)^2*'DCF_PYPL'!$B$4*'DCF_PYPL'!$B$9)/(1+0.11)^3+('DCF_PYPL'!$B$3*(1+'DCF_PYPL'!$B$4)^4*('DCF_PYPL'!$B$5*(1-'DCF_PYPL'!$B$6)+'DCF_PYPL'!$B$7-'DCF_PYPL'!$B$8)-'DCF_PYPL'!$B$3*(1+'DCF_PYPL'!$B$4)^3*'DCF_PYPL'!$B$4*'DCF_PYPL'!$B$9)/(1+0.11)^4+('DCF_PYPL'!$B$3*(1+'DCF_PYPL'!$B$4)^5*('DCF_PYPL'!$B$5*(1-'DCF_PYPL'!$B$6)+'DCF_PYPL'!$B$7-'DCF_PYPL'!$B$8)-'DCF_PYPL'!$B$3*(1+'DCF_PYPL'!$B$4)^4*'DCF_PYPL'!$B$4*'DCF_PYPL'!$B$9)/(1+0.11)^5+('DCF_PYPL'!$B$3*(1+'DCF_PYPL'!$B$4)^5*(1+0.015)*('DCF_PYPL'!$B$5*(1-'DCF_PYPL'!$B$6)+'DCF_PYPL'!$B$7-'DCF_PYPL'!$B$8)-'DCF_PYPL'!$B$3*(1+'DCF_PYPL'!$B$4)^5*0.015*'DCF_PYPL'!$B$9)/(0.11-0.015)/(1+0.11)^5-'DCF_PYPL'!$B$13)/'DCF_PYPL'!$B$12) -> 60.008438 | E11: =((('DCF_PYPL'!$B$3*(1+'DCF_PYPL'!$B$4)^1*('DCF_PYPL'!$B$5*(1-'DCF_PYPL'!$B$6)+'DCF_PYPL'!$B$7-'DCF_PYPL'!$B$8)-'DCF_PYPL'!$B$3*(1+'DCF_PYPL'!$B$4)^0*'DCF_PYPL'!$B$4*'DCF_PYPL'!$B$9)/(1+0.11)^1+('DCF_PYPL'!$B$3*(1+'DCF_PYPL'!$B$4)^2*('DCF_PYPL'!$B$5*(1-'DCF_PYPL'!$B$6)+'DCF_PYPL'!$B$7-'DCF_PYPL'!$B$8)-'DCF_PYPL'!$B$3*(1+'DCF_PYPL'!$B$4)^1*'DCF_PYPL'!$B$4*'DCF_PYPL'!$B$9)/(1+0.11)^2+('DCF_PYPL'!$B$3*(1+'DCF_PYPL'!$B$4)^3*('DCF_PYPL'!$B$5*(1-'DCF_PYPL'!$B$6)+'DCF_PYPL'!$B$7-'DCF_PYPL'!$B$8)-'DCF_PYPL'!$B$3*(1+'DCF_PYPL'!$B$4)^2*'DCF_PYPL'!$B$4*'DCF_PYPL'!$B$9)/(1+0.11)^3+('DCF_PYPL'!$B$3*(1+'DCF_PYPL'!$B$4)^4*('DCF_PYPL'!$B$5*(1-'DCF_PYPL'!$B$6)+'DCF_PYPL'!$B$7-'DCF_PYPL'!$B$8)-'DCF_PYPL'!$B$3*(1+'DCF_PYPL'!$B$4)^3*'DCF_PYPL'!$B$4*'DCF_PYPL'!$B$9)/(1+0.11)^4+('DCF_PYPL'!$B$3*(1+'DCF_PYPL'!$B$4)^5*('DCF_PYPL'!$B$5*(1-'DCF_PYPL'!$B$6)+'DCF_PYPL'!$B$7-'DCF_PYPL'!$B$8)-'DCF_PYPL'!$B$3*(1+'DCF_PYPL'!$B$4)^4*'DCF_PYPL'!$B$4*'DCF_PYPL'!$B$9)/(1+0.11)^5+('DCF_PYPL'!$B$3*(1+'DCF_PYPL'!$B$4)^5*(1+0.02)*('DCF_PYPL'!$B$5*(1-'DCF_PYPL'!$B$6)+'DCF_PYPL'!$B$7-'DCF_PYPL'!$B$8)-'DCF_PYPL'!$B$3*(1+'DCF_PYPL'!$B$4)^5*0.02*'DCF_PYPL'!$B$9)/(0.11-0.02)/(1+0.11)^5-'DCF_PYPL'!$B$13)/'DCF_PYPL'!$B$12) -> 62.340798 | F11: =((('DCF_PYPL'!$B$3*(1+'DCF_PYPL'!$B$4)^1*('DCF_PYPL'!$B$5*(1-'DCF_PYPL'!$B$6)+'DCF_PYPL'!$B$7-'DCF_PYPL'!$B$8)-'DCF_PYPL'!$B$3*(1+'DCF_PYPL'!$B$4)^0*'DCF_PYPL'!$B$4*'DCF_PYPL'!$B$9)/(1+0.11)^1+('DCF_PYPL'!$B$3*(1+'DCF_PYPL'!$B$4)^2*('DCF_PYPL'!$B$5*(1-'DCF_PYPL'!$B$6)+'DCF_PYPL'!$B$7-'DCF_PYPL'!$B$8)-'DCF_PYPL'!$B$3*(1+'DCF_PYPL'!$B$4)^1*'DCF_PYPL'!$B$4*'DCF_PYPL'!$B$9)/(1+0.11)^2+('DCF_PYPL'!$B$3*(1+'DCF_PYPL'!$B$4)^3*('DCF_PYPL'!$B$5*(1-'DCF_PYPL'!$B$6)+'DCF_PYPL'!$B$7-'DCF_PYPL'!$B$8)-'DCF_PYPL'!$B$3*(1+'DCF_PYPL'!$B$4)^2*'DCF_PYPL'!$B$4*'DCF_PYPL'!$B$9)/(1+0.11)^3+('DCF_PYPL'!$B$3*(1+'DCF_PYPL'!$B$4)^4*('DCF_PYPL'!$B$5*(1-'DCF_PYPL'!$B$6)+'DCF_PYPL'!$B$7-'DCF_PYPL'!$B$8)-'DCF_PYPL'!$B$3*(1+'DCF_PYPL'!$B$4)^3*'DCF_PYPL'!$B$4*'DCF_PYPL'!$B$9)/(1+0.11)^4+('DCF_PYPL'!$B$3*(1+'DCF_PYPL'!$B$4)^5*('DCF_PYPL'!$B$5*(1-'DCF_PYPL'!$B$6)+'DCF_PYPL'!$B$7-'DCF_PYPL'!$B$8)-'DCF_PYPL'!$B$3*(1+'DCF_PYPL'!$B$4)^4*'DCF_PYPL'!$B$4*'DCF_PYPL'!$B$9)/(1+0.11)^5+('DCF_PYPL'!$B$3*(1+'DCF_PYPL'!$B$4)^5*(1+0.025)*('DCF_PYPL'!$B$5*(1-'DCF_PYPL'!$B$6)+'DCF_PYPL'!$B$7-'DCF_PYPL'!$B$8)-'DCF_PYPL'!$B$3*(1+'DCF_PYPL'!$B$4)^5*0.025*'DCF_PYPL'!$B$9)/(0.11-0.025)/(1+0.11)^5-'DCF_PYPL'!$B$13)/'DCF_PYPL'!$B$12) -> 64.947552 | G11: =((('DCF_PYPL'!$B$3*(1+'DCF_PYPL'!$B$4)^1*('DCF_PYPL'!$B$5*(1-'DCF_PYPL'!$B$6)+'DCF_PYPL'!$B$7-'DCF_PYPL'!$B$8)-'DCF_PYPL'!$B$3*(1+'DCF_PYPL'!$B$4)^0*'DCF_PYPL'!$B$4*'DCF_PYPL'!$B$9)/(1+0.11)^1+('DCF_PYPL'!$B$3*(1+'DCF_PYPL'!$B$4)^2*('DCF_PYPL'!$B$5*(1-'DCF_PYPL'!$B$6)+'DCF_PYPL'!$B$7-'DCF_PYPL'!$B$8)-'DCF_PYPL'!$B$3*(1+'DCF_PYPL'!$B$4)^1*'DCF_PYPL'!$B$4*'DCF_PYPL'!$B$9)/(1+0.11)^2+('DCF_PYPL'!$B$3*(1+'DCF_PYPL'!$B$4)^3*('DCF_PYPL'!$B$5*(1-'DCF_PYPL'!$B$6)+'DCF_PYPL'!$B$7-'DCF_PYPL'!$B$8)-'DCF_PYPL'!$B$3*(1+'DCF_PYPL'!$B$4)^2*'DCF_PYPL'!$B$4*'DCF_PYPL'!$B$9)/(1+0.11)^3+('DCF_PYPL'!$B$3*(1+'DCF_PYPL'!$B$4)^4*('DCF_PYPL'!$B$5*(1-'DCF_PYPL'!$B$6)+'DCF_PYPL'!$B$7-'DCF_PYPL'!$B$8)-'DCF_PYPL'!$B$3*(1+'DCF_PYPL'!$B$4)^3*'DCF_PYPL'!$B$4*'DCF_PYPL'!$B$9)/(1+0.11)^4+('DCF_PYPL'!$B$3*(1+'DCF_PYPL'!$B$4)^5*('DCF_PYPL'!$B$5*(1-'DCF_PYPL'!$B$6)+'DCF_PYPL'!$B$7-'DCF_PYPL'!$B$8)-'DCF_PYPL'!$B$3*(1+'DCF_PYPL'!$B$4)^4*'DCF_PYPL'!$B$4*'DCF_PYPL'!$B$9)/(1+0.11)^5+('DCF_PYPL'!$B$3*(1+'DCF_PYPL'!$B$4)^5*(1+0.03)*('DCF_PYPL'!$B$5*(1-'DCF_PYPL'!$B$6)+'DCF_PYPL'!$B$7-'DCF_PYPL'!$B$8)-'DCF_PYPL'!$B$3*(1+'DCF_PYPL'!$B$4)^5*0.03*'DCF_PYPL'!$B$9)/(0.11-0.03)/(1+0.11)^5-'DCF_PYPL'!$B$13)/'DCF_PYPL'!$B$12) -> 67.880151
A12: PYPL | B12: 0.115 | C12: =((('DCF_PYPL'!$B$3*(1+'DCF_PYPL'!$B$4)^1*('DCF_PYPL'!$B$5*(1-'DCF_PYPL'!$B$6)+'DCF_PYPL'!$B$7-'DCF_PYPL'!$B$8)-'DCF_PYPL'!$B$3*(1+'DCF_PYPL'!$B$4)^0*'DCF_PYPL'!$B$4*'DCF_PYPL'!$B$9)/(1+0.11499999999999999)^1+('DCF_PYPL'!$B$3*(1+'DCF_PYPL'!$B$4)^2*('DCF_PYPL'!$B$5*(1-'DCF_PYPL'!$B$6)+'DCF_PYPL'!$B$7-'DCF_PYPL'!$B$8)-'DCF_PYPL'!$B$3*(1+'DCF_PYPL'!$B$4)^1*'DCF_PYPL'!$B$4*'DCF_PYPL'!$B$9)/(1+0.11499999999999999)^2+('DCF_PYPL'!$B$3*(1+'DCF_PYPL'!$B$4)^3*('DCF_PYPL'!$B$5*(1-'DCF_PYPL'!$B$6)+'DCF_PYPL'!$B$7-'DCF_PYPL'!$B$8)-'DCF_PYPL'!$B$3*(1+'DCF_PYPL'!$B$4)^2*'DCF_PYPL'!$B$4*'DCF_PYPL'!$B$9)/(1+0.11499999999999999)^3+('DCF_PYPL'!$B$3*(1+'DCF_PYPL'!$B$4)^4*('DCF_PYPL'!$B$5*(1-'DCF_PYPL'!$B$6)+'DCF_PYPL'!$B$7-'DCF_PYPL'!$B$8)-'DCF_PYPL'!$B$3*(1+'DCF_PYPL'!$B$4)^3*'DCF_PYPL'!$B$4*'DCF_PYPL'!$B$9)/(1+0.11499999999999999)^4+('DCF_PYPL'!$B$3*(1+'DCF_PYPL'!$B$4)^5*('DCF_PYPL'!$B$5*(1-'DCF_PYPL'!$B$6)+'DCF_PYPL'!$B$7-'DCF_PYPL'!$B$8)-'DCF_PYPL'!$B$3*(1+'DCF_PYPL'!$B$4)^4*'DCF_PYPL'!$B$4*'DCF_PYPL'!$B$9)/(1+0.11499999999999999)^5+('DCF_PYPL'!$B$3*(1+'DCF_PYPL'!$B$4)^5*(1+0.01)*('DCF_PYPL'!$B$5*(1-'DCF_PYPL'!$B$6)+'DCF_PYPL'!$B$7-'DCF_PYPL'!$B$8)-'DCF_PYPL'!$B$3*(1+'DCF_PYPL'!$B$4)^5*0.01*'DCF_PYPL'!$B$9)/(0.11499999999999999-0.01)/(1+0.11499999999999999)^5-'DCF_PYPL'!$B$13)/'DCF_PYPL'!$B$12) -> 55.117343 | D12: =((('DCF_PYPL'!$B$3*(1+'DCF_PYPL'!$B$4)^1*('DCF_PYPL'!$B$5*(1-'DCF_PYPL'!$B$6)+'DCF_PYPL'!$B$7-'DCF_PYPL'!$B$8)-'DCF_PYPL'!$B$3*(1+'DCF_PYPL'!$B$4)^0*'DCF_PYPL'!$B$4*'DCF_PYPL'!$B$9)/(1+0.11499999999999999)^1+('DCF_PYPL'!$B$3*(1+'DCF_PYPL'!$B$4)^2*('DCF_PYPL'!$B$5*(1-'DCF_PYPL'!$B$6)+'DCF_PYPL'!$B$7-'DCF_PYPL'!$B$8)-'DCF_PYPL'!$B$3*(1+'DCF_PYPL'!$B$4)^1*'DCF_PYPL'!$B$4*'DCF_PYPL'!$B$9)/(1+0.11499999999999999)^2+('DCF_PYPL'!$B$3*(1+'DCF_PYPL'!$B$4)^3*('DCF_PYPL'!$B$5*(1-'DCF_PYPL'!$B$6)+'DCF_PYPL'!$B$7-'DCF_PYPL'!$B$8)-'DCF_PYPL'!$B$3*(1+'DCF_PYPL'!$B$4)^2*'DCF_PYPL'!$B$4*'DCF_PYPL'!$B$9)/(1+0.11499999999999999)^3+('DCF_PYPL'!$B$3*(1+'DCF_PYPL'!$B$4)^4*('DCF_PYPL'!$B$5*(1-'DCF_PYPL'!$B$6)+'DCF_PYPL'!$B$7-'DCF_PYPL'!$B$8)-'DCF_PYPL'!$B$3*(1+'DCF_PYPL'!$B$4)^3*'DCF_PYPL'!$B$4*'DCF_PYPL'!$B$9)/(1+0.11499999999999999)^4+('DCF_PYPL'!$B$3*(1+'DCF_PYPL'!$B$4)^5*('DCF_PYPL'!$B$5*(1-'DCF_PYPL'!$B$6)+'DCF_PYPL'!$B$7-'DCF_PYPL'!$B$8)-'DCF_PYPL'!$B$3*(1+'DCF_PYPL'!$B$4)^4*'DCF_PYPL'!$B$4*'DCF_PYPL'!$B$9)/(1+0.11499999999999999)^5+('DCF_PYPL'!$B$3*(1+'DCF_PYPL'!$B$4)^5*(1+0.015)*('DCF_PYPL'!$B$5*(1-'DCF_PYPL'!$B$6)+'DCF_PYPL'!$B$7-'DCF_PYPL'!$B$8)-'DCF_PYPL'!$B$3*(1+'DCF_PYPL'!$B$4)^5*0.015*'DCF_PYPL'!$B$9)/(0.11499999999999999-0.015)/(1+0.11499999999999999)^5-'DCF_PYPL'!$B$13)/'DCF_PYPL'!$B$12) -> 56.981674 | E12: =((('DCF_PYPL'!$B$3*(1+'DCF_PYPL'!$B$4)^1*('DCF_PYPL'!$B$5*(1-'DCF_PYPL'!$B$6)+'DCF_PYPL'!$B$7-'DCF_PYPL'!$B$8)-'DCF_PYPL'!$B$3*(1+'DCF_PYPL'!$B$4)^0*'DCF_PYPL'!$B$4*'DCF_PYPL'!$B$9)/(1+0.11499999999999999)^1+('DCF_PYPL'!$B$3*(1+'DCF_PYPL'!$B$4)^2*('DCF_PYPL'!$B$5*(1-'DCF_PYPL'!$B$6)+'DCF_PYPL'!$B$7-'DCF_PYPL'!$B$8)-'DCF_PYPL'!$B$3*(1+'DCF_PYPL'!$B$4)^1*'DCF_PYPL'!$B$4*'DCF_PYPL'!$B$9)/(1+0.11499999999999999)^2+('DCF_PYPL'!$B$3*(1+'DCF_PYPL'!$B$4)^3*('DCF_PYPL'!$B$5*(1-'DCF_PYPL'!$B$6)+'DCF_PYPL'!$B$7-'DCF_PYPL'!$B$8)-'DCF_PYPL'!$B$3*(1+'DCF_PYPL'!$B$4)^2*'DCF_PYPL'!$B$4*'DCF_PYPL'!$B$9)/(1+0.11499999999999999)^3+('DCF_PYPL'!$B$3*(1+'DCF_PYPL'!$B$4)^4*('DCF_PYPL'!$B$5*(1-'DCF_PYPL'!$B$6)+'DCF_PYPL'!$B$7-'DCF_PYPL'!$B$8)-'DCF_PYPL'!$B$3*(1+'DCF_PYPL'!$B$4)^3*'DCF_PYPL'!$B$4*'DCF_PYPL'!$B$9)/(1+0.11499999999999999)^4+('DCF_PYPL'!$B$3*(1+'DCF_PYPL'!$B$4)^5*('DCF_PYPL'!$B$5*(1-'DCF_PYPL'!$B$6)+'DCF_PYPL'!$B$7-'DCF_PYPL'!$B$8)-'DCF_PYPL'!$B$3*(1+'DCF_PYPL'!$B$4)^4*'DCF_PYPL'!$B$4*'DCF_PYPL'!$B$9)/(1+0.11499999999999999)^5+('DCF_PYPL'!$B$3*(1+'DCF_PYPL'!$B$4)^5*(1+0.02)*('DCF_PYPL'!$B$5*(1-'DCF_PYPL'!$B$6)+'DCF_PYPL'!$B$7-'DCF_PYPL'!$B$8)-'DCF_PYPL'!$B$3*(1+'DCF_PYPL'!$B$4)^5*0.02*'DCF_PYPL'!$B$9)/(0.11499999999999999-0.02)/(1+0.11499999999999999)^5-'DCF_PYPL'!$B$13)/'DCF_PYPL'!$B$12) -> 59.04225 | F12: =((('DCF_PYPL'!$B$3*(1+'DCF_PYPL'!$B$4)^1*('DCF_PYPL'!$B$5*(1-'DCF_PYPL'!$B$6)+'DCF_PYPL'!$B$7-'DCF_PYPL'!$B$8)-'DCF_PYPL'!$B$3*(1+'DCF_PYPL'!$B$4)^0*'DCF_PYPL'!$B$4*'DCF_PYPL'!$B$9)/(1+0.11499999999999999)^1+('DCF_PYPL'!$B$3*(1+'DCF_PYPL'!$B$4)^2*('DCF_PYPL'!$B$5*(1-'DCF_PYPL'!$B$6)+'DCF_PYPL'!$B$7-'DCF_PYPL'!$B$8)-'DCF_PYPL'!$B$3*(1+'DCF_PYPL'!$B$4)^1*'DCF_PYPL'!$B$4*'DCF_PYPL'!$B$9)/(1+0.11499999999999999)^2+('DCF_PYPL'!$B$3*(1+'DCF_PYPL'!$B$4)^3*('DCF_PYPL'!$B$5*(1-'DCF_PYPL'!$B$6)+'DCF_PYPL'!$B$7-'DCF_PYPL'!$B$8)-'DCF_PYPL'!$B$3*(1+'DCF_PYPL'!$B$4)^2*'DCF_PYPL'!$B$4*'DCF_PYPL'!$B$9)/(1+0.11499999999999999)^3+('DCF_PYPL'!$B$3*(1+'DCF_PYPL'!$B$4)^4*('DCF_PYPL'!$B$5*(1-'DCF_PYPL'!$B$6)+'DCF_PYPL'!$B$7-'DCF_PYPL'!$B$8)-'DCF_PYPL'!$B$3*(1+'DCF_PYPL'!$B$4)^3*'DCF_PYPL'!$B$4*'DCF_PYPL'!$B$9)/(1+0.11499999999999999)^4+('DCF_PYPL'!$B$3*(1+'DCF_PYPL'!$B$4)^5*('DCF_PYPL'!$B$5*(1-'DCF_PYPL'!$B$6)+'DCF_PYPL'!$B$7-'DCF_PYPL'!$B$8)-'DCF_PYPL'!$B$3*(1+'DCF_PYPL'!$B$4)^4*'DCF_PYPL'!$B$4*'DCF_PYPL'!$B$9)/(1+0.11499999999999999)^5+('DCF_PYPL'!$B$3*(1+'DCF_PYPL'!$B$4)^5*(1+0.025)*('DCF_PYPL'!$B$5*(1-'DCF_PYPL'!$B$6)+'DCF_PYPL'!$B$7-'DCF_PYPL'!$B$8)-'DCF_PYPL'!$B$3*(1+'DCF_PYPL'!$B$4)^5*0.025*'DCF_PYPL'!$B$9)/(0.11499999999999999-0.025)/(1+0.11499999999999999)^5-'DCF_PYPL'!$B$13)/'DCF_PYPL'!$B$12) -> 61.331779 | G12: =((('DCF_PYPL'!$B$3*(1+'DCF_PYPL'!$B$4)^1*('DCF_PYPL'!$B$5*(1-'DCF_PYPL'!$B$6)+'DCF_PYPL'!$B$7-'DCF_PYPL'!$B$8)-'DCF_PYPL'!$B$3*(1+'DCF_PYPL'!$B$4)^0*'DCF_PYPL'!$B$4*'DCF_PYPL'!$B$9)/(1+0.11499999999999999)^1+('DCF_PYPL'!$B$3*(1+'DCF_PYPL'!$B$4)^2*('DCF_PYPL'!$B$5*(1-'DCF_PYPL'!$B$6)+'DCF_PYPL'!$B$7-'DCF_PYPL'!$B$8)-'DCF_PYPL'!$B$3*(1+'DCF_PYPL'!$B$4)^1*'DCF_PYPL'!$B$4*'DCF_PYPL'!$B$9)/(1+0.11499999999999999)^2+('DCF_PYPL'!$B$3*(1+'DCF_PYPL'!$B$4)^3*('DCF_PYPL'!$B$5*(1-'DCF_PYPL'!$B$6)+'DCF_PYPL'!$B$7-'DCF_PYPL'!$B$8)-'DCF_PYPL'!$B$3*(1+'DCF_PYPL'!$B$4)^2*'DCF_PYPL'!$B$4*'DCF_PYPL'!$B$9)/(1+0.11499999999999999)^3+('DCF_PYPL'!$B$3*(1+'DCF_PYPL'!$B$4)^4*('DCF_PYPL'!$B$5*(1-'DCF_PYPL'!$B$6)+'DCF_PYPL'!$B$7-'DCF_PYPL'!$B$8)-'DCF_PYPL'!$B$3*(1+'DCF_PYPL'!$B$4)^3*'DCF_PYPL'!$B$4*'DCF_PYPL'!$B$9)/(1+0.11499999999999999)^4+('DCF_PYPL'!$B$3*(1+'DCF_PYPL'!$B$4)^5*('DCF_PYPL'!$B$5*(1-'DCF_PYPL'!$B$6)+'DCF_PYPL'!$B$7-'DCF_PYPL'!$B$8)-'DCF_PYPL'!$B$3*(1+'DCF_PYPL'!$B$4)^4*'DCF_PYPL'!$B$4*'DCF_PYPL'!$B$9)/(1+0.11499999999999999)^5+('DCF_PYPL'!$B$3*(1+'DCF_PYPL'!$B$4)^5*(1+0.03)*('DCF_PYPL'!$B$5*(1-'DCF_PYPL'!$B$6)+'DCF_PYPL'!$B$7-'DCF_PYPL'!$B$8)-'DCF_PYPL'!$B$3*(1+'DCF_PYPL'!$B$4)^5*0.03*'DCF_PYPL'!$B$9)/(0.11499999999999999-0.03)/(1+0.11499999999999999)^5-'DCF_PYPL'!$B$13)/'DCF_PYPL'!$B$12) -> 63.890665
A13: NKE | B13: 0.09 | C13: =((('DCF_NKE'!$B$3*(1+'DCF_NKE'!$B$4)^1*('DCF_NKE'!$B$5*(1-'DCF_NKE'!$B$6)+'DCF_NKE'!$B$7-'DCF_NKE'!$B$8)-'DCF_NKE'!$B$3*(1+'DCF_NKE'!$B$4)^0*'DCF_NKE'!$B$4*'DCF_NKE'!$B$9)/(1+0.09000000000000001)^1+('DCF_NKE'!$B$3*(1+'DCF_NKE'!$B$4)^2*('DCF_NKE'!$B$5*(1-'DCF_NKE'!$B$6)+'DCF_NKE'!$B$7-'DCF_NKE'!$B$8)-'DCF_NKE'!$B$3*(1+'DCF_NKE'!$B$4)^1*'DCF_NKE'!$B$4*'DCF_NKE'!$B$9)/(1+0.09000000000000001)^2+('DCF_NKE'!$B$3*(1+'DCF_NKE'!$B$4)^3*('DCF_NKE'!$B$5*(1-'DCF_NKE'!$B$6)+'DCF_NKE'!$B$7-'DCF_NKE'!$B$8)-'DCF_NKE'!$B$3*(1+'DCF_NKE'!$B$4)^2*'DCF_NKE'!$B$4*'DCF_NKE'!$B$9)/(1+0.09000000000000001)^3+('DCF_NKE'!$B$3*(1+'DCF_NKE'!$B$4)^4*('DCF_NKE'!$B$5*(1-'DCF_NKE'!$B$6)+'DCF_NKE'!$B$7-'DCF_NKE'!$B$8)-'DCF_NKE'!$B$3*(1+'DCF_NKE'!$B$4)^3*'DCF_NKE'!$B$4*'DCF_NKE'!$B$9)/(1+0.09000000000000001)^4+('DCF_NKE'!$B$3*(1+'DCF_NKE'!$B$4)^5*('DCF_NKE'!$B$5*(1-'DCF_NKE'!$B$6)+'DCF_NKE'!$B$7-'DCF_NKE'!$B$8)-'DCF_NKE'!$B$3*(1+'DCF_NKE'!$B$4)^4*'DCF_NKE'!$B$4*'DCF_NKE'!$B$9)/(1+0.09000000000000001)^5+('DCF_NKE'!$B$3*(1+'DCF_NKE'!$B$4)^5*(1+0.01)*('DCF_NKE'!$B$5*(1-'DCF_NKE'!$B$6)+'DCF_NKE'!$B$7-'DCF_NKE'!$B$8)-'DCF_NKE'!$B$3*(1+'DCF_NKE'!$B$4)^5*0.01*'DCF_NKE'!$B$9)/(0.09000000000000001-0.01)/(1+0.09000000000000001)^5-'DCF_NKE'!$B$13)/'DCF_NKE'!$B$12) -> 30.760257 | D13: =((('DCF_NKE'!$B$3*(1+'DCF_NKE'!$B$4)^1*('DCF_NKE'!$B$5*(1-'DCF_NKE'!$B$6)+'DCF_NKE'!$B$7-'DCF_NKE'!$B$8)-'DCF_NKE'!$B$3*(1+'DCF_NKE'!$B$4)^0*'DCF_NKE'!$B$4*'DCF_NKE'!$B$9)/(1+0.09000000000000001)^1+('DCF_NKE'!$B$3*(1+'DCF_NKE'!$B$4)^2*('DCF_NKE'!$B$5*(1-'DCF_NKE'!$B$6)+'DCF_NKE'!$B$7-'DCF_NKE'!$B$8)-'DCF_NKE'!$B$3*(1+'DCF_NKE'!$B$4)^1*'DCF_NKE'!$B$4*'DCF_NKE'!$B$9)/(1+0.09000000000000001)^2+('DCF_NKE'!$B$3*(1+'DCF_NKE'!$B$4)^3*('DCF_NKE'!$B$5*(1-'DCF_NKE'!$B$6)+'DCF_NKE'!$B$7-'DCF_NKE'!$B$8)-'DCF_NKE'!$B$3*(1+'DCF_NKE'!$B$4)^2*'DCF_NKE'!$B$4*'DCF_NKE'!$B$9)/(1+0.09000000000000001)^3+('DCF_NKE'!$B$3*(1+'DCF_NKE'!$B$4)^4*('DCF_NKE'!$B$5*(1-'DCF_NKE'!$B$6)+'DCF_NKE'!$B$7-'DCF_NKE'!$B$8)-'DCF_NKE'!$B$3*(1+'DCF_NKE'!$B$4)^3*'DCF_NKE'!$B$4*'DCF_NKE'!$B$9)/(1+0.09000000000000001)^4+('DCF_NKE'!$B$3*(1+'DCF_NKE'!$B$4)^5*('DCF_NKE'!$B$5*(1-'DCF_NKE'!$B$6)+'DCF_NKE'!$B$7-'DCF_NKE'!$B$8)-'DCF_NKE'!$B$3*(1+'DCF_NKE'!$B$4)^4*'DCF_NKE'!$B$4*'DCF_NKE'!$B$9)/(1+0.09000000000000001)^5+('DCF_NKE'!$B$3*(1+'DCF_NKE'!$B$4)^5*(1+0.015)*('DCF_NKE'!$B$5*(1-'DCF_NKE'!$B$6)+'DCF_NKE'!$B$7-'DCF_NKE'!$B$8)-'DCF_NKE'!$B$3*(1+'DCF_NKE'!$B$4)^5*0.015*'DCF_NKE'!$B$9)/(0.09000000000000001-0.015)/(1+0.09000000000000001)^5-'DCF_NKE'!$B$13)/'DCF_NKE'!$B$12) -> 32.11653 | E13: =((('DCF_NKE'!$B$3*(1+'DCF_NKE'!$B$4)^1*('DCF_NKE'!$B$5*(1-'DCF_NKE'!$B$6)+'DCF_NKE'!$B$7-'DCF_NKE'!$B$8)-'DCF_NKE'!$B$3*(1+'DCF_NKE'!$B$4)^0*'DCF_NKE'!$B$4*'DCF_NKE'!$B$9)/(1+0.09000000000000001)^1+('DCF_NKE'!$B$3*(1+'DCF_NKE'!$B$4)^2*('DCF_NKE'!$B$5*(1-'DCF_NKE'!$B$6)+'DCF_NKE'!$B$7-'DCF_NKE'!$B$8)-'DCF_NKE'!$B$3*(1+'DCF_NKE'!$B$4)^1*'DCF_NKE'!$B$4*'DCF_NKE'!$B$9)/(1+0.09000000000000001)^2+('DCF_NKE'!$B$3*(1+'DCF_NKE'!$B$4)^3*('DCF_NKE'!$B$5*(1-'DCF_NKE'!$B$6)+'DCF_NKE'!$B$7-'DCF_NKE'!$B$8)-'DCF_NKE'!$B$3*(1+'DCF_NKE'!$B$4)^2*'DCF_NKE'!$B$4*'DCF_NKE'!$B$9)/(1+0.09000000000000001)^3+('DCF_NKE'!$B$3*(1+'DCF_NKE'!$B$4)^4*('DCF_NKE'!$B$5*(1-'DCF_NKE'!$B$6)+'DCF_NKE'!$B$7-'DCF_NKE'!$B$8)-'DCF_NKE'!$B$3*(1+'DCF_NKE'!$B$4)^3*'DCF_NKE'!$B$4*'DCF_NKE'!$B$9)/(1+0.09000000000000001)^4+('DCF_NKE'!$B$3*(1+'DCF_NKE'!$B$4)^5*('DCF_NKE'!$B$5*(1-'DCF_NKE'!$B$6)+'DCF_NKE'!$B$7-'DCF_NKE'!$B$8)-'DCF_NKE'!$B$3*(1+'DCF_NKE'!$B$4)^4*'DCF_NKE'!$B$4*'DCF_NKE'!$B$9)/(1+0.09000000000000001)^5+('DCF_NKE'!$B$3*(1+'DCF_NKE'!$B$4)^5*(1+0.02)*('DCF_NKE'!$B$5*(1-'DCF_NKE'!$B$6)+'DCF_NKE'!$B$7-'DCF_NKE'!$B$8)-'DCF_NKE'!$B$3*(1+'DCF_NKE'!$B$4)^5*0.02*'DCF_NKE'!$B$9)/(0.09000000000000001-0.02)/(1+0.09000000000000001)^5-'DCF_NKE'!$B$13)/'DCF_NKE'!$B$12) -> 33.666557 | F13: =((('DCF_NKE'!$B$3*(1+'DCF_NKE'!$B$4)^1*('DCF_NKE'!$B$5*(1-'DCF_NKE'!$B$6)+'DCF_NKE'!$B$7-'DCF_NKE'!$B$8)-'DCF_NKE'!$B$3*(1+'DCF_NKE'!$B$4)^0*'DCF_NKE'!$B$4*'DCF_NKE'!$B$9)/(1+0.09000000000000001)^1+('DCF_NKE'!$B$3*(1+'DCF_NKE'!$B$4)^2*('DCF_NKE'!$B$5*(1-'DCF_NKE'!$B$6)+'DCF_NKE'!$B$7-'DCF_NKE'!$B$8)-'DCF_NKE'!$B$3*(1+'DCF_NKE'!$B$4)^1*'DCF_NKE'!$B$4*'DCF_NKE'!$B$9)/(1+0.09000000000000001)^2+('DCF_NKE'!$B$3*(1+'DCF_NKE'!$B$4)^3*('DCF_NKE'!$B$5*(1-'DCF_NKE'!$B$6)+'DCF_NKE'!$B$7-'DCF_NKE'!$B$8)-'DCF_NKE'!$B$3*(1+'DCF_NKE'!$B$4)^2*'DCF_NKE'!$B$4*'DCF_NKE'!$B$9)/(1+0.09000000000000001)^3+('DCF_NKE'!$B$3*(1+'DCF_NKE'!$B$4)^4*('DCF_NKE'!$B$5*(1-'DCF_NKE'!$B$6)+'DCF_NKE'!$B$7-'DCF_NKE'!$B$8)-'DCF_NKE'!$B$3*(1+'DCF_NKE'!$B$4)^3*'DCF_NKE'!$B$4*'DCF_NKE'!$B$9)/(1+0.09000000000000001)^4+('DCF_NKE'!$B$3*(1+'DCF_NKE'!$B$4)^5*('DCF_NKE'!$B$5*(1-'DCF_NKE'!$B$6)+'DCF_NKE'!$B$7-'DCF_NKE'!$B$8)-'DCF_NKE'!$B$3*(1+'DCF_NKE'!$B$4)^4*'DCF_NKE'!$B$4*'DCF_NKE'!$B$9)/(1+0.09000000000000001)^5+('DCF_NKE'!$B$3*(1+'DCF_NKE'!$B$4)^5*(1+0.025)*('DCF_NKE'!$B$5*(1-'DCF_NKE'!$B$6)+'DCF_NKE'!$B$7-'DCF_NKE'!$B$8)-'DCF_NKE'!$B$3*(1+'DCF_NKE'!$B$4)^5*0.025*'DCF_NKE'!$B$9)/(0.09000000000000001-0.025)/(1+0.09000000000000001)^5-'DCF_NKE'!$B$13)/'DCF_NKE'!$B$12) -> 35.455049 | G13: =((('DCF_NKE'!$B$3*(1+'DCF_NKE'!$B$4)^1*('DCF_NKE'!$B$5*(1-'DCF_NKE'!$B$6)+'DCF_NKE'!$B$7-'DCF_NKE'!$B$8)-'DCF_NKE'!$B$3*(1+'DCF_NKE'!$B$4)^0*'DCF_NKE'!$B$4*'DCF_NKE'!$B$9)/(1+0.09000000000000001)^1+('DCF_NKE'!$B$3*(1+'DCF_NKE'!$B$4)^2*('DCF_NKE'!$B$5*(1-'DCF_NKE'!$B$6)+'DCF_NKE'!$B$7-'DCF_NKE'!$B$8)-'DCF_NKE'!$B$3*(1+'DCF_NKE'!$B$4)^1*'DCF_NKE'!$B$4*'DCF_NKE'!$B$9)/(1+0.09000000000000001)^2+('DCF_NKE'!$B$3*(1+'DCF_NKE'!$B$4)^3*('DCF_NKE'!$B$5*(1-'DCF_NKE'!$B$6)+'DCF_NKE'!$B$7-'DCF_NKE'!$B$8)-'DCF_NKE'!$B$3*(1+'DCF_NKE'!$B$4)^2*'DCF_NKE'!$B$4*'DCF_NKE'!$B$9)/(1+0.09000000000000001)^3+('DCF_NKE'!$B$3*(1+'DCF_NKE'!$B$4)^4*('DCF_NKE'!$B$5*(1-'DCF_NKE'!$B$6)+'DCF_NKE'!$B$7-'DCF_NKE'!$B$8)-'DCF_NKE'!$B$3*(1+'DCF_NKE'!$B$4)^3*'DCF_NKE'!$B$4*'DCF_NKE'!$B$9)/(1+0.09000000000000001)^4+('DCF_NKE'!$B$3*(1+'DCF_NKE'!$B$4)^5*('DCF_NKE'!$B$5*(1-'DCF_NKE'!$B$6)+'DCF_NKE'!$B$7-'DCF_NKE'!$B$8)-'DCF_NKE'!$B$3*(1+'DCF_NKE'!$B$4)^4*'DCF_NKE'!$B$4*'DCF_NKE'!$B$9)/(1+0.09000000000000001)^5+('DCF_NKE'!$B$3*(1+'DCF_NKE'!$B$4)^5*(1+0.03)*('DCF_NKE'!$B$5*(1-'DCF_NKE'!$B$6)+'DCF_NKE'!$B$7-'DCF_NKE'!$B$8)-'DCF_NKE'!$B$3*(1+'DCF_NKE'!$B$4)^5*0.03*'DCF_NKE'!$B$9)/(0.09000000000000001-0.03)/(1+0.09000000000000001)^5-'DCF_NKE'!$B$13)/'DCF_NKE'!$B$12) -> 37.541624
A14: NKE | B14: 0.095 | C14: =((('DCF_NKE'!$B$3*(1+'DCF_NKE'!$B$4)^1*('DCF_NKE'!$B$5*(1-'DCF_NKE'!$B$6)+'DCF_NKE'!$B$7-'DCF_NKE'!$B$8)-'DCF_NKE'!$B$3*(1+'DCF_NKE'!$B$4)^0*'DCF_NKE'!$B$4*'DCF_NKE'!$B$9)/(1+0.095)^1+('DCF_NKE'!$B$3*(1+'DCF_NKE'!$B$4)^2*('DCF_NKE'!$B$5*(1-'DCF_NKE'!$B$6)+'DCF_NKE'!$B$7-'DCF_NKE'!$B$8)-'DCF_NKE'!$B$3*(1+'DCF_NKE'!$B$4)^1*'DCF_NKE'!$B$4*'DCF_NKE'!$B$9)/(1+0.095)^2+('DCF_NKE'!$B$3*(1+'DCF_NKE'!$B$4)^3*('DCF_NKE'!$B$5*(1-'DCF_NKE'!$B$6)+'DCF_NKE'!$B$7-'DCF_NKE'!$B$8)-'DCF_NKE'!$B$3*(1+'DCF_NKE'!$B$4)^2*'DCF_NKE'!$B$4*'DCF_NKE'!$B$9)/(1+0.095)^3+('DCF_NKE'!$B$3*(1+'DCF_NKE'!$B$4)^4*('DCF_NKE'!$B$5*(1-'DCF_NKE'!$B$6)+'DCF_NKE'!$B$7-'DCF_NKE'!$B$8)-'DCF_NKE'!$B$3*(1+'DCF_NKE'!$B$4)^3*'DCF_NKE'!$B$4*'DCF_NKE'!$B$9)/(1+0.095)^4+('DCF_NKE'!$B$3*(1+'DCF_NKE'!$B$4)^5*('DCF_NKE'!$B$5*(1-'DCF_NKE'!$B$6)+'DCF_NKE'!$B$7-'DCF_NKE'!$B$8)-'DCF_NKE'!$B$3*(1+'DCF_NKE'!$B$4)^4*'DCF_NKE'!$B$4*'DCF_NKE'!$B$9)/(1+0.095)^5+('DCF_NKE'!$B$3*(1+'DCF_NKE'!$B$4)^5*(1+0.01)*('DCF_NKE'!$B$5*(1-'DCF_NKE'!$B$6)+'DCF_NKE'!$B$7-'DCF_NKE'!$B$8)-'DCF_NKE'!$B$3*(1+'DCF_NKE'!$B$4)^5*0.01*'DCF_NKE'!$B$9)/(0.095-0.01)/(1+0.095)^5-'DCF_NKE'!$B$13)/'DCF_NKE'!$B$12) -> 28.954454 | D14: =((('DCF_NKE'!$B$3*(1+'DCF_NKE'!$B$4)^1*('DCF_NKE'!$B$5*(1-'DCF_NKE'!$B$6)+'DCF_NKE'!$B$7-'DCF_NKE'!$B$8)-'DCF_NKE'!$B$3*(1+'DCF_NKE'!$B$4)^0*'DCF_NKE'!$B$4*'DCF_NKE'!$B$9)/(1+0.095)^1+('DCF_NKE'!$B$3*(1+'DCF_NKE'!$B$4)^2*('DCF_NKE'!$B$5*(1-'DCF_NKE'!$B$6)+'DCF_NKE'!$B$7-'DCF_NKE'!$B$8)-'DCF_NKE'!$B$3*(1+'DCF_NKE'!$B$4)^1*'DCF_NKE'!$B$4*'DCF_NKE'!$B$9)/(1+0.095)^2+('DCF_NKE'!$B$3*(1+'DCF_NKE'!$B$4)^3*('DCF_NKE'!$B$5*(1-'DCF_NKE'!$B$6)+'DCF_NKE'!$B$7-'DCF_NKE'!$B$8)-'DCF_NKE'!$B$3*(1+'DCF_NKE'!$B$4)^2*'DCF_NKE'!$B$4*'DCF_NKE'!$B$9)/(1+0.095)^3+('DCF_NKE'!$B$3*(1+'DCF_NKE'!$B$4)^4*('DCF_NKE'!$B$5*(1-'DCF_NKE'!$B$6)+'DCF_NKE'!$B$7-'DCF_NKE'!$B$8)-'DCF_NKE'!$B$3*(1+'DCF_NKE'!$B$4)^3*'DCF_NKE'!$B$4*'DCF_NKE'!$B$9)/(1+0.095)^4+('DCF_NKE'!$B$3*(1+'DCF_NKE'!$B$4)^5*('DCF_NKE'!$B$5*(1-'DCF_NKE'!$B$6)+'DCF_NKE'!$B$7-'DCF_NKE'!$B$8)-'DCF_NKE'!$B$3*(1+'DCF_NKE'!$B$4)^4*'DCF_NKE'!$B$4*'DCF_NKE'!$B$9)/(1+0.095)^5+('DCF_NKE'!$B$3*(1+'DCF_NKE'!$B$4)^5*(1+0.015)*('DCF_NKE'!$B$5*(1-'DCF_NKE'!$B$6)+'DCF_NKE'!$B$7-'DCF_NKE'!$B$8)-'DCF_NKE'!$B$3*(1+'DCF_NKE'!$B$4)^5*0.015*'DCF_NKE'!$B$9)/(0.095-0.015)/(1+0.095)^5-'DCF_NKE'!$B$13)/'DCF_NKE'!$B$12) -> 30.121486 | E14: =((('DCF_NKE'!$B$3*(1+'DCF_NKE'!$B$4)^1*('DCF_NKE'!$B$5*(1-'DCF_NKE'!$B$6)+'DCF_NKE'!$B$7-'DCF_NKE'!$B$8)-'DCF_NKE'!$B$3*(1+'DCF_NKE'!$B$4)^0*'DCF_NKE'!$B$4*'DCF_NKE'!$B$9)/(1+0.095)^1+('DCF_NKE'!$B$3*(1+'DCF_NKE'!$B$4)^2*('DCF_NKE'!$B$5*(1-'DCF_NKE'!$B$6)+'DCF_NKE'!$B$7-'DCF_NKE'!$B$8)-'DCF_NKE'!$B$3*(1+'DCF_NKE'!$B$4)^1*'DCF_NKE'!$B$4*'DCF_NKE'!$B$9)/(1+0.095)^2+('DCF_NKE'!$B$3*(1+'DCF_NKE'!$B$4)^3*('DCF_NKE'!$B$5*(1-'DCF_NKE'!$B$6)+'DCF_NKE'!$B$7-'DCF_NKE'!$B$8)-'DCF_NKE'!$B$3*(1+'DCF_NKE'!$B$4)^2*'DCF_NKE'!$B$4*'DCF_NKE'!$B$9)/(1+0.095)^3+('DCF_NKE'!$B$3*(1+'DCF_NKE'!$B$4)^4*('DCF_NKE'!$B$5*(1-'DCF_NKE'!$B$6)+'DCF_NKE'!$B$7-'DCF_NKE'!$B$8)-'DCF_NKE'!$B$3*(1+'DCF_NKE'!$B$4)^3*'DCF_NKE'!$B$4*'DCF_NKE'!$B$9)/(1+0.095)^4+('DCF_NKE'!$B$3*(1+'DCF_NKE'!$B$4)^5*('DCF_NKE'!$B$5*(1-'DCF_NKE'!$B$6)+'DCF_NKE'!$B$7-'DCF_NKE'!$B$8)-'DCF_NKE'!$B$3*(1+'DCF_NKE'!$B$4)^4*'DCF_NKE'!$B$4*'DCF_NKE'!$B$9)/(1+0.095)^5+('DCF_NKE'!$B$3*(1+'DCF_NKE'!$B$4)^5*(1+0.02)*('DCF_NKE'!$B$5*(1-'DCF_NKE'!$B$6)+'DCF_NKE'!$B$7-'DCF_NKE'!$B$8)-'DCF_NKE'!$B$3*(1+'DCF_NKE'!$B$4)^5*0.02*'DCF_NKE'!$B$9)/(0.095-0.02)/(1+0.095)^5-'DCF_NKE'!$B$13)/'DCF_NKE'!$B$12) -> 31.444121 | F14: =((('DCF_NKE'!$B$3*(1+'DCF_NKE'!$B$4)^1*('DCF_NKE'!$B$5*(1-'DCF_NKE'!$B$6)+'DCF_NKE'!$B$7-'DCF_NKE'!$B$8)-'DCF_NKE'!$B$3*(1+'DCF_NKE'!$B$4)^0*'DCF_NKE'!$B$4*'DCF_NKE'!$B$9)/(1+0.095)^1+('DCF_NKE'!$B$3*(1+'DCF_NKE'!$B$4)^2*('DCF_NKE'!$B$5*(1-'DCF_NKE'!$B$6)+'DCF_NKE'!$B$7-'DCF_NKE'!$B$8)-'DCF_NKE'!$B$3*(1+'DCF_NKE'!$B$4)^1*'DCF_NKE'!$B$4*'DCF_NKE'!$B$9)/(1+0.095)^2+('DCF_NKE'!$B$3*(1+'DCF_NKE'!$B$4)^3*('DCF_NKE'!$B$5*(1-'DCF_NKE'!$B$6)+'DCF_NKE'!$B$7-'DCF_NKE'!$B$8)-'DCF_NKE'!$B$3*(1+'DCF_NKE'!$B$4)^2*'DCF_NKE'!$B$4*'DCF_NKE'!$B$9)/(1+0.095)^3+('DCF_NKE'!$B$3*(1+'DCF_NKE'!$B$4)^4*('DCF_NKE'!$B$5*(1-'DCF_NKE'!$B$6)+'DCF_NKE'!$B$7-'DCF_NKE'!$B$8)-'DCF_NKE'!$B$3*(1+'DCF_NKE'!$B$4)^3*'DCF_NKE'!$B$4*'DCF_NKE'!$B$9)/(1+0.095)^4+('DCF_NKE'!$B$3*(1+'DCF_NKE'!$B$4)^5*('DCF_NKE'!$B$5*(1-'DCF_NKE'!$B$6)+'DCF_NKE'!$B$7-'DCF_NKE'!$B$8)-'DCF_NKE'!$B$3*(1+'DCF_NKE'!$B$4)^4*'DCF_NKE'!$B$4*'DCF_NKE'!$B$9)/(1+0.095)^5+('DCF_NKE'!$B$3*(1+'DCF_NKE'!$B$4)^5*(1+0.025)*('DCF_NKE'!$B$5*(1-'DCF_NKE'!$B$6)+'DCF_NKE'!$B$7-'DCF_NKE'!$B$8)-'DCF_NKE'!$B$3*(1+'DCF_NKE'!$B$4)^5*0.025*'DCF_NKE'!$B$9)/(0.095-0.025)/(1+0.095)^5-'DCF_NKE'!$B$13)/'DCF_NKE'!$B$12) -> 32.955704 | G14: =((('DCF_NKE'!$B$3*(1+'DCF_NKE'!$B$4)^1*('DCF_NKE'!$B$5*(1-'DCF_NKE'!$B$6)+'DCF_NKE'!$B$7-'DCF_NKE'!$B$8)-'DCF_NKE'!$B$3*(1+'DCF_NKE'!$B$4)^0*'DCF_NKE'!$B$4*'DCF_NKE'!$B$9)/(1+0.095)^1+('DCF_NKE'!$B$3*(1+'DCF_NKE'!$B$4)^2*('DCF_NKE'!$B$5*(1-'DCF_NKE'!$B$6)+'DCF_NKE'!$B$7-'DCF_NKE'!$B$8)-'DCF_NKE'!$B$3*(1+'DCF_NKE'!$B$4)^1*'DCF_NKE'!$B$4*'DCF_NKE'!$B$9)/(1+0.095)^2+('DCF_NKE'!$B$3*(1+'DCF_NKE'!$B$4)^3*('DCF_NKE'!$B$5*(1-'DCF_NKE'!$B$6)+'DCF_NKE'!$B$7-'DCF_NKE'!$B$8)-'DCF_NKE'!$B$3*(1+'DCF_NKE'!$B$4)^2*'DCF_NKE'!$B$4*'DCF_NKE'!$B$9)/(1+0.095)^3+('DCF_NKE'!$B$3*(1+'DCF_NKE'!$B$4)^4*('DCF_NKE'!$B$5*(1-'DCF_NKE'!$B$6)+'DCF_NKE'!$B$7-'DCF_NKE'!$B$8)-'DCF_NKE'!$B$3*(1+'DCF_NKE'!$B$4)^3*'DCF_NKE'!$B$4*'DCF_NKE'!$B$9)/(1+0.095)^4+('DCF_NKE'!$B$3*(1+'DCF_NKE'!$B$4)^5*('DCF_NKE'!$B$5*(1-'DCF_NKE'!$B$6)+'DCF_NKE'!$B$7-'DCF_NKE'!$B$8)-'DCF_NKE'!$B$3*(1+'DCF_NKE'!$B$4)^4*'DCF_NKE'!$B$4*'DCF_NKE'!$B$9)/(1+0.095)^5+('DCF_NKE'!$B$3*(1+'DCF_NKE'!$B$4)^5*(1+0.03)*('DCF_NKE'!$B$5*(1-'DCF_NKE'!$B$6)+'DCF_NKE'!$B$7-'DCF_NKE'!$B$8)-'DCF_NKE'!$B$3*(1+'DCF_NKE'!$B$4)^5*0.03*'DCF_NKE'!$B$9)/(0.095-0.03)/(1+0.095)^5-'DCF_NKE'!$B$13)/'DCF_NKE'!$B$12) -> 34.699839
A15: NKE | B15: 0.1 | C15: =((('DCF_NKE'!$B$3*(1+'DCF_NKE'!$B$4)^1*('DCF_NKE'!$B$5*(1-'DCF_NKE'!$B$6)+'DCF_NKE'!$B$7-'DCF_NKE'!$B$8)-'DCF_NKE'!$B$3*(1+'DCF_NKE'!$B$4)^0*'DCF_NKE'!$B$4*'DCF_NKE'!$B$9)/(1+0.1)^1+('DCF_NKE'!$B$3*(1+'DCF_NKE'!$B$4)^2*('DCF_NKE'!$B$5*(1-'DCF_NKE'!$B$6)+'DCF_NKE'!$B$7-'DCF_NKE'!$B$8)-'DCF_NKE'!$B$3*(1+'DCF_NKE'!$B$4)^1*'DCF_NKE'!$B$4*'DCF_NKE'!$B$9)/(1+0.1)^2+('DCF_NKE'!$B$3*(1+'DCF_NKE'!$B$4)^3*('DCF_NKE'!$B$5*(1-'DCF_NKE'!$B$6)+'DCF_NKE'!$B$7-'DCF_NKE'!$B$8)-'DCF_NKE'!$B$3*(1+'DCF_NKE'!$B$4)^2*'DCF_NKE'!$B$4*'DCF_NKE'!$B$9)/(1+0.1)^3+('DCF_NKE'!$B$3*(1+'DCF_NKE'!$B$4)^4*('DCF_NKE'!$B$5*(1-'DCF_NKE'!$B$6)+'DCF_NKE'!$B$7-'DCF_NKE'!$B$8)-'DCF_NKE'!$B$3*(1+'DCF_NKE'!$B$4)^3*'DCF_NKE'!$B$4*'DCF_NKE'!$B$9)/(1+0.1)^4+('DCF_NKE'!$B$3*(1+'DCF_NKE'!$B$4)^5*('DCF_NKE'!$B$5*(1-'DCF_NKE'!$B$6)+'DCF_NKE'!$B$7-'DCF_NKE'!$B$8)-'DCF_NKE'!$B$3*(1+'DCF_NKE'!$B$4)^4*'DCF_NKE'!$B$4*'DCF_NKE'!$B$9)/(1+0.1)^5+('DCF_NKE'!$B$3*(1+'DCF_NKE'!$B$4)^5*(1+0.01)*('DCF_NKE'!$B$5*(1-'DCF_NKE'!$B$6)+'DCF_NKE'!$B$7-'DCF_NKE'!$B$8)-'DCF_NKE'!$B$3*(1+'DCF_NKE'!$B$4)^5*0.01*'DCF_NKE'!$B$9)/(0.1-0.01)/(1+0.1)^5-'DCF_NKE'!$B$13)/'DCF_NKE'!$B$12) -> 27.350097 | D15: =((('DCF_NKE'!$B$3*(1+'DCF_NKE'!$B$4)^1*('DCF_NKE'!$B$5*(1-'DCF_NKE'!$B$6)+'DCF_NKE'!$B$7-'DCF_NKE'!$B$8)-'DCF_NKE'!$B$3*(1+'DCF_NKE'!$B$4)^0*'DCF_NKE'!$B$4*'DCF_NKE'!$B$9)/(1+0.1)^1+('DCF_NKE'!$B$3*(1+'DCF_NKE'!$B$4)^2*('DCF_NKE'!$B$5*(1-'DCF_NKE'!$B$6)+'DCF_NKE'!$B$7-'DCF_NKE'!$B$8)-'DCF_NKE'!$B$3*(1+'DCF_NKE'!$B$4)^1*'DCF_NKE'!$B$4*'DCF_NKE'!$B$9)/(1+0.1)^2+('DCF_NKE'!$B$3*(1+'DCF_NKE'!$B$4)^3*('DCF_NKE'!$B$5*(1-'DCF_NKE'!$B$6)+'DCF_NKE'!$B$7-'DCF_NKE'!$B$8)-'DCF_NKE'!$B$3*(1+'DCF_NKE'!$B$4)^2*'DCF_NKE'!$B$4*'DCF_NKE'!$B$9)/(1+0.1)^3+('DCF_NKE'!$B$3*(1+'DCF_NKE'!$B$4)^4*('DCF_NKE'!$B$5*(1-'DCF_NKE'!$B$6)+'DCF_NKE'!$B$7-'DCF_NKE'!$B$8)-'DCF_NKE'!$B$3*(1+'DCF_NKE'!$B$4)^3*'DCF_NKE'!$B$4*'DCF_NKE'!$B$9)/(1+0.1)^4+('DCF_NKE'!$B$3*(1+'DCF_NKE'!$B$4)^5*('DCF_NKE'!$B$5*(1-'DCF_NKE'!$B$6)+'DCF_NKE'!$B$7-'DCF_NKE'!$B$8)-'DCF_NKE'!$B$3*(1+'DCF_NKE'!$B$4)^4*'DCF_NKE'!$B$4*'DCF_NKE'!$B$9)/(1+0.1)^5+('DCF_NKE'!$B$3*(1+'DCF_NKE'!$B$4)^5*(1+0.015)*('DCF_NKE'!$B$5*(1-'DCF_NKE'!$B$6)+'DCF_NKE'!$B$7-'DCF_NKE'!$B$8)-'DCF_NKE'!$B$3*(1+'DCF_NKE'!$B$4)^5*0.015*'DCF_NKE'!$B$9)/(0.1-0.015)/(1+0.1)^5-'DCF_NKE'!$B$13)/'DCF_NKE'!$B$12) -> 28.36183 | E15: =((('DCF_NKE'!$B$3*(1+'DCF_NKE'!$B$4)^1*('DCF_NKE'!$B$5*(1-'DCF_NKE'!$B$6)+'DCF_NKE'!$B$7-'DCF_NKE'!$B$8)-'DCF_NKE'!$B$3*(1+'DCF_NKE'!$B$4)^0*'DCF_NKE'!$B$4*'DCF_NKE'!$B$9)/(1+0.1)^1+('DCF_NKE'!$B$3*(1+'DCF_NKE'!$B$4)^2*('DCF_NKE'!$B$5*(1-'DCF_NKE'!$B$6)+'DCF_NKE'!$B$7-'DCF_NKE'!$B$8)-'DCF_NKE'!$B$3*(1+'DCF_NKE'!$B$4)^1*'DCF_NKE'!$B$4*'DCF_NKE'!$B$9)/(1+0.1)^2+('DCF_NKE'!$B$3*(1+'DCF_NKE'!$B$4)^3*('DCF_NKE'!$B$5*(1-'DCF_NKE'!$B$6)+'DCF_NKE'!$B$7-'DCF_NKE'!$B$8)-'DCF_NKE'!$B$3*(1+'DCF_NKE'!$B$4)^2*'DCF_NKE'!$B$4*'DCF_NKE'!$B$9)/(1+0.1)^3+('DCF_NKE'!$B$3*(1+'DCF_NKE'!$B$4)^4*('DCF_NKE'!$B$5*(1-'DCF_NKE'!$B$6)+'DCF_NKE'!$B$7-'DCF_NKE'!$B$8)-'DCF_NKE'!$B$3*(1+'DCF_NKE'!$B$4)^3*'DCF_NKE'!$B$4*'DCF_NKE'!$B$9)/(1+0.1)^4+('DCF_NKE'!$B$3*(1+'DCF_NKE'!$B$4)^5*('DCF_NKE'!$B$5*(1-'DCF_NKE'!$B$6)+'DCF_NKE'!$B$7-'DCF_NKE'!$B$8)-'DCF_NKE'!$B$3*(1+'DCF_NKE'!$B$4)^4*'DCF_NKE'!$B$4*'DCF_NKE'!$B$9)/(1+0.1)^5+('DCF_NKE'!$B$3*(1+'DCF_NKE'!$B$4)^5*(1+0.02)*('DCF_NKE'!$B$5*(1-'DCF_NKE'!$B$6)+'DCF_NKE'!$B$7-'DCF_NKE'!$B$8)-'DCF_NKE'!$B$3*(1+'DCF_NKE'!$B$4)^5*0.02*'DCF_NKE'!$B$9)/(0.1-0.02)/(1+0.1)^5-'DCF_NKE'!$B$13)/'DCF_NKE'!$B$12) -> 29.500029 | F15: =((('DCF_NKE'!$B$3*(1+'DCF_NKE'!$B$4)^1*('DCF_NKE'!$B$5*(1-'DCF_NKE'!$B$6)+'DCF_NKE'!$B$7-'DCF_NKE'!$B$8)-'DCF_NKE'!$B$3*(1+'DCF_NKE'!$B$4)^0*'DCF_NKE'!$B$4*'DCF_NKE'!$B$9)/(1+0.1)^1+('DCF_NKE'!$B$3*(1+'DCF_NKE'!$B$4)^2*('DCF_NKE'!$B$5*(1-'DCF_NKE'!$B$6)+'DCF_NKE'!$B$7-'DCF_NKE'!$B$8)-'DCF_NKE'!$B$3*(1+'DCF_NKE'!$B$4)^1*'DCF_NKE'!$B$4*'DCF_NKE'!$B$9)/(1+0.1)^2+('DCF_NKE'!$B$3*(1+'DCF_NKE'!$B$4)^3*('DCF_NKE'!$B$5*(1-'DCF_NKE'!$B$6)+'DCF_NKE'!$B$7-'DCF_NKE'!$B$8)-'DCF_NKE'!$B$3*(1+'DCF_NKE'!$B$4)^2*'DCF_NKE'!$B$4*'DCF_NKE'!$B$9)/(1+0.1)^3+('DCF_NKE'!$B$3*(1+'DCF_NKE'!$B$4)^4*('DCF_NKE'!$B$5*(1-'DCF_NKE'!$B$6)+'DCF_NKE'!$B$7-'DCF_NKE'!$B$8)-'DCF_NKE'!$B$3*(1+'DCF_NKE'!$B$4)^3*'DCF_NKE'!$B$4*'DCF_NKE'!$B$9)/(1+0.1)^4+('DCF_NKE'!$B$3*(1+'DCF_NKE'!$B$4)^5*('DCF_NKE'!$B$5*(1-'DCF_NKE'!$B$6)+'DCF_NKE'!$B$7-'DCF_NKE'!$B$8)-'DCF_NKE'!$B$3*(1+'DCF_NKE'!$B$4)^4*'DCF_NKE'!$B$4*'DCF_NKE'!$B$9)/(1+0.1)^5+('DCF_NKE'!$B$3*(1+'DCF_NKE'!$B$4)^5*(1+0.025)*('DCF_NKE'!$B$5*(1-'DCF_NKE'!$B$6)+'DCF_NKE'!$B$7-'DCF_NKE'!$B$8)-'DCF_NKE'!$B$3*(1+'DCF_NKE'!$B$4)^5*0.025*'DCF_NKE'!$B$9)/(0.1-0.025)/(1+0.1)^5-'DCF_NKE'!$B$13)/'DCF_NKE'!$B$12) -> 30.789989 | G15: =((('DCF_NKE'!$B$3*(1+'DCF_NKE'!$B$4)^1*('DCF_NKE'!$B$5*(1-'DCF_NKE'!$B$6)+'DCF_NKE'!$B$7-'DCF_NKE'!$B$8)-'DCF_NKE'!$B$3*(1+'DCF_NKE'!$B$4)^0*'DCF_NKE'!$B$4*'DCF_NKE'!$B$9)/(1+0.1)^1+('DCF_NKE'!$B$3*(1+'DCF_NKE'!$B$4)^2*('DCF_NKE'!$B$5*(1-'DCF_NKE'!$B$6)+'DCF_NKE'!$B$7-'DCF_NKE'!$B$8)-'DCF_NKE'!$B$3*(1+'DCF_NKE'!$B$4)^1*'DCF_NKE'!$B$4*'DCF_NKE'!$B$9)/(1+0.1)^2+('DCF_NKE'!$B$3*(1+'DCF_NKE'!$B$4)^3*('DCF_NKE'!$B$5*(1-'DCF_NKE'!$B$6)+'DCF_NKE'!$B$7-'DCF_NKE'!$B$8)-'DCF_NKE'!$B$3*(1+'DCF_NKE'!$B$4)^2*'DCF_NKE'!$B$4*'DCF_NKE'!$B$9)/(1+0.1)^3+('DCF_NKE'!$B$3*(1+'DCF_NKE'!$B$4)^4*('DCF_NKE'!$B$5*(1-'DCF_NKE'!$B$6)+'DCF_NKE'!$B$7-'DCF_NKE'!$B$8)-'DCF_NKE'!$B$3*(1+'DCF_NKE'!$B$4)^3*'DCF_NKE'!$B$4*'DCF_NKE'!$B$9)/(1+0.1)^4+('DCF_NKE'!$B$3*(1+'DCF_NKE'!$B$4)^5*('DCF_NKE'!$B$5*(1-'DCF_NKE'!$B$6)+'DCF_NKE'!$B$7-'DCF_NKE'!$B$8)-'DCF_NKE'!$B$3*(1+'DCF_NKE'!$B$4)^4*'DCF_NKE'!$B$4*'DCF_NKE'!$B$9)/(1+0.1)^5+('DCF_NKE'!$B$3*(1+'DCF_NKE'!$B$4)^5*(1+0.03)*('DCF_NKE'!$B$5*(1-'DCF_NKE'!$B$6)+'DCF_NKE'!$B$7-'DCF_NKE'!$B$8)-'DCF_NKE'!$B$3*(1+'DCF_NKE'!$B$4)^5*0.03*'DCF_NKE'!$B$9)/(0.1-0.03)/(1+0.1)^5-'DCF_NKE'!$B$13)/'DCF_NKE'!$B$12) -> 32.264228
A16: NKE | B16: 0.105 | C16: =((('DCF_NKE'!$B$3*(1+'DCF_NKE'!$B$4)^1*('DCF_NKE'!$B$5*(1-'DCF_NKE'!$B$6)+'DCF_NKE'!$B$7-'DCF_NKE'!$B$8)-'DCF_NKE'!$B$3*(1+'DCF_NKE'!$B$4)^0*'DCF_NKE'!$B$4*'DCF_NKE'!$B$9)/(1+0.10500000000000001)^1+('DCF_NKE'!$B$3*(1+'DCF_NKE'!$B$4)^2*('DCF_NKE'!$B$5*(1-'DCF_NKE'!$B$6)+'DCF_NKE'!$B$7-'DCF_NKE'!$B$8)-'DCF_NKE'!$B$3*(1+'DCF_NKE'!$B$4)^1*'DCF_NKE'!$B$4*'DCF_NKE'!$B$9)/(1+0.10500000000000001)^2+('DCF_NKE'!$B$3*(1+'DCF_NKE'!$B$4)^3*('DCF_NKE'!$B$5*(1-'DCF_NKE'!$B$6)+'DCF_NKE'!$B$7-'DCF_NKE'!$B$8)-'DCF_NKE'!$B$3*(1+'DCF_NKE'!$B$4)^2*'DCF_NKE'!$B$4*'DCF_NKE'!$B$9)/(1+0.10500000000000001)^3+('DCF_NKE'!$B$3*(1+'DCF_NKE'!$B$4)^4*('DCF_NKE'!$B$5*(1-'DCF_NKE'!$B$6)+'DCF_NKE'!$B$7-'DCF_NKE'!$B$8)-'DCF_NKE'!$B$3*(1+'DCF_NKE'!$B$4)^3*'DCF_NKE'!$B$4*'DCF_NKE'!$B$9)/(1+0.10500000000000001)^4+('DCF_NKE'!$B$3*(1+'DCF_NKE'!$B$4)^5*('DCF_NKE'!$B$5*(1-'DCF_NKE'!$B$6)+'DCF_NKE'!$B$7-'DCF_NKE'!$B$8)-'DCF_NKE'!$B$3*(1+'DCF_NKE'!$B$4)^4*'DCF_NKE'!$B$4*'DCF_NKE'!$B$9)/(1+0.10500000000000001)^5+('DCF_NKE'!$B$3*(1+'DCF_NKE'!$B$4)^5*(1+0.01)*('DCF_NKE'!$B$5*(1-'DCF_NKE'!$B$6)+'DCF_NKE'!$B$7-'DCF_NKE'!$B$8)-'DCF_NKE'!$B$3*(1+'DCF_NKE'!$B$4)^5*0.01*'DCF_NKE'!$B$9)/(0.10500000000000001-0.01)/(1+0.10500000000000001)^5-'DCF_NKE'!$B$13)/'DCF_NKE'!$B$12) -> 25.915356 | D16: =((('DCF_NKE'!$B$3*(1+'DCF_NKE'!$B$4)^1*('DCF_NKE'!$B$5*(1-'DCF_NKE'!$B$6)+'DCF_NKE'!$B$7-'DCF_NKE'!$B$8)-'DCF_NKE'!$B$3*(1+'DCF_NKE'!$B$4)^0*'DCF_NKE'!$B$4*'DCF_NKE'!$B$9)/(1+0.10500000000000001)^1+('DCF_NKE'!$B$3*(1+'DCF_NKE'!$B$4)^2*('DCF_NKE'!$B$5*(1-'DCF_NKE'!$B$6)+'DCF_NKE'!$B$7-'DCF_NKE'!$B$8)-'DCF_NKE'!$B$3*(1+'DCF_NKE'!$B$4)^1*'DCF_NKE'!$B$4*'DCF_NKE'!$B$9)/(1+0.10500000000000001)^2+('DCF_NKE'!$B$3*(1+'DCF_NKE'!$B$4)^3*('DCF_NKE'!$B$5*(1-'DCF_NKE'!$B$6)+'DCF_NKE'!$B$7-'DCF_NKE'!$B$8)-'DCF_NKE'!$B$3*(1+'DCF_NKE'!$B$4)^2*'DCF_NKE'!$B$4*'DCF_NKE'!$B$9)/(1+0.10500000000000001)^3+('DCF_NKE'!$B$3*(1+'DCF_NKE'!$B$4)^4*('DCF_NKE'!$B$5*(1-'DCF_NKE'!$B$6)+'DCF_NKE'!$B$7-'DCF_NKE'!$B$8)-'DCF_NKE'!$B$3*(1+'DCF_NKE'!$B$4)^3*'DCF_NKE'!$B$4*'DCF_NKE'!$B$9)/(1+0.10500000000000001)^4+('DCF_NKE'!$B$3*(1+'DCF_NKE'!$B$4)^5*('DCF_NKE'!$B$5*(1-'DCF_NKE'!$B$6)+'DCF_NKE'!$B$7-'DCF_NKE'!$B$8)-'DCF_NKE'!$B$3*(1+'DCF_NKE'!$B$4)^4*'DCF_NKE'!$B$4*'DCF_NKE'!$B$9)/(1+0.10500000000000001)^5+('DCF_NKE'!$B$3*(1+'DCF_NKE'!$B$4)^5*(1+0.015)*('DCF_NKE'!$B$5*(1-'DCF_NKE'!$B$6)+'DCF_NKE'!$B$7-'DCF_NKE'!$B$8)-'DCF_NKE'!$B$3*(1+'DCF_NKE'!$B$4)^5*0.015*'DCF_NKE'!$B$9)/(0.10500000000000001-0.015)/(1+0.10500000000000001)^5-'DCF_NKE'!$B$13)/'DCF_NKE'!$B$12) -> 26.798314 | E16: =((('DCF_NKE'!$B$3*(1+'DCF_NKE'!$B$4)^1*('DCF_NKE'!$B$5*(1-'DCF_NKE'!$B$6)+'DCF_NKE'!$B$7-'DCF_NKE'!$B$8)-'DCF_NKE'!$B$3*(1+'DCF_NKE'!$B$4)^0*'DCF_NKE'!$B$4*'DCF_NKE'!$B$9)/(1+0.10500000000000001)^1+('DCF_NKE'!$B$3*(1+'DCF_NKE'!$B$4)^2*('DCF_NKE'!$B$5*(1-'DCF_NKE'!$B$6)+'DCF_NKE'!$B$7-'DCF_NKE'!$B$8)-'DCF_NKE'!$B$3*(1+'DCF_NKE'!$B$4)^1*'DCF_NKE'!$B$4*'DCF_NKE'!$B$9)/(1+0.10500000000000001)^2+('DCF_NKE'!$B$3*(1+'DCF_NKE'!$B$4)^3*('DCF_NKE'!$B$5*(1-'DCF_NKE'!$B$6)+'DCF_NKE'!$B$7-'DCF_NKE'!$B$8)-'DCF_NKE'!$B$3*(1+'DCF_NKE'!$B$4)^2*'DCF_NKE'!$B$4*'DCF_NKE'!$B$9)/(1+0.10500000000000001)^3+('DCF_NKE'!$B$3*(1+'DCF_NKE'!$B$4)^4*('DCF_NKE'!$B$5*(1-'DCF_NKE'!$B$6)+'DCF_NKE'!$B$7-'DCF_NKE'!$B$8)-'DCF_NKE'!$B$3*(1+'DCF_NKE'!$B$4)^3*'DCF_NKE'!$B$4*'DCF_NKE'!$B$9)/(1+0.10500000000000001)^4+('DCF_NKE'!$B$3*(1+'DCF_NKE'!$B$4)^5*('DCF_NKE'!$B$5*(1-'DCF_NKE'!$B$6)+'DCF_NKE'!$B$7-'DCF_NKE'!$B$8)-'DCF_NKE'!$B$3*(1+'DCF_NKE'!$B$4)^4*'DCF_NKE'!$B$4*'DCF_NKE'!$B$9)/(1+0.10500000000000001)^5+('DCF_NKE'!$B$3*(1+'DCF_NKE'!$B$4)^5*(1+0.02)*('DCF_NKE'!$B$5*(1-'DCF_NKE'!$B$6)+'DCF_NKE'!$B$7-'DCF_NKE'!$B$8)-'DCF_NKE'!$B$3*(1+'DCF_NKE'!$B$4)^5*0.02*'DCF_NKE'!$B$9)/(0.10500000000000001-0.02)/(1+0.10500000000000001)^5-'DCF_NKE'!$B$13)/'DCF_NKE'!$B$12) -> 27.785149 | F16: =((('DCF_NKE'!$B$3*(1+'DCF_NKE'!$B$4)^1*('DCF_NKE'!$B$5*(1-'DCF_NKE'!$B$6)+'DCF_NKE'!$B$7-'DCF_NKE'!$B$8)-'DCF_NKE'!$B$3*(1+'DCF_NKE'!$B$4)^0*'DCF_NKE'!$B$4*'DCF_NKE'!$B$9)/(1+0.10500000000000001)^1+('DCF_NKE'!$B$3*(1+'DCF_NKE'!$B$4)^2*('DCF_NKE'!$B$5*(1-'DCF_NKE'!$B$6)+'DCF_NKE'!$B$7-'DCF_NKE'!$B$8)-'DCF_NKE'!$B$3*(1+'DCF_NKE'!$B$4)^1*'DCF_NKE'!$B$4*'DCF_NKE'!$B$9)/(1+0.10500000000000001)^2+('DCF_NKE'!$B$3*(1+'DCF_NKE'!$B$4)^3*('DCF_NKE'!$B$5*(1-'DCF_NKE'!$B$6)+'DCF_NKE'!$B$7-'DCF_NKE'!$B$8)-'DCF_NKE'!$B$3*(1+'DCF_NKE'!$B$4)^2*'DCF_NKE'!$B$4*'DCF_NKE'!$B$9)/(1+0.10500000000000001)^3+('DCF_NKE'!$B$3*(1+'DCF_NKE'!$B$4)^4*('DCF_NKE'!$B$5*(1-'DCF_NKE'!$B$6)+'DCF_NKE'!$B$7-'DCF_NKE'!$B$8)-'DCF_NKE'!$B$3*(1+'DCF_NKE'!$B$4)^3*'DCF_NKE'!$B$4*'DCF_NKE'!$B$9)/(1+0.10500000000000001)^4+('DCF_NKE'!$B$3*(1+'DCF_NKE'!$B$4)^5*('DCF_NKE'!$B$5*(1-'DCF_NKE'!$B$6)+'DCF_NKE'!$B$7-'DCF_NKE'!$B$8)-'DCF_NKE'!$B$3*(1+'DCF_NKE'!$B$4)^4*'DCF_NKE'!$B$4*'DCF_NKE'!$B$9)/(1+0.10500000000000001)^5+('DCF_NKE'!$B$3*(1+'DCF_NKE'!$B$4)^5*(1+0.025)*('DCF_NKE'!$B$5*(1-'DCF_NKE'!$B$6)+'DCF_NKE'!$B$7-'DCF_NKE'!$B$8)-'DCF_NKE'!$B$3*(1+'DCF_NKE'!$B$4)^5*0.025*'DCF_NKE'!$B$9)/(0.10500000000000001-0.025)/(1+0.10500000000000001)^5-'DCF_NKE'!$B$13)/'DCF_NKE'!$B$12) -> 28.895338 | G16: =((('DCF_NKE'!$B$3*(1+'DCF_NKE'!$B$4)^1*('DCF_NKE'!$B$5*(1-'DCF_NKE'!$B$6)+'DCF_NKE'!$B$7-'DCF_NKE'!$B$8)-'DCF_NKE'!$B$3*(1+'DCF_NKE'!$B$4)^0*'DCF_NKE'!$B$4*'DCF_NKE'!$B$9)/(1+0.10500000000000001)^1+('DCF_NKE'!$B$3*(1+'DCF_NKE'!$B$4)^2*('DCF_NKE'!$B$5*(1-'DCF_NKE'!$B$6)+'DCF_NKE'!$B$7-'DCF_NKE'!$B$8)-'DCF_NKE'!$B$3*(1+'DCF_NKE'!$B$4)^1*'DCF_NKE'!$B$4*'DCF_NKE'!$B$9)/(1+0.10500000000000001)^2+('DCF_NKE'!$B$3*(1+'DCF_NKE'!$B$4)^3*('DCF_NKE'!$B$5*(1-'DCF_NKE'!$B$6)+'DCF_NKE'!$B$7-'DCF_NKE'!$B$8)-'DCF_NKE'!$B$3*(1+'DCF_NKE'!$B$4)^2*'DCF_NKE'!$B$4*'DCF_NKE'!$B$9)/(1+0.10500000000000001)^3+('DCF_NKE'!$B$3*(1+'DCF_NKE'!$B$4)^4*('DCF_NKE'!$B$5*(1-'DCF_NKE'!$B$6)+'DCF_NKE'!$B$7-'DCF_NKE'!$B$8)-'DCF_NKE'!$B$3*(1+'DCF_NKE'!$B$4)^3*'DCF_NKE'!$B$4*'DCF_NKE'!$B$9)/(1+0.10500000000000001)^4+('DCF_NKE'!$B$3*(1+'DCF_NKE'!$B$4)^5*('DCF_NKE'!$B$5*(1-'DCF_NKE'!$B$6)+'DCF_NKE'!$B$7-'DCF_NKE'!$B$8)-'DCF_NKE'!$B$3*(1+'DCF_NKE'!$B$4)^4*'DCF_NKE'!$B$4*'DCF_NKE'!$B$9)/(1+0.10500000000000001)^5+('DCF_NKE'!$B$3*(1+'DCF_NKE'!$B$4)^5*(1+0.03)*('DCF_NKE'!$B$5*(1-'DCF_NKE'!$B$6)+'DCF_NKE'!$B$7-'DCF_NKE'!$B$8)-'DCF_NKE'!$B$3*(1+'DCF_NKE'!$B$4)^5*0.03*'DCF_NKE'!$B$9)/(0.10500000000000001-0.03)/(1+0.10500000000000001)^5-'DCF_NKE'!$B$13)/'DCF_NKE'!$B$12) -> 30.153553
A17: NKE | B17: 0.11 | C17: =((('DCF_NKE'!$B$3*(1+'DCF_NKE'!$B$4)^1*('DCF_NKE'!$B$5*(1-'DCF_NKE'!$B$6)+'DCF_NKE'!$B$7-'DCF_NKE'!$B$8)-'DCF_NKE'!$B$3*(1+'DCF_NKE'!$B$4)^0*'DCF_NKE'!$B$4*'DCF_NKE'!$B$9)/(1+0.11)^1+('DCF_NKE'!$B$3*(1+'DCF_NKE'!$B$4)^2*('DCF_NKE'!$B$5*(1-'DCF_NKE'!$B$6)+'DCF_NKE'!$B$7-'DCF_NKE'!$B$8)-'DCF_NKE'!$B$3*(1+'DCF_NKE'!$B$4)^1*'DCF_NKE'!$B$4*'DCF_NKE'!$B$9)/(1+0.11)^2+('DCF_NKE'!$B$3*(1+'DCF_NKE'!$B$4)^3*('DCF_NKE'!$B$5*(1-'DCF_NKE'!$B$6)+'DCF_NKE'!$B$7-'DCF_NKE'!$B$8)-'DCF_NKE'!$B$3*(1+'DCF_NKE'!$B$4)^2*'DCF_NKE'!$B$4*'DCF_NKE'!$B$9)/(1+0.11)^3+('DCF_NKE'!$B$3*(1+'DCF_NKE'!$B$4)^4*('DCF_NKE'!$B$5*(1-'DCF_NKE'!$B$6)+'DCF_NKE'!$B$7-'DCF_NKE'!$B$8)-'DCF_NKE'!$B$3*(1+'DCF_NKE'!$B$4)^3*'DCF_NKE'!$B$4*'DCF_NKE'!$B$9)/(1+0.11)^4+('DCF_NKE'!$B$3*(1+'DCF_NKE'!$B$4)^5*('DCF_NKE'!$B$5*(1-'DCF_NKE'!$B$6)+'DCF_NKE'!$B$7-'DCF_NKE'!$B$8)-'DCF_NKE'!$B$3*(1+'DCF_NKE'!$B$4)^4*'DCF_NKE'!$B$4*'DCF_NKE'!$B$9)/(1+0.11)^5+('DCF_NKE'!$B$3*(1+'DCF_NKE'!$B$4)^5*(1+0.01)*('DCF_NKE'!$B$5*(1-'DCF_NKE'!$B$6)+'DCF_NKE'!$B$7-'DCF_NKE'!$B$8)-'DCF_NKE'!$B$3*(1+'DCF_NKE'!$B$4)^5*0.01*'DCF_NKE'!$B$9)/(0.11-0.01)/(1+0.11)^5-'DCF_NKE'!$B$13)/'DCF_NKE'!$B$12) -> 24.624771 | D17: =((('DCF_NKE'!$B$3*(1+'DCF_NKE'!$B$4)^1*('DCF_NKE'!$B$5*(1-'DCF_NKE'!$B$6)+'DCF_NKE'!$B$7-'DCF_NKE'!$B$8)-'DCF_NKE'!$B$3*(1+'DCF_NKE'!$B$4)^0*'DCF_NKE'!$B$4*'DCF_NKE'!$B$9)/(1+0.11)^1+('DCF_NKE'!$B$3*(1+'DCF_NKE'!$B$4)^2*('DCF_NKE'!$B$5*(1-'DCF_NKE'!$B$6)+'DCF_NKE'!$B$7-'DCF_NKE'!$B$8)-'DCF_NKE'!$B$3*(1+'DCF_NKE'!$B$4)^1*'DCF_NKE'!$B$4*'DCF_NKE'!$B$9)/(1+0.11)^2+('DCF_NKE'!$B$3*(1+'DCF_NKE'!$B$4)^3*('DCF_NKE'!$B$5*(1-'DCF_NKE'!$B$6)+'DCF_NKE'!$B$7-'DCF_NKE'!$B$8)-'DCF_NKE'!$B$3*(1+'DCF_NKE'!$B$4)^2*'DCF_NKE'!$B$4*'DCF_NKE'!$B$9)/(1+0.11)^3+('DCF_NKE'!$B$3*(1+'DCF_NKE'!$B$4)^4*('DCF_NKE'!$B$5*(1-'DCF_NKE'!$B$6)+'DCF_NKE'!$B$7-'DCF_NKE'!$B$8)-'DCF_NKE'!$B$3*(1+'DCF_NKE'!$B$4)^3*'DCF_NKE'!$B$4*'DCF_NKE'!$B$9)/(1+0.11)^4+('DCF_NKE'!$B$3*(1+'DCF_NKE'!$B$4)^5*('DCF_NKE'!$B$5*(1-'DCF_NKE'!$B$6)+'DCF_NKE'!$B$7-'DCF_NKE'!$B$8)-'DCF_NKE'!$B$3*(1+'DCF_NKE'!$B$4)^4*'DCF_NKE'!$B$4*'DCF_NKE'!$B$9)/(1+0.11)^5+('DCF_NKE'!$B$3*(1+'DCF_NKE'!$B$4)^5*(1+0.015)*('DCF_NKE'!$B$5*(1-'DCF_NKE'!$B$6)+'DCF_NKE'!$B$7-'DCF_NKE'!$B$8)-'DCF_NKE'!$B$3*(1+'DCF_NKE'!$B$4)^5*0.015*'DCF_NKE'!$B$9)/(0.11-0.015)/(1+0.11)^5-'DCF_NKE'!$B$13)/'DCF_NKE'!$B$12) -> 25.399952 | E17: =((('DCF_NKE'!$B$3*(1+'DCF_NKE'!$B$4)^1*('DCF_NKE'!$B$5*(1-'DCF_NKE'!$B$6)+'DCF_NKE'!$B$7-'DCF_NKE'!$B$8)-'DCF_NKE'!$B$3*(1+'DCF_NKE'!$B$4)^0*'DCF_NKE'!$B$4*'DCF_NKE'!$B$9)/(1+0.11)^1+('DCF_NKE'!$B$3*(1+'DCF_NKE'!$B$4)^2*('DCF_NKE'!$B$5*(1-'DCF_NKE'!$B$6)+'DCF_NKE'!$B$7-'DCF_NKE'!$B$8)-'DCF_NKE'!$B$3*(1+'DCF_NKE'!$B$4)^1*'DCF_NKE'!$B$4*'DCF_NKE'!$B$9)/(1+0.11)^2+('DCF_NKE'!$B$3*(1+'DCF_NKE'!$B$4)^3*('DCF_NKE'!$B$5*(1-'DCF_NKE'!$B$6)+'DCF_NKE'!$B$7-'DCF_NKE'!$B$8)-'DCF_NKE'!$B$3*(1+'DCF_NKE'!$B$4)^2*'DCF_NKE'!$B$4*'DCF_NKE'!$B$9)/(1+0.11)^3+('DCF_NKE'!$B$3*(1+'DCF_NKE'!$B$4)^4*('DCF_NKE'!$B$5*(1-'DCF_NKE'!$B$6)+'DCF_NKE'!$B$7-'DCF_NKE'!$B$8)-'DCF_NKE'!$B$3*(1+'DCF_NKE'!$B$4)^3*'DCF_NKE'!$B$4*'DCF_NKE'!$B$9)/(1+0.11)^4+('DCF_NKE'!$B$3*(1+'DCF_NKE'!$B$4)^5*('DCF_NKE'!$B$5*(1-'DCF_NKE'!$B$6)+'DCF_NKE'!$B$7-'DCF_NKE'!$B$8)-'DCF_NKE'!$B$3*(1+'DCF_NKE'!$B$4)^4*'DCF_NKE'!$B$4*'DCF_NKE'!$B$9)/(1+0.11)^5+('DCF_NKE'!$B$3*(1+'DCF_NKE'!$B$4)^5*(1+0.02)*('DCF_NKE'!$B$5*(1-'DCF_NKE'!$B$6)+'DCF_NKE'!$B$7-'DCF_NKE'!$B$8)-'DCF_NKE'!$B$3*(1+'DCF_NKE'!$B$4)^5*0.02*'DCF_NKE'!$B$9)/(0.11-0.02)/(1+0.11)^5-'DCF_NKE'!$B$13)/'DCF_NKE'!$B$12) -> 26.261265 | F17: =((('DCF_NKE'!$B$3*(1+'DCF_NKE'!$B$4)^1*('DCF_NKE'!$B$5*(1-'DCF_NKE'!$B$6)+'DCF_NKE'!$B$7-'DCF_NKE'!$B$8)-'DCF_NKE'!$B$3*(1+'DCF_NKE'!$B$4)^0*'DCF_NKE'!$B$4*'DCF_NKE'!$B$9)/(1+0.11)^1+('DCF_NKE'!$B$3*(1+'DCF_NKE'!$B$4)^2*('DCF_NKE'!$B$5*(1-'DCF_NKE'!$B$6)+'DCF_NKE'!$B$7-'DCF_NKE'!$B$8)-'DCF_NKE'!$B$3*(1+'DCF_NKE'!$B$4)^1*'DCF_NKE'!$B$4*'DCF_NKE'!$B$9)/(1+0.11)^2+('DCF_NKE'!$B$3*(1+'DCF_NKE'!$B$4)^3*('DCF_NKE'!$B$5*(1-'DCF_NKE'!$B$6)+'DCF_NKE'!$B$7-'DCF_NKE'!$B$8)-'DCF_NKE'!$B$3*(1+'DCF_NKE'!$B$4)^2*'DCF_NKE'!$B$4*'DCF_NKE'!$B$9)/(1+0.11)^3+('DCF_NKE'!$B$3*(1+'DCF_NKE'!$B$4)^4*('DCF_NKE'!$B$5*(1-'DCF_NKE'!$B$6)+'DCF_NKE'!$B$7-'DCF_NKE'!$B$8)-'DCF_NKE'!$B$3*(1+'DCF_NKE'!$B$4)^3*'DCF_NKE'!$B$4*'DCF_NKE'!$B$9)/(1+0.11)^4+('DCF_NKE'!$B$3*(1+'DCF_NKE'!$B$4)^5*('DCF_NKE'!$B$5*(1-'DCF_NKE'!$B$6)+'DCF_NKE'!$B$7-'DCF_NKE'!$B$8)-'DCF_NKE'!$B$3*(1+'DCF_NKE'!$B$4)^4*'DCF_NKE'!$B$4*'DCF_NKE'!$B$9)/(1+0.11)^5+('DCF_NKE'!$B$3*(1+'DCF_NKE'!$B$4)^5*(1+0.025)*('DCF_NKE'!$B$5*(1-'DCF_NKE'!$B$6)+'DCF_NKE'!$B$7-'DCF_NKE'!$B$8)-'DCF_NKE'!$B$3*(1+'DCF_NKE'!$B$4)^5*0.025*'DCF_NKE'!$B$9)/(0.11-0.025)/(1+0.11)^5-'DCF_NKE'!$B$13)/'DCF_NKE'!$B$12) -> 27.223908 | G17: =((('DCF_NKE'!$B$3*(1+'DCF_NKE'!$B$4)^1*('DCF_NKE'!$B$5*(1-'DCF_NKE'!$B$6)+'DCF_NKE'!$B$7-'DCF_NKE'!$B$8)-'DCF_NKE'!$B$3*(1+'DCF_NKE'!$B$4)^0*'DCF_NKE'!$B$4*'DCF_NKE'!$B$9)/(1+0.11)^1+('DCF_NKE'!$B$3*(1+'DCF_NKE'!$B$4)^2*('DCF_NKE'!$B$5*(1-'DCF_NKE'!$B$6)+'DCF_NKE'!$B$7-'DCF_NKE'!$B$8)-'DCF_NKE'!$B$3*(1+'DCF_NKE'!$B$4)^1*'DCF_NKE'!$B$4*'DCF_NKE'!$B$9)/(1+0.11)^2+('DCF_NKE'!$B$3*(1+'DCF_NKE'!$B$4)^3*('DCF_NKE'!$B$5*(1-'DCF_NKE'!$B$6)+'DCF_NKE'!$B$7-'DCF_NKE'!$B$8)-'DCF_NKE'!$B$3*(1+'DCF_NKE'!$B$4)^2*'DCF_NKE'!$B$4*'DCF_NKE'!$B$9)/(1+0.11)^3+('DCF_NKE'!$B$3*(1+'DCF_NKE'!$B$4)^4*('DCF_NKE'!$B$5*(1-'DCF_NKE'!$B$6)+'DCF_NKE'!$B$7-'DCF_NKE'!$B$8)-'DCF_NKE'!$B$3*(1+'DCF_NKE'!$B$4)^3*'DCF_NKE'!$B$4*'DCF_NKE'!$B$9)/(1+0.11)^4+('DCF_NKE'!$B$3*(1+'DCF_NKE'!$B$4)^5*('DCF_NKE'!$B$5*(1-'DCF_NKE'!$B$6)+'DCF_NKE'!$B$7-'DCF_NKE'!$B$8)-'DCF_NKE'!$B$3*(1+'DCF_NKE'!$B$4)^4*'DCF_NKE'!$B$4*'DCF_NKE'!$B$9)/(1+0.11)^5+('DCF_NKE'!$B$3*(1+'DCF_NKE'!$B$4)^5*(1+0.03)*('DCF_NKE'!$B$5*(1-'DCF_NKE'!$B$6)+'DCF_NKE'!$B$7-'DCF_NKE'!$B$8)-'DCF_NKE'!$B$3*(1+'DCF_NKE'!$B$4)^5*0.03*'DCF_NKE'!$B$9)/(0.11-0.03)/(1+0.11)^5-'DCF_NKE'!$B$13)/'DCF_NKE'!$B$12) -> 28.306882

Sheet REVERSE
A1: MIRROR X · PRELIMINARY · MX-3777d2e495a9
A2: Ticker | B2: Market price input | C2: Implied growth | D2: Status
A3: ADBE | C3: =IF(OR(B3="",B3<=0),"N/A",IF(OR(B3<((('DCF_ADBE'!$B$3*(1+-0.45)^1*('DCF_ADBE'!$B$5*(1-'DCF_ADBE'!$B$6)+'DCF_ADBE'!$B$7-'DCF_ADBE'!$B$8)-'DCF_ADBE'!$B$3*(1+-0.45)^0*-0.45*'DCF_ADBE'!$B$9)/(1+'DCF_ADBE'!$B$10)^1+('DCF_ADBE'!$B$3*(1+-0.45)^2*('DCF_ADBE'!$B$5*(1-'DCF_ADBE'!$B$6)+'DCF_ADBE'!$B$7-'DCF_ADBE'!$B$8)-'DCF_ADBE'!$B$3*(1+-0.45)^1*-0.45*'DCF_ADBE'!$B$9)/(1+'DCF_ADBE'!$B$10)^2+('DCF_ADBE'!$B$3*(1+-0.45)^3*('DCF_ADBE'!$B$5*(1-'DCF_ADBE'!$B$6)+'DCF_ADBE'!$B$7-'DCF_ADBE'!$B$8)-'DCF_ADBE'!$B$3*(1+-0.45)^2*-0.45*'DCF_ADBE'!$B$9)/(1+'DCF_ADBE'!$B$10)^3+('DCF_ADBE'!$B$3*(1+-0.45)^4*('DCF_ADBE'!$B$5*(1-'DCF_ADBE'!$B$6)+'DCF_ADBE'!$B$7-'DCF_ADBE'!$B$8)-'DCF_ADBE'!$B$3*(1+-0.45)^3*-0.45*'DCF_ADBE'!$B$9)/(1+'DCF_ADBE'!$B$10)^4+('DCF_ADBE'!$B$3*(1+-0.45)^5*('DCF_ADBE'!$B$5*(1-'DCF_ADBE'!$B$6)+'DCF_ADBE'!$B$7-'DCF_ADBE'!$B$8)-'DCF_ADBE'!$B$3*(1+-0.45)^4*-0.45*'DCF_ADBE'!$B$9)/(1+'DCF_ADBE'!$B$10)^5+('DCF_ADBE'!$B$3*(1+-0.45)^5*(1+'DCF_ADBE'!$B$11)*('DCF_ADBE'!$B$5*(1-'DCF_ADBE'!$B$6)+'DCF_ADBE'!$B$7-'DCF_ADBE'!$B$8)-'DCF_ADBE'!$B$3*(1+-0.45)^5*'DCF_ADBE'!$B$11*'DCF_ADBE'!$B$9)/('DCF_ADBE'!$B$10-'DCF_ADBE'!$B$11)/(1+'DCF_ADBE'!$B$10)^5-'DCF_ADBE'!$B$13)/'DCF_ADBE'!$B$12),B3>((('DCF_ADBE'!$B$3*(1+0.5)^1*('DCF_ADBE'!$B$5*(1-'DCF_ADBE'!$B$6)+'DCF_ADBE'!$B$7-'DCF_ADBE'!$B$8)-'DCF_ADBE'!$B$3*(1+0.5)^0*0.5*'DCF_ADBE'!$B$9)/(1+'DCF_ADBE'!$B$10)^1+('DCF_ADBE'!$B$3*(1+0.5)^2*('DCF_ADBE'!$B$5*(1-'DCF_ADBE'!$B$6)+'DCF_ADBE'!$B$7-'DCF_ADBE'!$B$8)-'DCF_ADBE'!$B$3*(1+0.5)^1*0.5*'DCF_ADBE'!$B$9)/(1+'DCF_ADBE'!$B$10)^2+('DCF_ADBE'!$B$3*(1+0.5)^3*('DCF_ADBE'!$B$5*(1-'DCF_ADBE'!$B$6)+'DCF_ADBE'!$B$7-'DCF_ADBE'!$B$8)-'DCF_ADBE'!$B$3*(1+0.5)^2*0.5*'DCF_ADBE'!$B$9)/(1+'DCF_ADBE'!$B$10)^3+('DCF_ADBE'!$B$3*(1+0.5)^4*('DCF_ADBE'!$B$5*(1-'DCF_ADBE'!$B$6)+'DCF_ADBE'!$B$7-'DCF_ADBE'!$B$8)-'DCF_ADBE'!$B$3*(1+0.5)^3*0.5*'DCF_ADBE'!$B$9)/(1+'DCF_ADBE'!$B$10)^4+('DCF_ADBE'!$B$3*(1+0.5)^5*('DCF_ADBE'!$B$5*(1-'DCF_ADBE'!$B$6)+'DCF_ADBE'!$B$7-'DCF_ADBE'!$B$8)-'DCF_ADBE'!$B$3*(1+0.5)^4*0.5*'DCF_ADBE'!$B$9)/(1+'DCF_ADBE'!$B$10)^5+('DCF_ADBE'!$B$3*(1+0.5)^5*(1+'DCF_ADBE'!$B$11)*('DCF_ADBE'!$B$5*(1-'DCF_ADBE'!$B$6)+'DCF_ADBE'!$B$7-'DCF_ADBE'!$B$8)-'DCF_ADBE'!$B$3*(1+0.5)^5*'DCF_ADBE'!$B$11*'DCF_ADBE'!$B$9)/('DCF_ADBE'!$B$10-'DCF_ADBE'!$B$11)/(1+'DCF_ADBE'!$B$10)^5-'DCF_ADBE'!$B$13)/'DCF_ADBE'!$B$12)),"N/A",D68)) -> N/A | D3: Price not verified: blank
A4: PYPL | C4: =IF(OR(B4="",B4<=0),"N/A",IF(OR(B4<((('DCF_PYPL'!$B$3*(1+-0.45)^1*('DCF_PYPL'!$B$5*(1-'DCF_PYPL'!$B$6)+'DCF_PYPL'!$B$7-'DCF_PYPL'!$B$8)-'DCF_PYPL'!$B$3*(1+-0.45)^0*-0.45*'DCF_PYPL'!$B$9)/(1+'DCF_PYPL'!$B$10)^1+('DCF_PYPL'!$B$3*(1+-0.45)^2*('DCF_PYPL'!$B$5*(1-'DCF_PYPL'!$B$6)+'DCF_PYPL'!$B$7-'DCF_PYPL'!$B$8)-'DCF_PYPL'!$B$3*(1+-0.45)^1*-0.45*'DCF_PYPL'!$B$9)/(1+'DCF_PYPL'!$B$10)^2+('DCF_PYPL'!$B$3*(1+-0.45)^3*('DCF_PYPL'!$B$5*(1-'DCF_PYPL'!$B$6)+'DCF_PYPL'!$B$7-'DCF_PYPL'!$B$8)-'DCF_PYPL'!$B$3*(1+-0.45)^2*-0.45*'DCF_PYPL'!$B$9)/(1+'DCF_PYPL'!$B$10)^3+('DCF_PYPL'!$B$3*(1+-0.45)^4*('DCF_PYPL'!$B$5*(1-'DCF_PYPL'!$B$6)+'DCF_PYPL'!$B$7-'DCF_PYPL'!$B$8)-'DCF_PYPL'!$B$3*(1+-0.45)^3*-0.45*'DCF_PYPL'!$B$9)/(1+'DCF_PYPL'!$B$10)^4+('DCF_PYPL'!$B$3*(1+-0.45)^5*('DCF_PYPL'!$B$5*(1-'DCF_PYPL'!$B$6)+'DCF_PYPL'!$B$7-'DCF_PYPL'!$B$8)-'DCF_PYPL'!$B$3*(1+-0.45)^4*-0.45*'DCF_PYPL'!$B$9)/(1+'DCF_PYPL'!$B$10)^5+('DCF_PYPL'!$B$3*(1+-0.45)^5*(1+'DCF_PYPL'!$B$11)*('DCF_PYPL'!$B$5*(1-'DCF_PYPL'!$B$6)+'DCF_PYPL'!$B$7-'DCF_PYPL'!$B$8)-'DCF_PYPL'!$B$3*(1+-0.45)^5*'DCF_PYPL'!$B$11*'DCF_PYPL'!$B$9)/('DCF_PYPL'!$B$10-'DCF_PYPL'!$B$11)/(1+'DCF_PYPL'!$B$10)^5-'DCF_PYPL'!$B$13)/'DCF_PYPL'!$B$12),B4>((('DCF_PYPL'!$B$3*(1+0.5)^1*('DCF_PYPL'!$B$5*(1-'DCF_PYPL'!$B$6)+'DCF_PYPL'!$B$7-'DCF_PYPL'!$B$8)-'DCF_PYPL'!$B$3*(1+0.5)^0*0.5*'DCF_PYPL'!$B$9)/(1+'DCF_PYPL'!$B$10)^1+('DCF_PYPL'!$B$3*(1+0.5)^2*('DCF_PYPL'!$B$5*(1-'DCF_PYPL'!$B$6)+'DCF_PYPL'!$B$7-'DCF_PYPL'!$B$8)-'DCF_PYPL'!$B$3*(1+0.5)^1*0.5*'DCF_PYPL'!$B$9)/(1+'DCF_PYPL'!$B$10)^2+('DCF_PYPL'!$B$3*(1+0.5)^3*('DCF_PYPL'!$B$5*(1-'DCF_PYPL'!$B$6)+'DCF_PYPL'!$B$7-'DCF_PYPL'!$B$8)-'DCF_PYPL'!$B$3*(1+0.5)^2*0.5*'DCF_PYPL'!$B$9)/(1+'DCF_PYPL'!$B$10)^3+('DCF_PYPL'!$B$3*(1+0.5)^4*('DCF_PYPL'!$B$5*(1-'DCF_PYPL'!$B$6)+'DCF_PYPL'!$B$7-'DCF_PYPL'!$B$8)-'DCF_PYPL'!$B$3*(1+0.5)^3*0.5*'DCF_PYPL'!$B$9)/(1+'DCF_PYPL'!$B$10)^4+('DCF_PYPL'!$B$3*(1+0.5)^5*('DCF_PYPL'!$B$5*(1-'DCF_PYPL'!$B$6)+'DCF_PYPL'!$B$7-'DCF_PYPL'!$B$8)-'DCF_PYPL'!$B$3*(1+0.5)^4*0.5*'DCF_PYPL'!$B$9)/(1+'DCF_PYPL'!$B$10)^5+('DCF_PYPL'!$B$3*(1+0.5)^5*(1+'DCF_PYPL'!$B$11)*('DCF_PYPL'!$B$5*(1-'DCF_PYPL'!$B$6)+'DCF_PYPL'!$B$7-'DCF_PYPL'!$B$8)-'DCF_PYPL'!$B$3*(1+0.5)^5*'DCF_PYPL'!$B$11*'DCF_PYPL'!$B$9)/('DCF_PYPL'!$B$10-'DCF_PYPL'!$B$11)/(1+'DCF_PYPL'!$B$10)^5-'DCF_PYPL'!$B$13)/'DCF_PYPL'!$B$12)),"N/A",D132)) -> N/A | D4: Price not verified: blank
A5: NKE | C5: =IF(OR(B5="",B5<=0),"N/A",IF(OR(B5<((('DCF_NKE'!$B$3*(1+-0.45)^1*('DCF_NKE'!$B$5*(1-'DCF_NKE'!$B$6)+'DCF_NKE'!$B$7-'DCF_NKE'!$B$8)-'DCF_NKE'!$B$3*(1+-0.45)^0*-0.45*'DCF_NKE'!$B$9)/(1+'DCF_NKE'!$B$10)^1+('DCF_NKE'!$B$3*(1+-0.45)^2*('DCF_NKE'!$B$5*(1-'DCF_NKE'!$B$6)+'DCF_NKE'!$B$7-'DCF_NKE'!$B$8)-'DCF_NKE'!$B$3*(1+-0.45)^1*-0.45*'DCF_NKE'!$B$9)/(1+'DCF_NKE'!$B$10)^2+('DCF_NKE'!$B$3*(1+-0.45)^3*('DCF_NKE'!$B$5*(1-'DCF_NKE'!$B$6)+'DCF_NKE'!$B$7-'DCF_NKE'!$B$8)-'DCF_NKE'!$B$3*(1+-0.45)^2*-0.45*'DCF_NKE'!$B$9)/(1+'DCF_NKE'!$B$10)^3+('DCF_NKE'!$B$3*(1+-0.45)^4*('DCF_NKE'!$B$5*(1-'DCF_NKE'!$B$6)+'DCF_NKE'!$B$7-'DCF_NKE'!$B$8)-'DCF_NKE'!$B$3*(1+-0.45)^3*-0.45*'DCF_NKE'!$B$9)/(1+'DCF_NKE'!$B$10)^4+('DCF_NKE'!$B$3*(1+-0.45)^5*('DCF_NKE'!$B$5*(1-'DCF_NKE'!$B$6)+'DCF_NKE'!$B$7-'DCF_NKE'!$B$8)-'DCF_NKE'!$B$3*(1+-0.45)^4*-0.45*'DCF_NKE'!$B$9)/(1+'DCF_NKE'!$B$10)^5+('DCF_NKE'!$B$3*(1+-0.45)^5*(1+'DCF_NKE'!$B$11)*('DCF_NKE'!$B$5*(1-'DCF_NKE'!$B$6)+'DCF_NKE'!$B$7-'DCF_NKE'!$B$8)-'DCF_NKE'!$B$3*(1+-0.45)^5*'DCF_NKE'!$B$11*'DCF_NKE'!$B$9)/('DCF_NKE'!$B$10-'DCF_NKE'!$B$11)/(1+'DCF_NKE'!$B$10)^5-'DCF_NKE'!$B$13)/'DCF_NKE'!$B$12),B5>((('DCF_NKE'!$B$3*(1+0.5)^1*('DCF_NKE'!$B$5*(1-'DCF_NKE'!$B$6)+'DCF_NKE'!$B$7-'DCF_NKE'!$B$8)-'DCF_NKE'!$B$3*(1+0.5)^0*0.5*'DCF_NKE'!$B$9)/(1+'DCF_NKE'!$B$10)^1+('DCF_NKE'!$B$3*(1+0.5)^2*('DCF_NKE'!$B$5*(1-'DCF_NKE'!$B$6)+'DCF_NKE'!$B$7-'DCF_NKE'!$B$8)-'DCF_NKE'!$B$3*(1+0.5)^1*0.5*'DCF_NKE'!$B$9)/(1+'DCF_NKE'!$B$10)^2+('DCF_NKE'!$B$3*(1+0.5)^3*('DCF_NKE'!$B$5*(1-'DCF_NKE'!$B$6)+'DCF_NKE'!$B$7-'DCF_NKE'!$B$8)-'DCF_NKE'!$B$3*(1+0.5)^2*0.5*'DCF_NKE'!$B$9)/(1+'DCF_NKE'!$B$10)^3+('DCF_NKE'!$B$3*(1+0.5)^4*('DCF_NKE'!$B$5*(1-'DCF_NKE'!$B$6)+'DCF_NKE'!$B$7-'DCF_NKE'!$B$8)-'DCF_NKE'!$B$3*(1+0.5)^3*0.5*'DCF_NKE'!$B$9)/(1+'DCF_NKE'!$B$10)^4+('DCF_NKE'!$B$3*(1+0.5)^5*('DCF_NKE'!$B$5*(1-'DCF_NKE'!$B$6)+'DCF_NKE'!$B$7-'DCF_NKE'!$B$8)-'DCF_NKE'!$B$3*(1+0.5)^4*0.5*'DCF_NKE'!$B$9)/(1+'DCF_NKE'!$B$10)^5+('DCF_NKE'!$B$3*(1+0.5)^5*(1+'DCF_NKE'!$B$11)*('DCF_NKE'!$B$5*(1-'DCF_NKE'!$B$6)+'DCF_NKE'!$B$7-'DCF_NKE'!$B$8)-'DCF_NKE'!$B$3*(1+0.5)^5*'DCF_NKE'!$B$11*'DCF_NKE'!$B$9)/('DCF_NKE'!$B$10-'DCF_NKE'!$B$11)/(1+'DCF_NKE'!$B$10)^5-'DCF_NKE'!$B$13)/'DCF_NKE'!$B$12)),"N/A",D196)) -> N/A | D5: Price not verified: blank
A8: ADBE | B8: Lower growth | C8: Upper growth | D8: Mid growth | E8: Model price
A9: 1 | B9: -0.45 | C9: 0.5 | D9: =IF($B$3="","",(B9+C9)/2) | E9: =IF($B$3="","",((('DCF_ADBE'!$B$3*(1+D9)^1*('DCF_ADBE'!$B$5*(1-'DCF_ADBE'!$B$6)+'DCF_ADBE'!$B$7-'DCF_ADBE'!$B$8)-'DCF_ADBE'!$B$3*(1+D9)^0*D9*'DCF_ADBE'!$B$9)/(1+'DCF_ADBE'!$B$10)^1+('DCF_ADBE'!$B$3*(1+D9)^2*('DCF_ADBE'!$B$5*(1-'DCF_ADBE'!$B$6)+'DCF_ADBE'!$B$7-'DCF_ADBE'!$B$8)-'DCF_ADBE'!$B$3*(1+D9)^1*D9*'DCF_ADBE'!$B$9)/(1+'DCF_ADBE'!$B$10)^2+('DCF_ADBE'!$B$3*(1+D9)^3*('DCF_ADBE'!$B$5*(1-'DCF_ADBE'!$B$6)+'DCF_ADBE'!$B$7-'DCF_ADBE'!$B$8)-'DCF_ADBE'!$B$3*(1+D9)^2*D9*'DCF_ADBE'!$B$9)/(1+'DCF_ADBE'!$B$10)^3+('DCF_ADBE'!$B$3*(1+D9)^4*('DCF_ADBE'!$B$5*(1-'DCF_ADBE'!$B$6)+'DCF_ADBE'!$B$7-'DCF_ADBE'!$B$8)-'DCF_ADBE'!$B$3*(1+D9)^3*D9*'DCF_ADBE'!$B$9)/(1+'DCF_ADBE'!$B$10)^4+('DCF_ADBE'!$B$3*(1+D9)^5*('DCF_ADBE'!$B$5*(1-'DCF_ADBE'!$B$6)+'DCF_ADBE'!$B$7-'DCF_ADBE'!$B$8)-'DCF_ADBE'!$B$3*(1+D9)^4*D9*'DCF_ADBE'!$B$9)/(1+'DCF_ADBE'!$B$10)^5+('DCF_ADBE'!$B$3*(1+D9)^5*(1+'DCF_ADBE'!$B$11)*('DCF_ADBE'!$B$5*(1-'DCF_ADBE'!$B$6)+'DCF_ADBE'!$B$7-'DCF_ADBE'!$B$8)-'DCF_ADBE'!$B$3*(1+D9)^5*'DCF_ADBE'!$B$11*'DCF_ADBE'!$B$9)/('DCF_ADBE'!$B$10-'DCF_ADBE'!$B$11)/(1+'DCF_ADBE'!$B$10)^5-'DCF_ADBE'!$B$13)/'DCF_ADBE'!$B$12))
A10: 2 | B10: =IF($B$3="","",IF(E9<$B$3,D9,B9)) | C10: =IF($B$3="","",IF(E9<$B$3,C9,D9)) | D10: =IF($B$3="","",(B10+C10)/2) | E10: =IF($B$3="","",((('DCF_ADBE'!$B$3*(1+D10)^1*('DCF_ADBE'!$B$5*(1-'DCF_ADBE'!$B$6)+'DCF_ADBE'!$B$7-'DCF_ADBE'!$B$8)-'DCF_ADBE'!$B$3*(1+D10)^0*D10*'DCF_ADBE'!$B$9)/(1+'DCF_ADBE'!$B$10)^1+('DCF_ADBE'!$B$3*(1+D10)^2*('DCF_ADBE'!$B$5*(1-'DCF_ADBE'!$B$6)+'DCF_ADBE'!$B$7-'DCF_ADBE'!$B$8)-'DCF_ADBE'!$B$3*(1+D10)^1*D10*'DCF_ADBE'!$B$9)/(1+'DCF_ADBE'!$B$10)^2+('DCF_ADBE'!$B$3*(1+D10)^3*('DCF_ADBE'!$B$5*(1-'DCF_ADBE'!$B$6)+'DCF_ADBE'!$B$7-'DCF_ADBE'!$B$8)-'DCF_ADBE'!$B$3*(1+D10)^2*D10*'DCF_ADBE'!$B$9)/(1+'DCF_ADBE'!$B$10)^3+('DCF_ADBE'!$B$3*(1+D10)^4*('DCF_ADBE'!$B$5*(1-'DCF_ADBE'!$B$6)+'DCF_ADBE'!$B$7-'DCF_ADBE'!$B$8)-'DCF_ADBE'!$B$3*(1+D10)^3*D10*'DCF_ADBE'!$B$9)/(1+'DCF_ADBE'!$B$10)^4+('DCF_ADBE'!$B$3*(1+D10)^5*('DCF_ADBE'!$B$5*(1-'DCF_ADBE'!$B$6)+'DCF_ADBE'!$B$7-'DCF_ADBE'!$B$8)-'DCF_ADBE'!$B$3*(1+D10)^4*D10*'DCF_ADBE'!$B$9)/(1+'DCF_ADBE'!$B$10)^5+('DCF_ADBE'!$B$3*(1+D10)^5*(1+'DCF_ADBE'!$B$11)*('DCF_ADBE'!$B$5*(1-'DCF_ADBE'!$B$6)+'DCF_ADBE'!$B$7-'DCF_ADBE'!$B$8)-'DCF_ADBE'!$B$3*(1+D10)^5*'DCF_ADBE'!$B$11*'DCF_ADBE'!$B$9)/('DCF_ADBE'!$B$10-'DCF_ADBE'!$B$11)/(1+'DCF_ADBE'!$B$10)^5-'DCF_ADBE'!$B$13)/'DCF_ADBE'!$B$12))
A11: 3 | B11: =IF($B$3="","",IF(E10<$B$3,D10,B10)) | C11: =IF($B$3="","",IF(E10<$B$3,C10,D10)) | D11: =IF($B$3="","",(B11+C11)/2) | E11: =IF($B$3="","",((('DCF_ADBE'!$B$3*(1+D11)^1*('DCF_ADBE'!$B$5*(1-'DCF_ADBE'!$B$6)+'DCF_ADBE'!$B$7-'DCF_ADBE'!$B$8)-'DCF_ADBE'!$B$3*(1+D11)^0*D11*'DCF_ADBE'!$B$9)/(1+'DCF_ADBE'!$B$10)^1+('DCF_ADBE'!$B$3*(1+D11)^2*('DCF_ADBE'!$B$5*(1-'DCF_ADBE'!$B$6)+'DCF_ADBE'!$B$7-'DCF_ADBE'!$B$8)-'DCF_ADBE'!$B$3*(1+D11)^1*D11*'DCF_ADBE'!$B$9)/(1+'DCF_ADBE'!$B$10)^2+('DCF_ADBE'!$B$3*(1+D11)^3*('DCF_ADBE'!$B$5*(1-'DCF_ADBE'!$B$6)+'DCF_ADBE'!$B$7-'DCF_ADBE'!$B$8)-'DCF_ADBE'!$B$3*(1+D11)^2*D11*'DCF_ADBE'!$B$9)/(1+'DCF_ADBE'!$B$10)^3+('DCF_ADBE'!$B$3*(1+D11)^4*('DCF_ADBE'!$B$5*(1-'DCF_ADBE'!$B$6)+'DCF_ADBE'!$B$7-'DCF_ADBE'!$B$8)-'DCF_ADBE'!$B$3*(1+D11)^3*D11*'DCF_ADBE'!$B$9)/(1+'DCF_ADBE'!$B$10)^4+('DCF_ADBE'!$B$3*(1+D11)^5*('DCF_ADBE'!$B$5*(1-'DCF_ADBE'!$B$6)+'DCF_ADBE'!$B$7-'DCF_ADBE'!$B$8)-'DCF_ADBE'!$B$3*(1+D11)^4*D11*'DCF_ADBE'!$B$9)/(1+'DCF_ADBE'!$B$10)^5+('DCF_ADBE'!$B$3*(1+D11)^5*(1+'DCF_ADBE'!$B$11)*('DCF_ADBE'!$B$5*(1-'DCF_ADBE'!$B$6)+'DCF_ADBE'!$B$7-'DCF_ADBE'!$B$8)-'DCF_ADBE'!$B$3*(1+D11)^5*'DCF_ADBE'!$B$11*'DCF_ADBE'!$B$9)/('DCF_ADBE'!$B$10-'DCF_ADBE'!$B$11)/(1+'DCF_ADBE'!$B$10)^5-'DCF_ADBE'!$B$13)/'DCF_ADBE'!$B$12))
A12: 4 | B12: =IF($B$3="","",IF(E11<$B$3,D11,B11)) | C12: =IF($B$3="","",IF(E11<$B$3,C11,D11)) | D12: =IF($B$3="","",(B12+C12)/2) | E12: =IF($B$3="","",((('DCF_ADBE'!$B$3*(1+D12)^1*('DCF_ADBE'!$B$5*(1-'DCF_ADBE'!$B$6)+'DCF_ADBE'!$B$7-'DCF_ADBE'!$B$8)-'DCF_ADBE'!$B$3*(1+D12)^0*D12*'DCF_ADBE'!$B$9)/(1+'DCF_ADBE'!$B$10)^1+('DCF_ADBE'!$B$3*(1+D12)^2*('DCF_ADBE'!$B$5*(1-'DCF_ADBE'!$B$6)+'DCF_ADBE'!$B$7-'DCF_ADBE'!$B$8)-'DCF_ADBE'!$B$3*(1+D12)^1*D12*'DCF_ADBE'!$B$9)/(1+'DCF_ADBE'!$B$10)^2+('DCF_ADBE'!$B$3*(1+D12)^3*('DCF_ADBE'!$B$5*(1-'DCF_ADBE'!$B$6)+'DCF_ADBE'!$B$7-'DCF_ADBE'!$B$8)-'DCF_ADBE'!$B$3*(1+D12)^2*D12*'DCF_ADBE'!$B$9)/(1+'DCF_ADBE'!$B$10)^3+('DCF_ADBE'!$B$3*(1+D12)^4*('DCF_ADBE'!$B$5*(1-'DCF_ADBE'!$B$6)+'DCF_ADBE'!$B$7-'DCF_ADBE'!$B$8)-'DCF_ADBE'!$B$3*(1+D12)^3*D12*'DCF_ADBE'!$B$9)/(1+'DCF_ADBE'!$B$10)^4+('DCF_ADBE'!$B$3*(1+D12)^5*('DCF_ADBE'!$B$5*(1-'DCF_ADBE'!$B$6)+'DCF_ADBE'!$B$7-'DCF_ADBE'!$B$8)-'DCF_ADBE'!$B$3*(1+D12)^4*D12*'DCF_ADBE'!$B$9)/(1+'DCF_ADBE'!$B$10)^5+('DCF_ADBE'!$B$3*(1+D12)^5*(1+'DCF_ADBE'!$B$11)*('DCF_ADBE'!$B$5*(1-'DCF_ADBE'!$B$6)+'DCF_ADBE'!$B$7-'DCF_ADBE'!$B$8)-'DCF_ADBE'!$B$3*(1+D12)^5*'DCF_ADBE'!$B$11*'DCF_ADBE'!$B$9)/('DCF_ADBE'!$B$10-'DCF_ADBE'!$B$11)/(1+'DCF_ADBE'!$B$10)^5-'DCF_ADBE'!$B$13)/'DCF_ADBE'!$B$12))
A13: 5 | B13: =IF($B$3="","",IF(E12<$B$3,D12,B12)) | C13: =IF($B$3="","",IF(E12<$B$3,C12,D12)) | D13: =IF($B$3="","",(B13+C13)/2) | E13: =IF($B$3="","",((('DCF_ADBE'!$B$3*(1+D13)^1*('DCF_ADBE'!$B$5*(1-'DCF_ADBE'!$B$6)+'DCF_ADBE'!$B$7-'DCF_ADBE'!$B$8)-'DCF_ADBE'!$B$3*(1+D13)^0*D13*'DCF_ADBE'!$B$9)/(1+'DCF_ADBE'!$B$10)^1+('DCF_ADBE'!$B$3*(1+D13)^2*('DCF_ADBE'!$B$5*(1-'DCF_ADBE'!$B$6)+'DCF_ADBE'!$B$7-'DCF_ADBE'!$B$8)-'DCF_ADBE'!$B$3*(1+D13)^1*D13*'DCF_ADBE'!$B$9)/(1+'DCF_ADBE'!$B$10)^2+('DCF_ADBE'!$B$3*(1+D13)^3*('DCF_ADBE'!$B$5*(1-'DCF_ADBE'!$B$6)+'DCF_ADBE'!$B$7-'DCF_ADBE'!$B$8)-'DCF_ADBE'!$B$3*(1+D13)^2*D13*'DCF_ADBE'!$B$9)/(1+'DCF_ADBE'!$B$10)^3+('DCF_ADBE'!$B$3*(1+D13)^4*('DCF_ADBE'!$B$5*(1-'DCF_ADBE'!$B$6)+'DCF_ADBE'!$B$7-'DCF_ADBE'!$B$8)-'DCF_ADBE'!$B$3*(1+D13)^3*D13*'DCF_ADBE'!$B$9)/(1+'DCF_ADBE'!$B$10)^4+('DCF_ADBE'!$B$3*(1+D13)^5*('DCF_ADBE'!$B$5*(1-'DCF_ADBE'!$B$6)+'DCF_ADBE'!$B$7-'DCF_ADBE'!$B$8)-'DCF_ADBE'!$B$3*(1+D13)^4*D13*'DCF_ADBE'!$B$9)/(1+'DCF_ADBE'!$B$10)^5+('DCF_ADBE'!$B$3*(1+D13)^5*(1+'DCF_ADBE'!$B$11)*('DCF_ADBE'!$B$5*(1-'DCF_ADBE'!$B$6)+'DCF_ADBE'!$B$7-'DCF_ADBE'!$B$8)-'DCF_ADBE'!$B$3*(1+D13)^5*'DCF_ADBE'!$B$11*'DCF_ADBE'!$B$9)/('DCF_ADBE'!$B$10-'DCF_ADBE'!$B$11)/(1+'DCF_ADBE'!$B$10)^5-'DCF_ADBE'!$B$13)/'DCF_ADBE'!$B$12))
A14: 6 | B14: =IF($B$3="","",IF(E13<$B$3,D13,B13)) | C14: =IF($B$3="","",IF(E13<$B$3,C13,D13)) | D14: =IF($B$3="","",(B14+C14)/2) | E14: =IF($B$3="","",((('DCF_ADBE'!$B$3*(1+D14)^1*('DCF_ADBE'!$B$5*(1-'DCF_ADBE'!$B$6)+'DCF_ADBE'!$B$7-'DCF_ADBE'!$B$8)-'DCF_ADBE'!$B$3*(1+D14)^0*D14*'DCF_ADBE'!$B$9)/(1+'DCF_ADBE'!$B$10)^1+('DCF_ADBE'!$B$3*(1+D14)^2*('DCF_ADBE'!$B$5*(1-'DCF_ADBE'!$B$6)+'DCF_ADBE'!$B$7-'DCF_ADBE'!$B$8)-'DCF_ADBE'!$B$3*(1+D14)^1*D14*'DCF_ADBE'!$B$9)/(1+'DCF_ADBE'!$B$10)^2+('DCF_ADBE'!$B$3*(1+D14)^3*('DCF_ADBE'!$B$5*(1-'DCF_ADBE'!$B$6)+'DCF_ADBE'!$B$7-'DCF_ADBE'!$B$8)-'DCF_ADBE'!$B$3*(1+D14)^2*D14*'DCF_ADBE'!$B$9)/(1+'DCF_ADBE'!$B$10)^3+('DCF_ADBE'!$B$3*(1+D14)^4*('DCF_ADBE'!$B$5*(1-'DCF_ADBE'!$B$6)+'DCF_ADBE'!$B$7-'DCF_ADBE'!$B$8)-'DCF_ADBE'!$B$3*(1+D14)^3*D14*'DCF_ADBE'!$B$9)/(1+'DCF_ADBE'!$B$10)^4+('DCF_ADBE'!$B$3*(1+D14)^5*('DCF_ADBE'!$B$5*(1-'DCF_ADBE'!$B$6)+'DCF_ADBE'!$B$7-'DCF_ADBE'!$B$8)-'DCF_ADBE'!$B$3*(1+D14)^4*D14*'DCF_ADBE'!$B$9)/(1+'DCF_ADBE'!$B$10)^5+('DCF_ADBE'!$B$3*(1+D14)^5*(1+'DCF_ADBE'!$B$11)*('DCF_ADBE'!$B$5*(1-'DCF_ADBE'!$B$6)+'DCF_ADBE'!$B$7-'DCF_ADBE'!$B$8)-'DCF_ADBE'!$B$3*(1+D14)^5*'DCF_ADBE'!$B$11*'DCF_ADBE'!$B$9)/('DCF_ADBE'!$B$10-'DCF_ADBE'!$B$11)/(1+'DCF_ADBE'!$B$10)^5-'DCF_ADBE'!$B$13)/'DCF_ADBE'!$B$12))
A15: 7 | B15: =IF($B$3="","",IF(E14<$B$3,D14,B14)) | C15: =IF($B$3="","",IF(E14<$B$3,C14,D14)) | D15: =IF($B$3="","",(B15+C15)/2) | E15: =IF($B$3="","",((('DCF_ADBE'!$B$3*(1+D15)^1*('DCF_ADBE'!$B$5*(1-'DCF_ADBE'!$B$6)+'DCF_ADBE'!$B$7-'DCF_ADBE'!$B$8)-'DCF_ADBE'!$B$3*(1+D15)^0*D15*'DCF_ADBE'!$B$9)/(1+'DCF_ADBE'!$B$10)^1+('DCF_ADBE'!$B$3*(1+D15)^2*('DCF_ADBE'!$B$5*(1-'DCF_ADBE'!$B$6)+'DCF_ADBE'!$B$7-'DCF_ADBE'!$B$8)-'DCF_ADBE'!$B$3*(1+D15)^1*D15*'DCF_ADBE'!$B$9)/(1+'DCF_ADBE'!$B$10)^2+('DCF_ADBE'!$B$3*(1+D15)^3*('DCF_ADBE'!$B$5*(1-'DCF_ADBE'!$B$6)+'DCF_ADBE'!$B$7-'DCF_ADBE'!$B$8)-'DCF_ADBE'!$B$3*(1+D15)^2*D15*'DCF_ADBE'!$B$9)/(1+'DCF_ADBE'!$B$10)^3+('DCF_ADBE'!$B$3*(1+D15)^4*('DCF_ADBE'!$B$5*(1-'DCF_ADBE'!$B$6)+'DCF_ADBE'!$B$7-'DCF_ADBE'!$B$8)-'DCF_ADBE'!$B$3*(1+D15)^3*D15*'DCF_ADBE'!$B$9)/(1+'DCF_ADBE'!$B$10)^4+('DCF_ADBE'!$B$3*(1+D15)^5*('DCF_ADBE'!$B$5*(1-'DCF_ADBE'!$B$6)+'DCF_ADBE'!$B$7-'DCF_ADBE'!$B$8)-'DCF_ADBE'!$B$3*(1+D15)^4*D15*'DCF_ADBE'!$B$9)/(1+'DCF_ADBE'!$B$10)^5+('DCF_ADBE'!$B$3*(1+D15)^5*(1+'DCF_ADBE'!$B$11)*('DCF_ADBE'!$B$5*(1-'DCF_ADBE'!$B$6)+'DCF_ADBE'!$B$7-'DCF_ADBE'!$B$8)-'DCF_ADBE'!$B$3*(1+D15)^5*'DCF_ADBE'!$B$11*'DCF_ADBE'!$B$9)/('DCF_ADBE'!$B$10-'DCF_ADBE'!$B$11)/(1+'DCF_ADBE'!$B$10)^5-'DCF_ADBE'!$B$13)/'DCF_ADBE'!$B$12))
A16: 8 | B16: =IF($B$3="","",IF(E15<$B$3,D15,B15)) | C16: =IF($B$3="","",IF(E15<$B$3,C15,D15)) | D16: =IF($B$3="","",(B16+C16)/2) | E16: =IF($B$3="","",((('DCF_ADBE'!$B$3*(1+D16)^1*('DCF_ADBE'!$B$5*(1-'DCF_ADBE'!$B$6)+'DCF_ADBE'!$B$7-'DCF_ADBE'!$B$8)-'DCF_ADBE'!$B$3*(1+D16)^0*D16*'DCF_ADBE'!$B$9)/(1+'DCF_ADBE'!$B$10)^1+('DCF_ADBE'!$B$3*(1+D16)^2*('DCF_ADBE'!$B$5*(1-'DCF_ADBE'!$B$6)+'DCF_ADBE'!$B$7-'DCF_ADBE'!$B$8)-'DCF_ADBE'!$B$3*(1+D16)^1*D16*'DCF_ADBE'!$B$9)/(1+'DCF_ADBE'!$B$10)^2+('DCF_ADBE'!$B$3*(1+D16)^3*('DCF_ADBE'!$B$5*(1-'DCF_ADBE'!$B$6)+'DCF_ADBE'!$B$7-'DCF_ADBE'!$B$8)-'DCF_ADBE'!$B$3*(1+D16)^2*D16*'DCF_ADBE'!$B$9)/(1+'DCF_ADBE'!$B$10)^3+('DCF_ADBE'!$B$3*(1+D16)^4*('DCF_ADBE'!$B$5*(1-'DCF_ADBE'!$B$6)+'DCF_ADBE'!$B$7-'DCF_ADBE'!$B$8)-'DCF_ADBE'!$B$3*(1+D16)^3*D16*'DCF_ADBE'!$B$9)/(1+'DCF_ADBE'!$B$10)^4+('DCF_ADBE'!$B$3*(1+D16)^5*('DCF_ADBE'!$B$5*(1-'DCF_ADBE'!$B$6)+'DCF_ADBE'!$B$7-'DCF_ADBE'!$B$8)-'DCF_ADBE'!$B$3*(1+D16)^4*D16*'DCF_ADBE'!$B$9)/(1+'DCF_ADBE'!$B$10)^5+('DCF_ADBE'!$B$3*(1+D16)^5*(1+'DCF_ADBE'!$B$11)*('DCF_ADBE'!$B$5*(1-'DCF_ADBE'!$B$6)+'DCF_ADBE'!$B$7-'DCF_ADBE'!$B$8)-'DCF_ADBE'!$B$3*(1+D16)^5*'DCF_ADBE'!$B$11*'DCF_ADBE'!$B$9)/('DCF_ADBE'!$B$10-'DCF_ADBE'!$B$11)/(1+'DCF_ADBE'!$B$10)^5-'DCF_ADBE'!$B$13)/'DCF_ADBE'!$B$12))
A17: 9 | B17: =IF($B$3="","",IF(E16<$B$3,D16,B16)) | C17: =IF($B$3="","",IF(E16<$B$3,C16,D16)) | D17: =IF($B$3="","",(B17+C17)/2) | E17: =IF($B$3="","",((('DCF_ADBE'!$B$3*(1+D17)^1*('DCF_ADBE'!$B$5*(1-'DCF_ADBE'!$B$6)+'DCF_ADBE'!$B$7-'DCF_ADBE'!$B$8)-'DCF_ADBE'!$B$3*(1+D17)^0*D17*'DCF_ADBE'!$B$9)/(1+'DCF_ADBE'!$B$10)^1+('DCF_ADBE'!$B$3*(1+D17)^2*('DCF_ADBE'!$B$5*(1-'DCF_ADBE'!$B$6)+'DCF_ADBE'!$B$7-'DCF_ADBE'!$B$8)-'DCF_ADBE'!$B$3*(1+D17)^1*D17*'DCF_ADBE'!$B$9)/(1+'DCF_ADBE'!$B$10)^2+('DCF_ADBE'!$B$3*(1+D17)^3*('DCF_ADBE'!$B$5*(1-'DCF_ADBE'!$B$6)+'DCF_ADBE'!$B$7-'DCF_ADBE'!$B$8)-'DCF_ADBE'!$B$3*(1+D17)^2*D17*'DCF_ADBE'!$B$9)/(1+'DCF_ADBE'!$B$10)^3+('DCF_ADBE'!$B$3*(1+D17)^4*('DCF_ADBE'!$B$5*(1-'DCF_ADBE'!$B$6)+'DCF_ADBE'!$B$7-'DCF_ADBE'!$B$8)-'DCF_ADBE'!$B$3*(1+D17)^3*D17*'DCF_ADBE'!$B$9)/(1+'DCF_ADBE'!$B$10)^4+('DCF_ADBE'!$B$3*(1+D17)^5*('DCF_ADBE'!$B$5*(1-'DCF_ADBE'!$B$6)+'DCF_ADBE'!$B$7-'DCF_ADBE'!$B$8)-'DCF_ADBE'!$B$3*(1+D17)^4*D17*'DCF_ADBE'!$B$9)/(1+'DCF_ADBE'!$B$10)^5+('DCF_ADBE'!$B$3*(1+D17)^5*(1+'DCF_ADBE'!$B$11)*('DCF_ADBE'!$B$5*(1-'DCF_ADBE'!$B$6)+'DCF_ADBE'!$B$7-'DCF_ADBE'!$B$8)-'DCF_ADBE'!$B$3*(1+D17)^5*'DCF_ADBE'!$B$11*'DCF_ADBE'!$B$9)/('DCF_ADBE'!$B$10-'DCF_ADBE'!$B$11)/(1+'DCF_ADBE'!$B$10)^5-'DCF_ADBE'!$B$13)/'DCF_ADBE'!$B$12))
A18: 10 | B18: =IF($B$3="","",IF(E17<$B$3,D17,B17)) | C18: =IF($B$3="","",IF(E17<$B$3,C17,D17)) | D18: =IF($B$3="","",(B18+C18)/2) | E18: =IF($B$3="","",((('DCF_ADBE'!$B$3*(1+D18)^1*('DCF_ADBE'!$B$5*(1-'DCF_ADBE'!$B$6)+'DCF_ADBE'!$B$7-'DCF_ADBE'!$B$8)-'DCF_ADBE'!$B$3*(1+D18)^0*D18*'DCF_ADBE'!$B$9)/(1+'DCF_ADBE'!$B$10)^1+('DCF_ADBE'!$B$3*(1+D18)^2*('DCF_ADBE'!$B$5*(1-'DCF_ADBE'!$B$6)+'DCF_ADBE'!$B$7-'DCF_ADBE'!$B$8)-'DCF_ADBE'!$B$3*(1+D18)^1*D18*'DCF_ADBE'!$B$9)/(1+'DCF_ADBE'!$B$10)^2+('DCF_ADBE'!$B$3*(1+D18)^3*('DCF_ADBE'!$B$5*(1-'DCF_ADBE'!$B$6)+'DCF_ADBE'!$B$7-'DCF_ADBE'!$B$8)-'DCF_ADBE'!$B$3*(1+D18)^2*D18*'DCF_ADBE'!$B$9)/(1+'DCF_ADBE'!$B$10)^3+('DCF_ADBE'!$B$3*(1+D18)^4*('DCF_ADBE'!$B$5*(1-'DCF_ADBE'!$B$6)+'DCF_ADBE'!$B$7-'DCF_ADBE'!$B$8)-'DCF_ADBE'!$B$3*(1+D18)^3*D18*'DCF_ADBE'!$B$9)/(1+'DCF_ADBE'!$B$10)^4+('DCF_ADBE'!$B$3*(1+D18)^5*('DCF_ADBE'!$B$5*(1-'DCF_ADBE'!$B$6)+'DCF_ADBE'!$B$7-'DCF_ADBE'!$B$8)-'DCF_ADBE'!$B$3*(1+D18)^4*D18*'DCF_ADBE'!$B$9)/(1+'DCF_ADBE'!$B$10)^5+('DCF_ADBE'!$B$3*(1+D18)^5*(1+'DCF_ADBE'!$B$11)*('DCF_ADBE'!$B$5*(1-'DCF_ADBE'!$B$6)+'DCF_ADBE'!$B$7-'DCF_ADBE'!$B$8)-'DCF_ADBE'!$B$3*(1+D18)^5*'DCF_ADBE'!$B$11*'DCF_ADBE'!$B$9)/('DCF_ADBE'!$B$10-'DCF_ADBE'!$B$11)/(1+'DCF_ADBE'!$B$10)^5-'DCF_ADBE'!$B$13)/'DCF_ADBE'!$B$12))
A19: 11 | B19: =IF($B$3="","",IF(E18<$B$3,D18,B18)) | C19: =IF($B$3="","",IF(E18<$B$3,C18,D18)) | D19: =IF($B$3="","",(B19+C19)/2) | E19: =IF($B$3="","",((('DCF_ADBE'!$B$3*(1+D19)^1*('DCF_ADBE'!$B$5*(1-'DCF_ADBE'!$B$6)+'DCF_ADBE'!$B$7-'DCF_ADBE'!$B$8)-'DCF_ADBE'!$B$3*(1+D19)^0*D19*'DCF_ADBE'!$B$9)/(1+'DCF_ADBE'!$B$10)^1+('DCF_ADBE'!$B$3*(1+D19)^2*('DCF_ADBE'!$B$5*(1-'DCF_ADBE'!$B$6)+'DCF_ADBE'!$B$7-'DCF_ADBE'!$B$8)-'DCF_ADBE'!$B$3*(1+D19)^1*D19*'DCF_ADBE'!$B$9)/(1+'DCF_ADBE'!$B$10)^2+('DCF_ADBE'!$B$3*(1+D19)^3*('DCF_ADBE'!$B$5*(1-'DCF_ADBE'!$B$6)+'DCF_ADBE'!$B$7-'DCF_ADBE'!$B$8)-'DCF_ADBE'!$B$3*(1+D19)^2*D19*'DCF_ADBE'!$B$9)/(1+'DCF_ADBE'!$B$10)^3+('DCF_ADBE'!$B$3*(1+D19)^4*('DCF_ADBE'!$B$5*(1-'DCF_ADBE'!$B$6)+'DCF_ADBE'!$B$7-'DCF_ADBE'!$B$8)-'DCF_ADBE'!$B$3*(1+D19)^3*D19*'DCF_ADBE'!$B$9)/(1+'DCF_ADBE'!$B$10)^4+('DCF_ADBE'!$B$3*(1+D19)^5*('DCF_ADBE'!$B$5*(1-'DCF_ADBE'!$B$6)+'DCF_ADBE'!$B$7-'DCF_ADBE'!$B$8)-'DCF_ADBE'!$B$3*(1+D19)^4*D19*'DCF_ADBE'!$B$9)/(1+'DCF_ADBE'!$B$10)^5+('DCF_ADBE'!$B$3*(1+D19)^5*(1+'DCF_ADBE'!$B$11)*('DCF_ADBE'!$B$5*(1-'DCF_ADBE'!$B$6)+'DCF_ADBE'!$B$7-'DCF_ADBE'!$B$8)-'DCF_ADBE'!$B$3*(1+D19)^5*'DCF_ADBE'!$B$11*'DCF_ADBE'!$B$9)/('DCF_ADBE'!$B$10-'DCF_ADBE'!$B$11)/(1+'DCF_ADBE'!$B$10)^5-'DCF_ADBE'!$B$13)/'DCF_ADBE'!$B$12))
A20: 12 | B20: =IF($B$3="","",IF(E19<$B$3,D19,B19)) | C20: =IF($B$3="","",IF(E19<$B$3,C19,D19)) | D20: =IF($B$3="","",(B20+C20)/2) | E20: =IF($B$3="","",((('DCF_ADBE'!$B$3*(1+D20)^1*('DCF_ADBE'!$B$5*(1-'DCF_ADBE'!$B$6)+'DCF_ADBE'!$B$7-'DCF_ADBE'!$B$8)-'DCF_ADBE'!$B$3*(1+D20)^0*D20*'DCF_ADBE'!$B$9)/(1+'DCF_ADBE'!$B$10)^1+('DCF_ADBE'!$B$3*(1+D20)^2*('DCF_ADBE'!$B$5*(1-'DCF_ADBE'!$B$6)+'DCF_ADBE'!$B$7-'DCF_ADBE'!$B$8)-'DCF_ADBE'!$B$3*(1+D20)^1*D20*'DCF_ADBE'!$B$9)/(1+'DCF_ADBE'!$B$10)^2+('DCF_ADBE'!$B$3*(1+D20)^3*('DCF_ADBE'!$B$5*(1-'DCF_ADBE'!$B$6)+'DCF_ADBE'!$B$7-'DCF_ADBE'!$B$8)-'DCF_ADBE'!$B$3*(1+D20)^2*D20*'DCF_ADBE'!$B$9)/(1+'DCF_ADBE'!$B$10)^3+('DCF_ADBE'!$B$3*(1+D20)^4*('DCF_ADBE'!$B$5*(1-'DCF_ADBE'!$B$6)+'DCF_ADBE'!$B$7-'DCF_ADBE'!$B$8)-'DCF_ADBE'!$B$3*(1+D20)^3*D20*'DCF_ADBE'!$B$9)/(1+'DCF_ADBE'!$B$10)^4+('DCF_ADBE'!$B$3*(1+D20)^5*('DCF_ADBE'!$B$5*(1-'DCF_ADBE'!$B$6)+'DCF_ADBE'!$B$7-'DCF_ADBE'!$B$8)-'DCF_ADBE'!$B$3*(1+D20)^4*D20*'DCF_ADBE'!$B$9)/(1+'DCF_ADBE'!$B$10)^5+('DCF_ADBE'!$B$3*(1+D20)^5*(1+'DCF_ADBE'!$B$11)*('DCF_ADBE'!$B$5*(1-'DCF_ADBE'!$B$6)+'DCF_ADBE'!$B$7-'DCF_ADBE'!$B$8)-'DCF_ADBE'!$B$3*(1+D20)^5*'DCF_ADBE'!$B$11*'DCF_ADBE'!$B$9)/('DCF_ADBE'!$B$10-'DCF_ADBE'!$B$11)/(1+'DCF_ADBE'!$B$10)^5-'DCF_ADBE'!$B$13)/'DCF_ADBE'!$B$12))
A21: 13 | B21: =IF($B$3="","",IF(E20<$B$3,D20,B20)) | C21: =IF($B$3="","",IF(E20<$B$3,C20,D20)) | D21: =IF($B$3="","",(B21+C21)/2) | E21: =IF($B$3="","",((('DCF_ADBE'!$B$3*(1+D21)^1*('DCF_ADBE'!$B$5*(1-'DCF_ADBE'!$B$6)+'DCF_ADBE'!$B$7-'DCF_ADBE'!$B$8)-'DCF_ADBE'!$B$3*(1+D21)^0*D21*'DCF_ADBE'!$B$9)/(1+'DCF_ADBE'!$B$10)^1+('DCF_ADBE'!$B$3*(1+D21)^2*('DCF_ADBE'!$B$5*(1-'DCF_ADBE'!$B$6)+'DCF_ADBE'!$B$7-'DCF_ADBE'!$B$8)-'DCF_ADBE'!$B$3*(1+D21)^1*D21*'DCF_ADBE'!$B$9)/(1+'DCF_ADBE'!$B$10)^2+('DCF_ADBE'!$B$3*(1+D21)^3*('DCF_ADBE'!$B$5*(1-'DCF_ADBE'!$B$6)+'DCF_ADBE'!$B$7-'DCF_ADBE'!$B$8)-'DCF_ADBE'!$B$3*(1+D21)^2*D21*'DCF_ADBE'!$B$9)/(1+'DCF_ADBE'!$B$10)^3+('DCF_ADBE'!$B$3*(1+D21)^4*('DCF_ADBE'!$B$5*(1-'DCF_ADBE'!$B$6)+'DCF_ADBE'!$B$7-'DCF_ADBE'!$B$8)-'DCF_ADBE'!$B$3*(1+D21)^3*D21*'DCF_ADBE'!$B$9)/(1+'DCF_ADBE'!$B$10)^4+('DCF_ADBE'!$B$3*(1+D21)^5*('DCF_ADBE'!$B$5*(1-'DCF_ADBE'!$B$6)+'DCF_ADBE'!$B$7-'DCF_ADBE'!$B$8)-'DCF_ADBE'!$B$3*(1+D21)^4*D21*'DCF_ADBE'!$B$9)/(1+'DCF_ADBE'!$B$10)^5+('DCF_ADBE'!$B$3*(1+D21)^5*(1+'DCF_ADBE'!$B$11)*('DCF_ADBE'!$B$5*(1-'DCF_ADBE'!$B$6)+'DCF_ADBE'!$B$7-'DCF_ADBE'!$B$8)-'DCF_ADBE'!$B$3*(1+D21)^5*'DCF_ADBE'!$B$11*'DCF_ADBE'!$B$9)/('DCF_ADBE'!$B$10-'DCF_ADBE'!$B$11)/(1+'DCF_ADBE'!$B$10)^5-'DCF_ADBE'!$B$13)/'DCF_ADBE'!$B$12))
... A68: 60 | B68: =IF($B$3="","",IF(E67<$B$3,D67,B67)) | C68: =IF($B$3="","",IF(E67<$B$3,C67,D67)) | D68: =IF($B$3="","",(B68+C68)/2) | E68: =IF($B$3="","",((('DCF_ADBE'!$B$3*(1+D68)^1*('DCF_ADBE'!$B$5*(1-'DCF_ADBE'!$B$6)+'DCF_ADBE'!$B$7-'DCF_ADBE'!$B$8)-'DCF_ADBE'!$B$3*(1+D68)^0*D68*'DCF_ADBE'!$B$9)/(1+'DCF_ADBE'!$B$10)^1+('DCF_ADBE'!$B$3*(1+D68)^2*('DCF_ADBE'!$B$5*(1-'DCF_ADBE'!$B$6)+'DCF_ADBE'!$B$7-'DCF_ADBE'!$B$8)-'DCF_ADBE'!$B$3*(1+D68)^1*D68*'DCF_ADBE'!$B$9)/(1+'DCF_ADBE'!$B$10)^2+('DCF_ADBE'!$B$3*(1+D68)^3*('DCF_ADBE'!$B$5*(1-'DCF_ADBE'!$B$6)+'DCF_ADBE'!$B$7-'DCF_ADBE'!$B$8)-'DCF_ADBE'!$B$3*(1+D68)^2*D68*'DCF_ADBE'!$B$9)/(1+'DCF_ADBE'!$B$10)^3+('DCF_ADBE'!$B$3*(1+D68)^4*('DCF_ADBE'!$B$5*(1-'DCF_ADBE'!$B$6)+'DCF_ADBE'!$B$7-'DCF_ADBE'!$B$8)-'DCF_ADBE'!$B$3*(1+D68)^3*D68*'DCF_ADBE'!$B$9)/(1+'DCF_ADBE'!$B$10)^4+('DCF_ADBE'!$B$3*(1+D68)^5*('DCF_ADBE'!$B$5*(1-'DCF_ADBE'!$B$6)+'DCF_ADBE'!$B$7-'DCF_ADBE'!$B$8)-'DCF_ADBE'!$B$3*(1+D68)^4*D68*'DCF_ADBE'!$B$9)/(1+'DCF_ADBE'!$B$10)^5+('DCF_ADBE'!$B$3*(1+D68)^5*(1+'DCF_ADBE'!$B$11)*('DCF_ADBE'!$B$5*(1-'DCF_ADBE'!$B$6)+'DCF_ADBE'!$B$7-'DCF_ADBE'!$B$8)-'DCF_ADBE'!$B$3*(1+D68)^5*'DCF_ADBE'!$B$11*'DCF_ADBE'!$B$9)/('DCF_ADBE'!$B$10-'DCF_ADBE'!$B$11)/(1+'DCF_ADBE'!$B$10)^5-'DCF_ADBE'!$B$13)/'DCF_ADBE'!$B$12))
A72: PYPL | B72: Lower growth | C72: Upper growth | D72: Mid growth | E72: Model price
A73: 1 | B73: -0.45 | C73: 0.5 | D73: =IF($B$4="","",(B73+C73)/2) | E73: =IF($B$4="","",((('DCF_PYPL'!$B$3*(1+D73)^1*('DCF_PYPL'!$B$5*(1-'DCF_PYPL'!$B$6)+'DCF_PYPL'!$B$7-'DCF_PYPL'!$B$8)-'DCF_PYPL'!$B$3*(1+D73)^0*D73*'DCF_PYPL'!$B$9)/(1+'DCF_PYPL'!$B$10)^1+('DCF_PYPL'!$B$3*(1+D73)^2*('DCF_PYPL'!$B$5*(1-'DCF_PYPL'!$B$6)+'DCF_PYPL'!$B$7-'DCF_PYPL'!$B$8)-'DCF_PYPL'!$B$3*(1+D73)^1*D73*'DCF_PYPL'!$B$9)/(1+'DCF_PYPL'!$B$10)^2+('DCF_PYPL'!$B$3*(1+D73)^3*('DCF_PYPL'!$B$5*(1-'DCF_PYPL'!$B$6)+'DCF_PYPL'!$B$7-'DCF_PYPL'!$B$8)-'DCF_PYPL'!$B$3*(1+D73)^2*D73*'DCF_PYPL'!$B$9)/(1+'DCF_PYPL'!$B$10)^3+('DCF_PYPL'!$B$3*(1+D73)^4*('DCF_PYPL'!$B$5*(1-'DCF_PYPL'!$B$6)+'DCF_PYPL'!$B$7-'DCF_PYPL'!$B$8)-'DCF_PYPL'!$B$3*(1+D73)^3*D73*'DCF_PYPL'!$B$9)/(1+'DCF_PYPL'!$B$10)^4+('DCF_PYPL'!$B$3*(1+D73)^5*('DCF_PYPL'!$B$5*(1-'DCF_PYPL'!$B$6)+'DCF_PYPL'!$B$7-'DCF_PYPL'!$B$8)-'DCF_PYPL'!$B$3*(1+D73)^4*D73*'DCF_PYPL'!$B$9)/(1+'DCF_PYPL'!$B$10)^5+('DCF_PYPL'!$B$3*(1+D73)^5*(1+'DCF_PYPL'!$B$11)*('DCF_PYPL'!$B$5*(1-'DCF_PYPL'!$B$6)+'DCF_PYPL'!$B$7-'DCF_PYPL'!$B$8)-'DCF_PYPL'!$B$3*(1+D73)^5*'DCF_PYPL'!$B$11*'DCF_PYPL'!$B$9)/('DCF_PYPL'!$B$10-'DCF_PYPL'!$B$11)/(1+'DCF_PYPL'!$B$10)^5-'DCF_PYPL'!$B$13)/'DCF_PYPL'!$B$12))
A74: 2 | B74: =IF($B$4="","",IF(E73<$B$4,D73,B73)) | C74: =IF($B$4="","",IF(E73<$B$4,C73,D73)) | D74: =IF($B$4="","",(B74+C74)/2) | E74: =IF($B$4="","",((('DCF_PYPL'!$B$3*(1+D74)^1*('DCF_PYPL'!$B$5*(1-'DCF_PYPL'!$B$6)+'DCF_PYPL'!$B$7-'DCF_PYPL'!$B$8)-'DCF_PYPL'!$B$3*(1+D74)^0*D74*'DCF_PYPL'!$B$9)/(1+'DCF_PYPL'!$B$10)^1+('DCF_PYPL'!$B$3*(1+D74)^2*('DCF_PYPL'!$B$5*(1-'DCF_PYPL'!$B$6)+'DCF_PYPL'!$B$7-'DCF_PYPL'!$B$8)-'DCF_PYPL'!$B$3*(1+D74)^1*D74*'DCF_PYPL'!$B$9)/(1+'DCF_PYPL'!$B$10)^2+('DCF_PYPL'!$B$3*(1+D74)^3*('DCF_PYPL'!$B$5*(1-'DCF_PYPL'!$B$6)+'DCF_PYPL'!$B$7-'DCF_PYPL'!$B$8)-'DCF_PYPL'!$B$3*(1+D74)^2*D74*'DCF_PYPL'!$B$9)/(1+'DCF_PYPL'!$B$10)^3+('DCF_PYPL'!$B$3*(1+D74)^4*('DCF_PYPL'!$B$5*(1-'DCF_PYPL'!$B$6)+'DCF_PYPL'!$B$7-'DCF_PYPL'!$B$8)-'DCF_PYPL'!$B$3*(1+D74)^3*D74*'DCF_PYPL'!$B$9)/(1+'DCF_PYPL'!$B$10)^4+('DCF_PYPL'!$B$3*(1+D74)^5*('DCF_PYPL'!$B$5*(1-'DCF_PYPL'!$B$6)+'DCF_PYPL'!$B$7-'DCF_PYPL'!$B$8)-'DCF_PYPL'!$B$3*(1+D74)^4*D74*'DCF_PYPL'!$B$9)/(1+'DCF_PYPL'!$B$10)^5+('DCF_PYPL'!$B$3*(1+D74)^5*(1+'DCF_PYPL'!$B$11)*('DCF_PYPL'!$B$5*(1-'DCF_PYPL'!$B$6)+'DCF_PYPL'!$B$7-'DCF_PYPL'!$B$8)-'DCF_PYPL'!$B$3*(1+D74)^5*'DCF_PYPL'!$B$11*'DCF_PYPL'!$B$9)/('DCF_PYPL'!$B$10-'DCF_PYPL'!$B$11)/(1+'DCF_PYPL'!$B$10)^5-'DCF_PYPL'!$B$13)/'DCF_PYPL'!$B$12))
A75: 3 | B75: =IF($B$4="","",IF(E74<$B$4,D74,B74)) | C75: =IF($B$4="","",IF(E74<$B$4,C74,D74)) | D75: =IF($B$4="","",(B75+C75)/2) | E75: =IF($B$4="","",((('DCF_PYPL'!$B$3*(1+D75)^1*('DCF_PYPL'!$B$5*(1-'DCF_PYPL'!$B$6)+'DCF_PYPL'!$B$7-'DCF_PYPL'!$B$8)-'DCF_PYPL'!$B$3*(1+D75)^0*D75*'DCF_PYPL'!$B$9)/(1+'DCF_PYPL'!$B$10)^1+('DCF_PYPL'!$B$3*(1+D75)^2*('DCF_PYPL'!$B$5*(1-'DCF_PYPL'!$B$6)+'DCF_PYPL'!$B$7-'DCF_PYPL'!$B$8)-'DCF_PYPL'!$B$3*(1+D75)^1*D75*'DCF_PYPL'!$B$9)/(1+'DCF_PYPL'!$B$10)^2+('DCF_PYPL'!$B$3*(1+D75)^3*('DCF_PYPL'!$B$5*(1-'DCF_PYPL'!$B$6)+'DCF_PYPL'!$B$7-'DCF_PYPL'!$B$8)-'DCF_PYPL'!$B$3*(1+D75)^2*D75*'DCF_PYPL'!$B$9)/(1+'DCF_PYPL'!$B$10)^3+('DCF_PYPL'!$B$3*(1+D75)^4*('DCF_PYPL'!$B$5*(1-'DCF_PYPL'!$B$6)+'DCF_PYPL'!$B$7-'DCF_PYPL'!$B$8)-'DCF_PYPL'!$B$3*(1+D75)^3*D75*'DCF_PYPL'!$B$9)/(1+'DCF_PYPL'!$B$10)^4+('DCF_PYPL'!$B$3*(1+D75)^5*('DCF_PYPL'!$B$5*(1-'DCF_PYPL'!$B$6)+'DCF_PYPL'!$B$7-'DCF_PYPL'!$B$8)-'DCF_PYPL'!$B$3*(1+D75)^4*D75*'DCF_PYPL'!$B$9)/(1+'DCF_PYPL'!$B$10)^5+('DCF_PYPL'!$B$3*(1+D75)^5*(1+'DCF_PYPL'!$B$11)*('DCF_PYPL'!$B$5*(1-'DCF_PYPL'!$B$6)+'DCF_PYPL'!$B$7-'DCF_PYPL'!$B$8)-'DCF_PYPL'!$B$3*(1+D75)^5*'DCF_PYPL'!$B$11*'DCF_PYPL'!$B$9)/('DCF_PYPL'!$B$10-'DCF_PYPL'!$B$11)/(1+'DCF_PYPL'!$B$10)^5-'DCF_PYPL'!$B$13)/'DCF_PYPL'!$B$12))
A76: 4 | B76: =IF($B$4="","",IF(E75<$B$4,D75,B75)) | C76: =IF($B$4="","",IF(E75<$B$4,C75,D75)) | D76: =IF($B$4="","",(B76+C76)/2) | E76: =IF($B$4="","",((('DCF_PYPL'!$B$3*(1+D76)^1*('DCF_PYPL'!$B$5*(1-'DCF_PYPL'!$B$6)+'DCF_PYPL'!$B$7-'DCF_PYPL'!$B$8)-'DCF_PYPL'!$B$3*(1+D76)^0*D76*'DCF_PYPL'!$B$9)/(1+'DCF_PYPL'!$B$10)^1+('DCF_PYPL'!$B$3*(1+D76)^2*('DCF_PYPL'!$B$5*(1-'DCF_PYPL'!$B$6)+'DCF_PYPL'!$B$7-'DCF_PYPL'!$B$8)-'DCF_PYPL'!$B$3*(1+D76)^1*D76*'DCF_PYPL'!$B$9)/(1+'DCF_PYPL'!$B$10)^2+('DCF_PYPL'!$B$3*(1+D76)^3*('DCF_PYPL'!$B$5*(1-'DCF_PYPL'!$B$6)+'DCF_PYPL'!$B$7-'DCF_PYPL'!$B$8)-'DCF_PYPL'!$B$3*(1+D76)^2*D76*'DCF_PYPL'!$B$9)/(1+'DCF_PYPL'!$B$10)^3+('DCF_PYPL'!$B$3*(1+D76)^4*('DCF_PYPL'!$B$5*(1-'DCF_PYPL'!$B$6)+'DCF_PYPL'!$B$7-'DCF_PYPL'!$B$8)-'DCF_PYPL'!$B$3*(1+D76)^3*D76*'DCF_PYPL'!$B$9)/(1+'DCF_PYPL'!$B$10)^4+('DCF_PYPL'!$B$3*(1+D76)^5*('DCF_PYPL'!$B$5*(1-'DCF_PYPL'!$B$6)+'DCF_PYPL'!$B$7-'DCF_PYPL'!$B$8)-'DCF_PYPL'!$B$3*(1+D76)^4*D76*'DCF_PYPL'!$B$9)/(1+'DCF_PYPL'!$B$10)^5+('DCF_PYPL'!$B$3*(1+D76)^5*(1+'DCF_PYPL'!$B$11)*('DCF_PYPL'!$B$5*(1-'DCF_PYPL'!$B$6)+'DCF_PYPL'!$B$7-'DCF_PYPL'!$B$8)-'DCF_PYPL'!$B$3*(1+D76)^5*'DCF_PYPL'!$B$11*'DCF_PYPL'!$B$9)/('DCF_PYPL'!$B$10-'DCF_PYPL'!$B$11)/(1+'DCF_PYPL'!$B$10)^5-'DCF_PYPL'!$B$13)/'DCF_PYPL'!$B$12))
A77: 5 | B77: =IF($B$4="","",IF(E76<$B$4,D76,B76)) | C77: =IF($B$4="","",IF(E76<$B$4,C76,D76)) | D77: =IF($B$4="","",(B77+C77)/2) | E77: =IF($B$4="","",((('DCF_PYPL'!$B$3*(1+D77)^1*('DCF_PYPL'!$B$5*(1-'DCF_PYPL'!$B$6)+'DCF_PYPL'!$B$7-'DCF_PYPL'!$B$8)-'DCF_PYPL'!$B$3*(1+D77)^0*D77*'DCF_PYPL'!$B$9)/(1+'DCF_PYPL'!$B$10)^1+('DCF_PYPL'!$B$3*(1+D77)^2*('DCF_PYPL'!$B$5*(1-'DCF_PYPL'!$B$6)+'DCF_PYPL'!$B$7-'DCF_PYPL'!$B$8)-'DCF_PYPL'!$B$3*(1+D77)^1*D77*'DCF_PYPL'!$B$9)/(1+'DCF_PYPL'!$B$10)^2+('DCF_PYPL'!$B$3*(1+D77)^3*('DCF_PYPL'!$B$5*(1-'DCF_PYPL'!$B$6)+'DCF_PYPL'!$B$7-'DCF_PYPL'!$B$8)-'DCF_PYPL'!$B$3*(1+D77)^2*D77*'DCF_PYPL'!$B$9)/(1+'DCF_PYPL'!$B$10)^3+('DCF_PYPL'!$B$3*(1+D77)^4*('DCF_PYPL'!$B$5*(1-'DCF_PYPL'!$B$6)+'DCF_PYPL'!$B$7-'DCF_PYPL'!$B$8)-'DCF_PYPL'!$B$3*(1+D77)^3*D77*'DCF_PYPL'!$B$9)/(1+'DCF_PYPL'!$B$10)^4+('DCF_PYPL'!$B$3*(1+D77)^5*('DCF_PYPL'!$B$5*(1-'DCF_PYPL'!$B$6)+'DCF_PYPL'!$B$7-'DCF_PYPL'!$B$8)-'DCF_PYPL'!$B$3*(1+D77)^4*D77*'DCF_PYPL'!$B$9)/(1+'DCF_PYPL'!$B$10)^5+('DCF_PYPL'!$B$3*(1+D77)^5*(1+'DCF_PYPL'!$B$11)*('DCF_PYPL'!$B$5*(1-'DCF_PYPL'!$B$6)+'DCF_PYPL'!$B$7-'DCF_PYPL'!$B$8)-'DCF_PYPL'!$B$3*(1+D77)^5*'DCF_PYPL'!$B$11*'DCF_PYPL'!$B$9)/('DCF_PYPL'!$B$10-'DCF_PYPL'!$B$11)/(1+'DCF_PYPL'!$B$10)^5-'DCF_PYPL'!$B$13)/'DCF_PYPL'!$B$12))
A78: 6 | B78: =IF($B$4="","",IF(E77<$B$4,D77,B77)) | C78: =IF($B$4="","",IF(E77<$B$4,C77,D77)) | D78: =IF($B$4="","",(B78+C78)/2) | E78: =IF($B$4="","",((('DCF_PYPL'!$B$3*(1+D78)^1*('DCF_PYPL'!$B$5*(1-'DCF_PYPL'!$B$6)+'DCF_PYPL'!$B$7-'DCF_PYPL'!$B$8)-'DCF_PYPL'!$B$3*(1+D78)^0*D78*'DCF_PYPL'!$B$9)/(1+'DCF_PYPL'!$B$10)^1+('DCF_PYPL'!$B$3*(1+D78)^2*('DCF_PYPL'!$B$5*(1-'DCF_PYPL'!$B$6)+'DCF_PYPL'!$B$7-'DCF_PYPL'!$B$8)-'DCF_PYPL'!$B$3*(1+D78)^1*D78*'DCF_PYPL'!$B$9)/(1+'DCF_PYPL'!$B$10)^2+('DCF_PYPL'!$B$3*(1+D78)^3*('DCF_PYPL'!$B$5*(1-'DCF_PYPL'!$B$6)+'DCF_PYPL'!$B$7-'DCF_PYPL'!$B$8)-'DCF_PYPL'!$B$3*(1+D78)^2*D78*'DCF_PYPL'!$B$9)/(1+'DCF_PYPL'!$B$10)^3+('DCF_PYPL'!$B$3*(1+D78)^4*('DCF_PYPL'!$B$5*(1-'DCF_PYPL'!$B$6)+'DCF_PYPL'!$B$7-'DCF_PYPL'!$B$8)-'DCF_PYPL'!$B$3*(1+D78)^3*D78*'DCF_PYPL'!$B$9)/(1+'DCF_PYPL'!$B$10)^4+('DCF_PYPL'!$B$3*(1+D78)^5*('DCF_PYPL'!$B$5*(1-'DCF_PYPL'!$B$6)+'DCF_PYPL'!$B$7-'DCF_PYPL'!$B$8)-'DCF_PYPL'!$B$3*(1+D78)^4*D78*'DCF_PYPL'!$B$9)/(1+'DCF_PYPL'!$B$10)^5+('DCF_PYPL'!$B$3*(1+D78)^5*(1+'DCF_PYPL'!$B$11)*('DCF_PYPL'!$B$5*(1-'DCF_PYPL'!$B$6)+'DCF_PYPL'!$B$7-'DCF_PYPL'!$B$8)-'DCF_PYPL'!$B$3*(1+D78)^5*'DCF_PYPL'!$B$11*'DCF_PYPL'!$B$9)/('DCF_PYPL'!$B$10-'DCF_PYPL'!$B$11)/(1+'DCF_PYPL'!$B$10)^5-'DCF_PYPL'!$B$13)/'DCF_PYPL'!$B$12))
A79: 7 | B79: =IF($B$4="","",IF(E78<$B$4,D78,B78)) | C79: =IF($B$4="","",IF(E78<$B$4,C78,D78)) | D79: =IF($B$4="","",(B79+C79)/2) | E79: =IF($B$4="","",((('DCF_PYPL'!$B$3*(1+D79)^1*('DCF_PYPL'!$B$5*(1-'DCF_PYPL'!$B$6)+'DCF_PYPL'!$B$7-'DCF_PYPL'!$B$8)-'DCF_PYPL'!$B$3*(1+D79)^0*D79*'DCF_PYPL'!$B$9)/(1+'DCF_PYPL'!$B$10)^1+('DCF_PYPL'!$B$3*(1+D79)^2*('DCF_PYPL'!$B$5*(1-'DCF_PYPL'!$B$6)+'DCF_PYPL'!$B$7-'DCF_PYPL'!$B$8)-'DCF_PYPL'!$B$3*(1+D79)^1*D79*'DCF_PYPL'!$B$9)/(1+'DCF_PYPL'!$B$10)^2+('DCF_PYPL'!$B$3*(1+D79)^3*('DCF_PYPL'!$B$5*(1-'DCF_PYPL'!$B$6)+'DCF_PYPL'!$B$7-'DCF_PYPL'!$B$8)-'DCF_PYPL'!$B$3*(1+D79)^2*D79*'DCF_PYPL'!$B$9)/(1+'DCF_PYPL'!$B$10)^3+('DCF_PYPL'!$B$3*(1+D79)^4*('DCF_PYPL'!$B$5*(1-'DCF_PYPL'!$B$6)+'DCF_PYPL'!$B$7-'DCF_PYPL'!$B$8)-'DCF_PYPL'!$B$3*(1+D79)^3*D79*'DCF_PYPL'!$B$9)/(1+'DCF_PYPL'!$B$10)^4+('DCF_PYPL'!$B$3*(1+D79)^5*('DCF_PYPL'!$B$5*(1-'DCF_PYPL'!$B$6)+'DCF_PYPL'!$B$7-'DCF_PYPL'!$B$8)-'DCF_PYPL'!$B$3*(1+D79)^4*D79*'DCF_PYPL'!$B$9)/(1+'DCF_PYPL'!$B$10)^5+('DCF_PYPL'!$B$3*(1+D79)^5*(1+'DCF_PYPL'!$B$11)*('DCF_PYPL'!$B$5*(1-'DCF_PYPL'!$B$6)+'DCF_PYPL'!$B$7-'DCF_PYPL'!$B$8)-'DCF_PYPL'!$B$3*(1+D79)^5*'DCF_PYPL'!$B$11*'DCF_PYPL'!$B$9)/('DCF_PYPL'!$B$10-'DCF_PYPL'!$B$11)/(1+'DCF_PYPL'!$B$10)^5-'DCF_PYPL'!$B$13)/'DCF_PYPL'!$B$12))
A80: 8 | B80: =IF($B$4="","",IF(E79<$B$4,D79,B79)) | C80: =IF($B$4="","",IF(E79<$B$4,C79,D79)) | D80: =IF($B$4="","",(B80+C80)/2) | E80: =IF($B$4="","",((('DCF_PYPL'!$B$3*(1+D80)^1*('DCF_PYPL'!$B$5*(1-'DCF_PYPL'!$B$6)+'DCF_PYPL'!$B$7-'DCF_PYPL'!$B$8)-'DCF_PYPL'!$B$3*(1+D80)^0*D80*'DCF_PYPL'!$B$9)/(1+'DCF_PYPL'!$B$10)^1+('DCF_PYPL'!$B$3*(1+D80)^2*('DCF_PYPL'!$B$5*(1-'DCF_PYPL'!$B$6)+'DCF_PYPL'!$B$7-'DCF_PYPL'!$B$8)-'DCF_PYPL'!$B$3*(1+D80)^1*D80*'DCF_PYPL'!$B$9)/(1+'DCF_PYPL'!$B$10)^2+('DCF_PYPL'!$B$3*(1+D80)^3*('DCF_PYPL'!$B$5*(1-'DCF_PYPL'!$B$6)+'DCF_PYPL'!$B$7-'DCF_PYPL'!$B$8)-'DCF_PYPL'!$B$3*(1+D80)^2*D80*'DCF_PYPL'!$B$9)/(1+'DCF_PYPL'!$B$10)^3+('DCF_PYPL'!$B$3*(1+D80)^4*('DCF_PYPL'!$B$5*(1-'DCF_PYPL'!$B$6)+'DCF_PYPL'!$B$7-'DCF_PYPL'!$B$8)-'DCF_PYPL'!$B$3*(1+D80)^3*D80*'DCF_PYPL'!$B$9)/(1+'DCF_PYPL'!$B$10)^4+('DCF_PYPL'!$B$3*(1+D80)^5*('DCF_PYPL'!$B$5*(1-'DCF_PYPL'!$B$6)+'DCF_PYPL'!$B$7-'DCF_PYPL'!$B$8)-'DCF_PYPL'!$B$3*(1+D80)^4*D80*'DCF_PYPL'!$B$9)/(1+'DCF_PYPL'!$B$10)^5+('DCF_PYPL'!$B$3*(1+D80)^5*(1+'DCF_PYPL'!$B$11)*('DCF_PYPL'!$B$5*(1-'DCF_PYPL'!$B$6)+'DCF_PYPL'!$B$7-'DCF_PYPL'!$B$8)-'DCF_PYPL'!$B$3*(1+D80)^5*'DCF_PYPL'!$B$11*'DCF_PYPL'!$B$9)/('DCF_PYPL'!$B$10-'DCF_PYPL'!$B$11)/(1+'DCF_PYPL'!$B$10)^5-'DCF_PYPL'!$B$13)/'DCF_PYPL'!$B$12))
A81: 9 | B81: =IF($B$4="","",IF(E80<$B$4,D80,B80)) | C81: =IF($B$4="","",IF(E80<$B$4,C80,D80)) | D81: =IF($B$4="","",(B81+C81)/2) | E81: =IF($B$4="","",((('DCF_PYPL'!$B$3*(1+D81)^1*('DCF_PYPL'!$B$5*(1-'DCF_PYPL'!$B$6)+'DCF_PYPL'!$B$7-'DCF_PYPL'!$B$8)-'DCF_PYPL'!$B$3*(1+D81)^0*D81*'DCF_PYPL'!$B$9)/(1+'DCF_PYPL'!$B$10)^1+('DCF_PYPL'!$B$3*(1+D81)^2*('DCF_PYPL'!$B$5*(1-'DCF_PYPL'!$B$6)+'DCF_PYPL'!$B$7-'DCF_PYPL'!$B$8)-'DCF_PYPL'!$B$3*(1+D81)^1*D81*'DCF_PYPL'!$B$9)/(1+'DCF_PYPL'!$B$10)^2+('DCF_PYPL'!$B$3*(1+D81)^3*('DCF_PYPL'!$B$5*(1-'DCF_PYPL'!$B$6)+'DCF_PYPL'!$B$7-'DCF_PYPL'!$B$8)-'DCF_PYPL'!$B$3*(1+D81)^2*D81*'DCF_PYPL'!$B$9)/(1+'DCF_PYPL'!$B$10)^3+('DCF_PYPL'!$B$3*(1+D81)^4*('DCF_PYPL'!$B$5*(1-'DCF_PYPL'!$B$6)+'DCF_PYPL'!$B$7-'DCF_PYPL'!$B$8)-'DCF_PYPL'!$B$3*(1+D81)^3*D81*'DCF_PYPL'!$B$9)/(1+'DCF_PYPL'!$B$10)^4+('DCF_PYPL'!$B$3*(1+D81)^5*('DCF_PYPL'!$B$5*(1-'DCF_PYPL'!$B$6)+'DCF_PYPL'!$B$7-'DCF_PYPL'!$B$8)-'DCF_PYPL'!$B$3*(1+D81)^4*D81*'DCF_PYPL'!$B$9)/(1+'DCF_PYPL'!$B$10)^5+('DCF_PYPL'!$B$3*(1+D81)^5*(1+'DCF_PYPL'!$B$11)*('DCF_PYPL'!$B$5*(1-'DCF_PYPL'!$B$6)+'DCF_PYPL'!$B$7-'DCF_PYPL'!$B$8)-'DCF_PYPL'!$B$3*(1+D81)^5*'DCF_PYPL'!$B$11*'DCF_PYPL'!$B$9)/('DCF_PYPL'!$B$10-'DCF_PYPL'!$B$11)/(1+'DCF_PYPL'!$B$10)^5-'DCF_PYPL'!$B$13)/'DCF_PYPL'!$B$12))
A82: 10 | B82: =IF($B$4="","",IF(E81<$B$4,D81,B81)) | C82: =IF($B$4="","",IF(E81<$B$4,C81,D81)) | D82: =IF($B$4="","",(B82+C82)/2) | E82: =IF($B$4="","",((('DCF_PYPL'!$B$3*(1+D82)^1*('DCF_PYPL'!$B$5*(1-'DCF_PYPL'!$B$6)+'DCF_PYPL'!$B$7-'DCF_PYPL'!$B$8)-'DCF_PYPL'!$B$3*(1+D82)^0*D82*'DCF_PYPL'!$B$9)/(1+'DCF_PYPL'!$B$10)^1+('DCF_PYPL'!$B$3*(1+D82)^2*('DCF_PYPL'!$B$5*(1-'DCF_PYPL'!$B$6)+'DCF_PYPL'!$B$7-'DCF_PYPL'!$B$8)-'DCF_PYPL'!$B$3*(1+D82)^1*D82*'DCF_PYPL'!$B$9)/(1+'DCF_PYPL'!$B$10)^2+('DCF_PYPL'!$B$3*(1+D82)^3*('DCF_PYPL'!$B$5*(1-'DCF_PYPL'!$B$6)+'DCF_PYPL'!$B$7-'DCF_PYPL'!$B$8)-'DCF_PYPL'!$B$3*(1+D82)^2*D82*'DCF_PYPL'!$B$9)/(1+'DCF_PYPL'!$B$10)^3+('DCF_PYPL'!$B$3*(1+D82)^4*('DCF_PYPL'!$B$5*(1-'DCF_PYPL'!$B$6)+'DCF_PYPL'!$B$7-'DCF_PYPL'!$B$8)-'DCF_PYPL'!$B$3*(1+D82)^3*D82*'DCF_PYPL'!$B$9)/(1+'DCF_PYPL'!$B$10)^4+('DCF_PYPL'!$B$3*(1+D82)^5*('DCF_PYPL'!$B$5*(1-'DCF_PYPL'!$B$6)+'DCF_PYPL'!$B$7-'DCF_PYPL'!$B$8)-'DCF_PYPL'!$B$3*(1+D82)^4*D82*'DCF_PYPL'!$B$9)/(1+'DCF_PYPL'!$B$10)^5+('DCF_PYPL'!$B$3*(1+D82)^5*(1+'DCF_PYPL'!$B$11)*('DCF_PYPL'!$B$5*(1-'DCF_PYPL'!$B$6)+'DCF_PYPL'!$B$7-'DCF_PYPL'!$B$8)-'DCF_PYPL'!$B$3*(1+D82)^5*'DCF_PYPL'!$B$11*'DCF_PYPL'!$B$9)/('DCF_PYPL'!$B$10-'DCF_PYPL'!$B$11)/(1+'DCF_PYPL'!$B$10)^5-'DCF_PYPL'!$B$13)/'DCF_PYPL'!$B$12))
A83: 11 | B83: =IF($B$4="","",IF(E82<$B$4,D82,B82)) | C83: =IF($B$4="","",IF(E82<$B$4,C82,D82)) | D83: =IF($B$4="","",(B83+C83)/2) | E83: =IF($B$4="","",((('DCF_PYPL'!$B$3*(1+D83)^1*('DCF_PYPL'!$B$5*(1-'DCF_PYPL'!$B$6)+'DCF_PYPL'!$B$7-'DCF_PYPL'!$B$8)-'DCF_PYPL'!$B$3*(1+D83)^0*D83*'DCF_PYPL'!$B$9)/(1+'DCF_PYPL'!$B$10)^1+('DCF_PYPL'!$B$3*(1+D83)^2*('DCF_PYPL'!$B$5*(1-'DCF_PYPL'!$B$6)+'DCF_PYPL'!$B$7-'DCF_PYPL'!$B$8)-'DCF_PYPL'!$B$3*(1+D83)^1*D83*'DCF_PYPL'!$B$9)/(1+'DCF_PYPL'!$B$10)^2+('DCF_PYPL'!$B$3*(1+D83)^3*('DCF_PYPL'!$B$5*(1-'DCF_PYPL'!$B$6)+'DCF_PYPL'!$B$7-'DCF_PYPL'!$B$8)-'DCF_PYPL'!$B$3*(1+D83)^2*D83*'DCF_PYPL'!$B$9)/(1+'DCF_PYPL'!$B$10)^3+('DCF_PYPL'!$B$3*(1+D83)^4*('DCF_PYPL'!$B$5*(1-'DCF_PYPL'!$B$6)+'DCF_PYPL'!$B$7-'DCF_PYPL'!$B$8)-'DCF_PYPL'!$B$3*(1+D83)^3*D83*'DCF_PYPL'!$B$9)/(1+'DCF_PYPL'!$B$10)^4+('DCF_PYPL'!$B$3*(1+D83)^5*('DCF_PYPL'!$B$5*(1-'DCF_PYPL'!$B$6)+'DCF_PYPL'!$B$7-'DCF_PYPL'!$B$8)-'DCF_PYPL'!$B$3*(1+D83)^4*D83*'DCF_PYPL'!$B$9)/(1+'DCF_PYPL'!$B$10)^5+('DCF_PYPL'!$B$3*(1+D83)^5*(1+'DCF_PYPL'!$B$11)*('DCF_PYPL'!$B$5*(1-'DCF_PYPL'!$B$6)+'DCF_PYPL'!$B$7-'DCF_PYPL'!$B$8)-'DCF_PYPL'!$B$3*(1+D83)^5*'DCF_PYPL'!$B$11*'DCF_PYPL'!$B$9)/('DCF_PYPL'!$B$10-'DCF_PYPL'!$B$11)/(1+'DCF_PYPL'!$B$10)^5-'DCF_PYPL'!$B$13)/'DCF_PYPL'!$B$12))
A84: 12 | B84: =IF($B$4="","",IF(E83<$B$4,D83,B83)) | C84: =IF($B$4="","",IF(E83<$B$4,C83,D83)) | D84: =IF($B$4="","",(B84+C84)/2) | E84: =IF($B$4="","",((('DCF_PYPL'!$B$3*(1+D84)^1*('DCF_PYPL'!$B$5*(1-'DCF_PYPL'!$B$6)+'DCF_PYPL'!$B$7-'DCF_PYPL'!$B$8)-'DCF_PYPL'!$B$3*(1+D84)^0*D84*'DCF_PYPL'!$B$9)/(1+'DCF_PYPL'!$B$10)^1+('DCF_PYPL'!$B$3*(1+D84)^2*('DCF_PYPL'!$B$5*(1-'DCF_PYPL'!$B$6)+'DCF_PYPL'!$B$7-'DCF_PYPL'!$B$8)-'DCF_PYPL'!$B$3*(1+D84)^1*D84*'DCF_PYPL'!$B$9)/(1+'DCF_PYPL'!$B$10)^2+('DCF_PYPL'!$B$3*(1+D84)^3*('DCF_PYPL'!$B$5*(1-'DCF_PYPL'!$B$6)+'DCF_PYPL'!$B$7-'DCF_PYPL'!$B$8)-'DCF_PYPL'!$B$3*(1+D84)^2*D84*'DCF_PYPL'!$B$9)/(1+'DCF_PYPL'!$B$10)^3+('DCF_PYPL'!$B$3*(1+D84)^4*('DCF_PYPL'!$B$5*(1-'DCF_PYPL'!$B$6)+'DCF_PYPL'!$B$7-'DCF_PYPL'!$B$8)-'DCF_PYPL'!$B$3*(1+D84)^3*D84*'DCF_PYPL'!$B$9)/(1+'DCF_PYPL'!$B$10)^4+('DCF_PYPL'!$B$3*(1+D84)^5*('DCF_PYPL'!$B$5*(1-'DCF_PYPL'!$B$6)+'DCF_PYPL'!$B$7-'DCF_PYPL'!$B$8)-'DCF_PYPL'!$B$3*(1+D84)^4*D84*'DCF_PYPL'!$B$9)/(1+'DCF_PYPL'!$B$10)^5+('DCF_PYPL'!$B$3*(1+D84)^5*(1+'DCF_PYPL'!$B$11)*('DCF_PYPL'!$B$5*(1-'DCF_PYPL'!$B$6)+'DCF_PYPL'!$B$7-'DCF_PYPL'!$B$8)-'DCF_PYPL'!$B$3*(1+D84)^5*'DCF_PYPL'!$B$11*'DCF_PYPL'!$B$9)/('DCF_PYPL'!$B$10-'DCF_PYPL'!$B$11)/(1+'DCF_PYPL'!$B$10)^5-'DCF_PYPL'!$B$13)/'DCF_PYPL'!$B$12))
A85: 13 | B85: =IF($B$4="","",IF(E84<$B$4,D84,B84)) | C85: =IF($B$4="","",IF(E84<$B$4,C84,D84)) | D85: =IF($B$4="","",(B85+C85)/2) | E85: =IF($B$4="","",((('DCF_PYPL'!$B$3*(1+D85)^1*('DCF_PYPL'!$B$5*(1-'DCF_PYPL'!$B$6)+'DCF_PYPL'!$B$7-'DCF_PYPL'!$B$8)-'DCF_PYPL'!$B$3*(1+D85)^0*D85*'DCF_PYPL'!$B$9)/(1+'DCF_PYPL'!$B$10)^1+('DCF_PYPL'!$B$3*(1+D85)^2*('DCF_PYPL'!$B$5*(1-'DCF_PYPL'!$B$6)+'DCF_PYPL'!$B$7-'DCF_PYPL'!$B$8)-'DCF_PYPL'!$B$3*(1+D85)^1*D85*'DCF_PYPL'!$B$9)/(1+'DCF_PYPL'!$B$10)^2+('DCF_PYPL'!$B$3*(1+D85)^3*('DCF_PYPL'!$B$5*(1-'DCF_PYPL'!$B$6)+'DCF_PYPL'!$B$7-'DCF_PYPL'!$B$8)-'DCF_PYPL'!$B$3*(1+D85)^2*D85*'DCF_PYPL'!$B$9)/(1+'DCF_PYPL'!$B$10)^3+('DCF_PYPL'!$B$3*(1+D85)^4*('DCF_PYPL'!$B$5*(1-'DCF_PYPL'!$B$6)+'DCF_PYPL'!$B$7-'DCF_PYPL'!$B$8)-'DCF_PYPL'!$B$3*(1+D85)^3*D85*'DCF_PYPL'!$B$9)/(1+'DCF_PYPL'!$B$10)^4+('DCF_PYPL'!$B$3*(1+D85)^5*('DCF_PYPL'!$B$5*(1-'DCF_PYPL'!$B$6)+'DCF_PYPL'!$B$7-'DCF_PYPL'!$B$8)-'DCF_PYPL'!$B$3*(1+D85)^4*D85*'DCF_PYPL'!$B$9)/(1+'DCF_PYPL'!$B$10)^5+('DCF_PYPL'!$B$3*(1+D85)^5*(1+'DCF_PYPL'!$B$11)*('DCF_PYPL'!$B$5*(1-'DCF_PYPL'!$B$6)+'DCF_PYPL'!$B$7-'DCF_PYPL'!$B$8)-'DCF_PYPL'!$B$3*(1+D85)^5*'DCF_PYPL'!$B$11*'DCF_PYPL'!$B$9)/('DCF_PYPL'!$B$10-'DCF_PYPL'!$B$11)/(1+'DCF_PYPL'!$B$10)^5-'DCF_PYPL'!$B$13)/'DCF_PYPL'!$B$12))
... A132: 60 | B132: =IF($B$4="","",IF(E131<$B$4,D131,B131)) | C132: =IF($B$4="","",IF(E131<$B$4,C131,D131)) | D132: =IF($B$4="","",(B132+C132)/2) | E132: =IF($B$4="","",((('DCF_PYPL'!$B$3*(1+D132)^1*('DCF_PYPL'!$B$5*(1-'DCF_PYPL'!$B$6)+'DCF_PYPL'!$B$7-'DCF_PYPL'!$B$8)-'DCF_PYPL'!$B$3*(1+D132)^0*D132*'DCF_PYPL'!$B$9)/(1+'DCF_PYPL'!$B$10)^1+('DCF_PYPL'!$B$3*(1+D132)^2*('DCF_PYPL'!$B$5*(1-'DCF_PYPL'!$B$6)+'DCF_PYPL'!$B$7-'DCF_PYPL'!$B$8)-'DCF_PYPL'!$B$3*(1+D132)^1*D132*'DCF_PYPL'!$B$9)/(1+'DCF_PYPL'!$B$10)^2+('DCF_PYPL'!$B$3*(1+D132)^3*('DCF_PYPL'!$B$5*(1-'DCF_PYPL'!$B$6)+'DCF_PYPL'!$B$7-'DCF_PYPL'!$B$8)-'DCF_PYPL'!$B$3*(1+D132)^2*D132*'DCF_PYPL'!$B$9)/(1+'DCF_PYPL'!$B$10)^3+('DCF_PYPL'!$B$3*(1+D132)^4*('DCF_PYPL'!$B$5*(1-'DCF_PYPL'!$B$6)+'DCF_PYPL'!$B$7-'DCF_PYPL'!$B$8)-'DCF_PYPL'!$B$3*(1+D132)^3*D132*'DCF_PYPL'!$B$9)/(1+'DCF_PYPL'!$B$10)^4+('DCF_PYPL'!$B$3*(1+D132)^5*('DCF_PYPL'!$B$5*(1-'DCF_PYPL'!$B$6)+'DCF_PYPL'!$B$7-'DCF_PYPL'!$B$8)-'DCF_PYPL'!$B$3*(1+D132)^4*D132*'DCF_PYPL'!$B$9)/(1+'DCF_PYPL'!$B$10)^5+('DCF_PYPL'!$B$3*(1+D132)^5*(1+'DCF_PYPL'!$B$11)*('DCF_PYPL'!$B$5*(1-'DCF_PYPL'!$B$6)+'DCF_PYPL'!$B$7-'DCF_PYPL'!$B$8)-'DCF_PYPL'!$B$3*(1+D132)^5*'DCF_PYPL'!$B$11*'DCF_PYPL'!$B$9)/('DCF_PYPL'!$B$10-'DCF_PYPL'!$B$11)/(1+'DCF_PYPL'!$B$10)^5-'DCF_PYPL'!$B$13)/'DCF_PYPL'!$B$12))
A136: NKE | B136: Lower growth | C136: Upper growth | D136: Mid growth | E136: Model price
A137: 1 | B137: -0.45 | C137: 0.5 | D137: =IF($B$5="","",(B137+C137)/2) | E137: =IF($B$5="","",((('DCF_NKE'!$B$3*(1+D137)^1*('DCF_NKE'!$B$5*(1-'DCF_NKE'!$B$6)+'DCF_NKE'!$B$7-'DCF_NKE'!$B$8)-'DCF_NKE'!$B$3*(1+D137)^0*D137*'DCF_NKE'!$B$9)/(1+'DCF_NKE'!$B$10)^1+('DCF_NKE'!$B$3*(1+D137)^2*('DCF_NKE'!$B$5*(1-'DCF_NKE'!$B$6)+'DCF_NKE'!$B$7-'DCF_NKE'!$B$8)-'DCF_NKE'!$B$3*(1+D137)^1*D137*'DCF_NKE'!$B$9)/(1+'DCF_NKE'!$B$10)^2+('DCF_NKE'!$B$3*(1+D137)^3*('DCF_NKE'!$B$5*(1-'DCF_NKE'!$B$6)+'DCF_NKE'!$B$7-'DCF_NKE'!$B$8)-'DCF_NKE'!$B$3*(1+D137)^2*D137*'DCF_NKE'!$B$9)/(1+'DCF_NKE'!$B$10)^3+('DCF_NKE'!$B$3*(1+D137)^4*('DCF_NKE'!$B$5*(1-'DCF_NKE'!$B$6)+'DCF_NKE'!$B$7-'DCF_NKE'!$B$8)-'DCF_NKE'!$B$3*(1+D137)^3*D137*'DCF_NKE'!$B$9)/(1+'DCF_NKE'!$B$10)^4+('DCF_NKE'!$B$3*(1+D137)^5*('DCF_NKE'!$B$5*(1-'DCF_NKE'!$B$6)+'DCF_NKE'!$B$7-'DCF_NKE'!$B$8)-'DCF_NKE'!$B$3*(1+D137)^4*D137*'DCF_NKE'!$B$9)/(1+'DCF_NKE'!$B$10)^5+('DCF_NKE'!$B$3*(1+D137)^5*(1+'DCF_NKE'!$B$11)*('DCF_NKE'!$B$5*(1-'DCF_NKE'!$B$6)+'DCF_NKE'!$B$7-'DCF_NKE'!$B$8)-'DCF_NKE'!$B$3*(1+D137)^5*'DCF_NKE'!$B$11*'DCF_NKE'!$B$9)/('DCF_NKE'!$B$10-'DCF_NKE'!$B$11)/(1+'DCF_NKE'!$B$10)^5-'DCF_NKE'!$B$13)/'DCF_NKE'!$B$12))
A138: 2 | B138: =IF($B$5="","",IF(E137<$B$5,D137,B137)) | C138: =IF($B$5="","",IF(E137<$B$5,C137,D137)) | D138: =IF($B$5="","",(B138+C138)/2) | E138: =IF($B$5="","",((('DCF_NKE'!$B$3*(1+D138)^1*('DCF_NKE'!$B$5*(1-'DCF_NKE'!$B$6)+'DCF_NKE'!$B$7-'DCF_NKE'!$B$8)-'DCF_NKE'!$B$3*(1+D138)^0*D138*'DCF_NKE'!$B$9)/(1+'DCF_NKE'!$B$10)^1+('DCF_NKE'!$B$3*(1+D138)^2*('DCF_NKE'!$B$5*(1-'DCF_NKE'!$B$6)+'DCF_NKE'!$B$7-'DCF_NKE'!$B$8)-'DCF_NKE'!$B$3*(1+D138)^1*D138*'DCF_NKE'!$B$9)/(1+'DCF_NKE'!$B$10)^2+('DCF_NKE'!$B$3*(1+D138)^3*('DCF_NKE'!$B$5*(1-'DCF_NKE'!$B$6)+'DCF_NKE'!$B$7-'DCF_NKE'!$B$8)-'DCF_NKE'!$B$3*(1+D138)^2*D138*'DCF_NKE'!$B$9)/(1+'DCF_NKE'!$B$10)^3+('DCF_NKE'!$B$3*(1+D138)^4*('DCF_NKE'!$B$5*(1-'DCF_NKE'!$B$6)+'DCF_NKE'!$B$7-'DCF_NKE'!$B$8)-'DCF_NKE'!$B$3*(1+D138)^3*D138*'DCF_NKE'!$B$9)/(1+'DCF_NKE'!$B$10)^4+('DCF_NKE'!$B$3*(1+D138)^5*('DCF_NKE'!$B$5*(1-'DCF_NKE'!$B$6)+'DCF_NKE'!$B$7-'DCF_NKE'!$B$8)-'DCF_NKE'!$B$3*(1+D138)^4*D138*'DCF_NKE'!$B$9)/(1+'DCF_NKE'!$B$10)^5+('DCF_NKE'!$B$3*(1+D138)^5*(1+'DCF_NKE'!$B$11)*('DCF_NKE'!$B$5*(1-'DCF_NKE'!$B$6)+'DCF_NKE'!$B$7-'DCF_NKE'!$B$8)-'DCF_NKE'!$B$3*(1+D138)^5*'DCF_NKE'!$B$11*'DCF_NKE'!$B$9)/('DCF_NKE'!$B$10-'DCF_NKE'!$B$11)/(1+'DCF_NKE'!$B$10)^5-'DCF_NKE'!$B$13)/'DCF_NKE'!$B$12))
A139: 3 | B139: =IF($B$5="","",IF(E138<$B$5,D138,B138)) | C139: =IF($B$5="","",IF(E138<$B$5,C138,D138)) | D139: =IF($B$5="","",(B139+C139)/2) | E139: =IF($B$5="","",((('DCF_NKE'!$B$3*(1+D139)^1*('DCF_NKE'!$B$5*(1-'DCF_NKE'!$B$6)+'DCF_NKE'!$B$7-'DCF_NKE'!$B$8)-'DCF_NKE'!$B$3*(1+D139)^0*D139*'DCF_NKE'!$B$9)/(1+'DCF_NKE'!$B$10)^1+('DCF_NKE'!$B$3*(1+D139)^2*('DCF_NKE'!$B$5*(1-'DCF_NKE'!$B$6)+'DCF_NKE'!$B$7-'DCF_NKE'!$B$8)-'DCF_NKE'!$B$3*(1+D139)^1*D139*'DCF_NKE'!$B$9)/(1+'DCF_NKE'!$B$10)^2+('DCF_NKE'!$B$3*(1+D139)^3*('DCF_NKE'!$B$5*(1-'DCF_NKE'!$B$6)+'DCF_NKE'!$B$7-'DCF_NKE'!$B$8)-'DCF_NKE'!$B$3*(1+D139)^2*D139*'DCF_NKE'!$B$9)/(1+'DCF_NKE'!$B$10)^3+('DCF_NKE'!$B$3*(1+D139)^4*('DCF_NKE'!$B$5*(1-'DCF_NKE'!$B$6)+'DCF_NKE'!$B$7-'DCF_NKE'!$B$8)-'DCF_NKE'!$B$3*(1+D139)^3*D139*'DCF_NKE'!$B$9)/(1+'DCF_NKE'!$B$10)^4+('DCF_NKE'!$B$3*(1+D139)^5*('DCF_NKE'!$B$5*(1-'DCF_NKE'!$B$6)+'DCF_NKE'!$B$7-'DCF_NKE'!$B$8)-'DCF_NKE'!$B$3*(1+D139)^4*D139*'DCF_NKE'!$B$9)/(1+'DCF_NKE'!$B$10)^5+('DCF_NKE'!$B$3*(1+D139)^5*(1+'DCF_NKE'!$B$11)*('DCF_NKE'!$B$5*(1-'DCF_NKE'!$B$6)+'DCF_NKE'!$B$7-'DCF_NKE'!$B$8)-'DCF_NKE'!$B$3*(1+D139)^5*'DCF_NKE'!$B$11*'DCF_NKE'!$B$9)/('DCF_NKE'!$B$10-'DCF_NKE'!$B$11)/(1+'DCF_NKE'!$B$10)^5-'DCF_NKE'!$B$13)/'DCF_NKE'!$B$12))
A140: 4 | B140: =IF($B$5="","",IF(E139<$B$5,D139,B139)) | C140: =IF($B$5="","",IF(E139<$B$5,C139,D139)) | D140: =IF($B$5="","",(B140+C140)/2) | E140: =IF($B$5="","",((('DCF_NKE'!$B$3*(1+D140)^1*('DCF_NKE'!$B$5*(1-'DCF_NKE'!$B$6)+'DCF_NKE'!$B$7-'DCF_NKE'!$B$8)-'DCF_NKE'!$B$3*(1+D140)^0*D140*'DCF_NKE'!$B$9)/(1+'DCF_NKE'!$B$10)^1+('DCF_NKE'!$B$3*(1+D140)^2*('DCF_NKE'!$B$5*(1-'DCF_NKE'!$B$6)+'DCF_NKE'!$B$7-'DCF_NKE'!$B$8)-'DCF_NKE'!$B$3*(1+D140)^1*D140*'DCF_NKE'!$B$9)/(1+'DCF_NKE'!$B$10)^2+('DCF_NKE'!$B$3*(1+D140)^3*('DCF_NKE'!$B$5*(1-'DCF_NKE'!$B$6)+'DCF_NKE'!$B$7-'DCF_NKE'!$B$8)-'DCF_NKE'!$B$3*(1+D140)^2*D140*'DCF_NKE'!$B$9)/(1+'DCF_NKE'!$B$10)^3+('DCF_NKE'!$B$3*(1+D140)^4*('DCF_NKE'!$B$5*(1-'DCF_NKE'!$B$6)+'DCF_NKE'!$B$7-'DCF_NKE'!$B$8)-'DCF_NKE'!$B$3*(1+D140)^3*D140*'DCF_NKE'!$B$9)/(1+'DCF_NKE'!$B$10)^4+('DCF_NKE'!$B$3*(1+D140)^5*('DCF_NKE'!$B$5*(1-'DCF_NKE'!$B$6)+'DCF_NKE'!$B$7-'DCF_NKE'!$B$8)-'DCF_NKE'!$B$3*(1+D140)^4*D140*'DCF_NKE'!$B$9)/(1+'DCF_NKE'!$B$10)^5+('DCF_NKE'!$B$3*(1+D140)^5*(1+'DCF_NKE'!$B$11)*('DCF_NKE'!$B$5*(1-'DCF_NKE'!$B$6)+'DCF_NKE'!$B$7-'DCF_NKE'!$B$8)-'DCF_NKE'!$B$3*(1+D140)^5*'DCF_NKE'!$B$11*'DCF_NKE'!$B$9)/('DCF_NKE'!$B$10-'DCF_NKE'!$B$11)/(1+'DCF_NKE'!$B$10)^5-'DCF_NKE'!$B$13)/'DCF_NKE'!$B$12))
A141: 5 | B141: =IF($B$5="","",IF(E140<$B$5,D140,B140)) | C141: =IF($B$5="","",IF(E140<$B$5,C140,D140)) | D141: =IF($B$5="","",(B141+C141)/2) | E141: =IF($B$5="","",((('DCF_NKE'!$B$3*(1+D141)^1*('DCF_NKE'!$B$5*(1-'DCF_NKE'!$B$6)+'DCF_NKE'!$B$7-'DCF_NKE'!$B$8)-'DCF_NKE'!$B$3*(1+D141)^0*D141*'DCF_NKE'!$B$9)/(1+'DCF_NKE'!$B$10)^1+('DCF_NKE'!$B$3*(1+D141)^2*('DCF_NKE'!$B$5*(1-'DCF_NKE'!$B$6)+'DCF_NKE'!$B$7-'DCF_NKE'!$B$8)-'DCF_NKE'!$B$3*(1+D141)^1*D141*'DCF_NKE'!$B$9)/(1+'DCF_NKE'!$B$10)^2+('DCF_NKE'!$B$3*(1+D141)^3*('DCF_NKE'!$B$5*(1-'DCF_NKE'!$B$6)+'DCF_NKE'!$B$7-'DCF_NKE'!$B$8)-'DCF_NKE'!$B$3*(1+D141)^2*D141*'DCF_NKE'!$B$9)/(1+'DCF_NKE'!$B$10)^3+('DCF_NKE'!$B$3*(1+D141)^4*('DCF_NKE'!$B$5*(1-'DCF_NKE'!$B$6)+'DCF_NKE'!$B$7-'DCF_NKE'!$B$8)-'DCF_NKE'!$B$3*(1+D141)^3*D141*'DCF_NKE'!$B$9)/(1+'DCF_NKE'!$B$10)^4+('DCF_NKE'!$B$3*(1+D141)^5*('DCF_NKE'!$B$5*(1-'DCF_NKE'!$B$6)+'DCF_NKE'!$B$7-'DCF_NKE'!$B$8)-'DCF_NKE'!$B$3*(1+D141)^4*D141*'DCF_NKE'!$B$9)/(1+'DCF_NKE'!$B$10)^5+('DCF_NKE'!$B$3*(1+D141)^5*(1+'DCF_NKE'!$B$11)*('DCF_NKE'!$B$5*(1-'DCF_NKE'!$B$6)+'DCF_NKE'!$B$7-'DCF_NKE'!$B$8)-'DCF_NKE'!$B$3*(1+D141)^5*'DCF_NKE'!$B$11*'DCF_NKE'!$B$9)/('DCF_NKE'!$B$10-'DCF_NKE'!$B$11)/(1+'DCF_NKE'!$B$10)^5-'DCF_NKE'!$B$13)/'DCF_NKE'!$B$12))
A142: 6 | B142: =IF($B$5="","",IF(E141<$B$5,D141,B141)) | C142: =IF($B$5="","",IF(E141<$B$5,C141,D141)) | D142: =IF($B$5="","",(B142+C142)/2) | E142: =IF($B$5="","",((('DCF_NKE'!$B$3*(1+D142)^1*('DCF_NKE'!$B$5*(1-'DCF_NKE'!$B$6)+'DCF_NKE'!$B$7-'DCF_NKE'!$B$8)-'DCF_NKE'!$B$3*(1+D142)^0*D142*'DCF_NKE'!$B$9)/(1+'DCF_NKE'!$B$10)^1+('DCF_NKE'!$B$3*(1+D142)^2*('DCF_NKE'!$B$5*(1-'DCF_NKE'!$B$6)+'DCF_NKE'!$B$7-'DCF_NKE'!$B$8)-'DCF_NKE'!$B$3*(1+D142)^1*D142*'DCF_NKE'!$B$9)/(1+'DCF_NKE'!$B$10)^2+('DCF_NKE'!$B$3*(1+D142)^3*('DCF_NKE'!$B$5*(1-'DCF_NKE'!$B$6)+'DCF_NKE'!$B$7-'DCF_NKE'!$B$8)-'DCF_NKE'!$B$3*(1+D142)^2*D142*'DCF_NKE'!$B$9)/(1+'DCF_NKE'!$B$10)^3+('DCF_NKE'!$B$3*(1+D142)^4*('DCF_NKE'!$B$5*(1-'DCF_NKE'!$B$6)+'DCF_NKE'!$B$7-'DCF_NKE'!$B$8)-'DCF_NKE'!$B$3*(1+D142)^3*D142*'DCF_NKE'!$B$9)/(1+'DCF_NKE'!$B$10)^4+('DCF_NKE'!$B$3*(1+D142)^5*('DCF_NKE'!$B$5*(1-'DCF_NKE'!$B$6)+'DCF_NKE'!$B$7-'DCF_NKE'!$B$8)-'DCF_NKE'!$B$3*(1+D142)^4*D142*'DCF_NKE'!$B$9)/(1+'DCF_NKE'!$B$10)^5+('DCF_NKE'!$B$3*(1+D142)^5*(1+'DCF_NKE'!$B$11)*('DCF_NKE'!$B$5*(1-'DCF_NKE'!$B$6)+'DCF_NKE'!$B$7-'DCF_NKE'!$B$8)-'DCF_NKE'!$B$3*(1+D142)^5*'DCF_NKE'!$B$11*'DCF_NKE'!$B$9)/('DCF_NKE'!$B$10-'DCF_NKE'!$B$11)/(1+'DCF_NKE'!$B$10)^5-'DCF_NKE'!$B$13)/'DCF_NKE'!$B$12))
A143: 7 | B143: =IF($B$5="","",IF(E142<$B$5,D142,B142)) | C143: =IF($B$5="","",IF(E142<$B$5,C142,D142)) | D143: =IF($B$5="","",(B143+C143)/2) | E143: =IF($B$5="","",((('DCF_NKE'!$B$3*(1+D143)^1*('DCF_NKE'!$B$5*(1-'DCF_NKE'!$B$6)+'DCF_NKE'!$B$7-'DCF_NKE'!$B$8)-'DCF_NKE'!$B$3*(1+D143)^0*D143*'DCF_NKE'!$B$9)/(1+'DCF_NKE'!$B$10)^1+('DCF_NKE'!$B$3*(1+D143)^2*('DCF_NKE'!$B$5*(1-'DCF_NKE'!$B$6)+'DCF_NKE'!$B$7-'DCF_NKE'!$B$8)-'DCF_NKE'!$B$3*(1+D143)^1*D143*'DCF_NKE'!$B$9)/(1+'DCF_NKE'!$B$10)^2+('DCF_NKE'!$B$3*(1+D143)^3*('DCF_NKE'!$B$5*(1-'DCF_NKE'!$B$6)+'DCF_NKE'!$B$7-'DCF_NKE'!$B$8)-'DCF_NKE'!$B$3*(1+D143)^2*D143*'DCF_NKE'!$B$9)/(1+'DCF_NKE'!$B$10)^3+('DCF_NKE'!$B$3*(1+D143)^4*('DCF_NKE'!$B$5*(1-'DCF_NKE'!$B$6)+'DCF_NKE'!$B$7-'DCF_NKE'!$B$8)-'DCF_NKE'!$B$3*(1+D143)^3*D143*'DCF_NKE'!$B$9)/(1+'DCF_NKE'!$B$10)^4+('DCF_NKE'!$B$3*(1+D143)^5*('DCF_NKE'!$B$5*(1-'DCF_NKE'!$B$6)+'DCF_NKE'!$B$7-'DCF_NKE'!$B$8)-'DCF_NKE'!$B$3*(1+D143)^4*D143*'DCF_NKE'!$B$9)/(1+'DCF_NKE'!$B$10)^5+('DCF_NKE'!$B$3*(1+D143)^5*(1+'DCF_NKE'!$B$11)*('DCF_NKE'!$B$5*(1-'DCF_NKE'!$B$6)+'DCF_NKE'!$B$7-'DCF_NKE'!$B$8)-'DCF_NKE'!$B$3*(1+D143)^5*'DCF_NKE'!$B$11*'DCF_NKE'!$B$9)/('DCF_NKE'!$B$10-'DCF_NKE'!$B$11)/(1+'DCF_NKE'!$B$10)^5-'DCF_NKE'!$B$13)/'DCF_NKE'!$B$12))
A144: 8 | B144: =IF($B$5="","",IF(E143<$B$5,D143,B143)) | C144: =IF($B$5="","",IF(E143<$B$5,C143,D143)) | D144: =IF($B$5="","",(B144+C144)/2) | E144: =IF($B$5="","",((('DCF_NKE'!$B$3*(1+D144)^1*('DCF_NKE'!$B$5*(1-'DCF_NKE'!$B$6)+'DCF_NKE'!$B$7-'DCF_NKE'!$B$8)-'DCF_NKE'!$B$3*(1+D144)^0*D144*'DCF_NKE'!$B$9)/(1+'DCF_NKE'!$B$10)^1+('DCF_NKE'!$B$3*(1+D144)^2*('DCF_NKE'!$B$5*(1-'DCF_NKE'!$B$6)+'DCF_NKE'!$B$7-'DCF_NKE'!$B$8)-'DCF_NKE'!$B$3*(1+D144)^1*D144*'DCF_NKE'!$B$9)/(1+'DCF_NKE'!$B$10)^2+('DCF_NKE'!$B$3*(1+D144)^3*('DCF_NKE'!$B$5*(1-'DCF_NKE'!$B$6)+'DCF_NKE'!$B$7-'DCF_NKE'!$B$8)-'DCF_NKE'!$B$3*(1+D144)^2*D144*'DCF_NKE'!$B$9)/(1+'DCF_NKE'!$B$10)^3+('DCF_NKE'!$B$3*(1+D144)^4*('DCF_NKE'!$B$5*(1-'DCF_NKE'!$B$6)+'DCF_NKE'!$B$7-'DCF_NKE'!$B$8)-'DCF_NKE'!$B$3*(1+D144)^3*D144*'DCF_NKE'!$B$9)/(1+'DCF_NKE'!$B$10)^4+('DCF_NKE'!$B$3*(1+D144)^5*('DCF_NKE'!$B$5*(1-'DCF_NKE'!$B$6)+'DCF_NKE'!$B$7-'DCF_NKE'!$B$8)-'DCF_NKE'!$B$3*(1+D144)^4*D144*'DCF_NKE'!$B$9)/(1+'DCF_NKE'!$B$10)^5+('DCF_NKE'!$B$3*(1+D144)^5*(1+'DCF_NKE'!$B$11)*('DCF_NKE'!$B$5*(1-'DCF_NKE'!$B$6)+'DCF_NKE'!$B$7-'DCF_NKE'!$B$8)-'DCF_NKE'!$B$3*(1+D144)^5*'DCF_NKE'!$B$11*'DCF_NKE'!$B$9)/('DCF_NKE'!$B$10-'DCF_NKE'!$B$11)/(1+'DCF_NKE'!$B$10)^5-'DCF_NKE'!$B$13)/'DCF_NKE'!$B$12))
A145: 9 | B145: =IF($B$5="","",IF(E144<$B$5,D144,B144)) | C145: =IF($B$5="","",IF(E144<$B$5,C144,D144)) | D145: =IF($B$5="","",(B145+C145)/2) | E145: =IF($B$5="","",((('DCF_NKE'!$B$3*(1+D145)^1*('DCF_NKE'!$B$5*(1-'DCF_NKE'!$B$6)+'DCF_NKE'!$B$7-'DCF_NKE'!$B$8)-'DCF_NKE'!$B$3*(1+D145)^0*D145*'DCF_NKE'!$B$9)/(1+'DCF_NKE'!$B$10)^1+('DCF_NKE'!$B$3*(1+D145)^2*('DCF_NKE'!$B$5*(1-'DCF_NKE'!$B$6)+'DCF_NKE'!$B$7-'DCF_NKE'!$B$8)-'DCF_NKE'!$B$3*(1+D145)^1*D145*'DCF_NKE'!$B$9)/(1+'DCF_NKE'!$B$10)^2+('DCF_NKE'!$B$3*(1+D145)^3*('DCF_NKE'!$B$5*(1-'DCF_NKE'!$B$6)+'DCF_NKE'!$B$7-'DCF_NKE'!$B$8)-'DCF_NKE'!$B$3*(1+D145)^2*D145*'DCF_NKE'!$B$9)/(1+'DCF_NKE'!$B$10)^3+('DCF_NKE'!$B$3*(1+D145)^4*('DCF_NKE'!$B$5*(1-'DCF_NKE'!$B$6)+'DCF_NKE'!$B$7-'DCF_NKE'!$B$8)-'DCF_NKE'!$B$3*(1+D145)^3*D145*'DCF_NKE'!$B$9)/(1+'DCF_NKE'!$B$10)^4+('DCF_NKE'!$B$3*(1+D145)^5*('DCF_NKE'!$B$5*(1-'DCF_NKE'!$B$6)+'DCF_NKE'!$B$7-'DCF_NKE'!$B$8)-'DCF_NKE'!$B$3*(1+D145)^4*D145*'DCF_NKE'!$B$9)/(1+'DCF_NKE'!$B$10)^5+('DCF_NKE'!$B$3*(1+D145)^5*(1+'DCF_NKE'!$B$11)*('DCF_NKE'!$B$5*(1-'DCF_NKE'!$B$6)+'DCF_NKE'!$B$7-'DCF_NKE'!$B$8)-'DCF_NKE'!$B$3*(1+D145)^5*'DCF_NKE'!$B$11*'DCF_NKE'!$B$9)/('DCF_NKE'!$B$10-'DCF_NKE'!$B$11)/(1+'DCF_NKE'!$B$10)^5-'DCF_NKE'!$B$13)/'DCF_NKE'!$B$12))
A146: 10 | B146: =IF($B$5="","",IF(E145<$B$5,D145,B145)) | C146: =IF($B$5="","",IF(E145<$B$5,C145,D145)) | D146: =IF($B$5="","",(B146+C146)/2) | E146: =IF($B$5="","",((('DCF_NKE'!$B$3*(1+D146)^1*('DCF_NKE'!$B$5*(1-'DCF_NKE'!$B$6)+'DCF_NKE'!$B$7-'DCF_NKE'!$B$8)-'DCF_NKE'!$B$3*(1+D146)^0*D146*'DCF_NKE'!$B$9)/(1+'DCF_NKE'!$B$10)^1+('DCF_NKE'!$B$3*(1+D146)^2*('DCF_NKE'!$B$5*(1-'DCF_NKE'!$B$6)+'DCF_NKE'!$B$7-'DCF_NKE'!$B$8)-'DCF_NKE'!$B$3*(1+D146)^1*D146*'DCF_NKE'!$B$9)/(1+'DCF_NKE'!$B$10)^2+('DCF_NKE'!$B$3*(1+D146)^3*('DCF_NKE'!$B$5*(1-'DCF_NKE'!$B$6)+'DCF_NKE'!$B$7-'DCF_NKE'!$B$8)-'DCF_NKE'!$B$3*(1+D146)^2*D146*'DCF_NKE'!$B$9)/(1+'DCF_NKE'!$B$10)^3+('DCF_NKE'!$B$3*(1+D146)^4*('DCF_NKE'!$B$5*(1-'DCF_NKE'!$B$6)+'DCF_NKE'!$B$7-'DCF_NKE'!$B$8)-'DCF_NKE'!$B$3*(1+D146)^3*D146*'DCF_NKE'!$B$9)/(1+'DCF_NKE'!$B$10)^4+('DCF_NKE'!$B$3*(1+D146)^5*('DCF_NKE'!$B$5*(1-'DCF_NKE'!$B$6)+'DCF_NKE'!$B$7-'DCF_NKE'!$B$8)-'DCF_NKE'!$B$3*(1+D146)^4*D146*'DCF_NKE'!$B$9)/(1+'DCF_NKE'!$B$10)^5+('DCF_NKE'!$B$3*(1+D146)^5*(1+'DCF_NKE'!$B$11)*('DCF_NKE'!$B$5*(1-'DCF_NKE'!$B$6)+'DCF_NKE'!$B$7-'DCF_NKE'!$B$8)-'DCF_NKE'!$B$3*(1+D146)^5*'DCF_NKE'!$B$11*'DCF_NKE'!$B$9)/('DCF_NKE'!$B$10-'DCF_NKE'!$B$11)/(1+'DCF_NKE'!$B$10)^5-'DCF_NKE'!$B$13)/'DCF_NKE'!$B$12))
A147: 11 | B147: =IF($B$5="","",IF(E146<$B$5,D146,B146)) | C147: =IF($B$5="","",IF(E146<$B$5,C146,D146)) | D147: =IF($B$5="","",(B147+C147)/2) | E147: =IF($B$5="","",((('DCF_NKE'!$B$3*(1+D147)^1*('DCF_NKE'!$B$5*(1-'DCF_NKE'!$B$6)+'DCF_NKE'!$B$7-'DCF_NKE'!$B$8)-'DCF_NKE'!$B$3*(1+D147)^0*D147*'DCF_NKE'!$B$9)/(1+'DCF_NKE'!$B$10)^1+('DCF_NKE'!$B$3*(1+D147)^2*('DCF_NKE'!$B$5*(1-'DCF_NKE'!$B$6)+'DCF_NKE'!$B$7-'DCF_NKE'!$B$8)-'DCF_NKE'!$B$3*(1+D147)^1*D147*'DCF_NKE'!$B$9)/(1+'DCF_NKE'!$B$10)^2+('DCF_NKE'!$B$3*(1+D147)^3*('DCF_NKE'!$B$5*(1-'DCF_NKE'!$B$6)+'DCF_NKE'!$B$7-'DCF_NKE'!$B$8)-'DCF_NKE'!$B$3*(1+D147)^2*D147*'DCF_NKE'!$B$9)/(1+'DCF_NKE'!$B$10)^3+('DCF_NKE'!$B$3*(1+D147)^4*('DCF_NKE'!$B$5*(1-'DCF_NKE'!$B$6)+'DCF_NKE'!$B$7-'DCF_NKE'!$B$8)-'DCF_NKE'!$B$3*(1+D147)^3*D147*'DCF_NKE'!$B$9)/(1+'DCF_NKE'!$B$10)^4+('DCF_NKE'!$B$3*(1+D147)^5*('DCF_NKE'!$B$5*(1-'DCF_NKE'!$B$6)+'DCF_NKE'!$B$7-'DCF_NKE'!$B$8)-'DCF_NKE'!$B$3*(1+D147)^4*D147*'DCF_NKE'!$B$9)/(1+'DCF_NKE'!$B$10)^5+('DCF_NKE'!$B$3*(1+D147)^5*(1+'DCF_NKE'!$B$11)*('DCF_NKE'!$B$5*(1-'DCF_NKE'!$B$6)+'DCF_NKE'!$B$7-'DCF_NKE'!$B$8)-'DCF_NKE'!$B$3*(1+D147)^5*'DCF_NKE'!$B$11*'DCF_NKE'!$B$9)/('DCF_NKE'!$B$10-'DCF_NKE'!$B$11)/(1+'DCF_NKE'!$B$10)^5-'DCF_NKE'!$B$13)/'DCF_NKE'!$B$12))
A148: 12 | B148: =IF($B$5="","",IF(E147<$B$5,D147,B147)) | C148: =IF($B$5="","",IF(E147<$B$5,C147,D147)) | D148: =IF($B$5="","",(B148+C148)/2) | E148: =IF($B$5="","",((('DCF_NKE'!$B$3*(1+D148)^1*('DCF_NKE'!$B$5*(1-'DCF_NKE'!$B$6)+'DCF_NKE'!$B$7-'DCF_NKE'!$B$8)-'DCF_NKE'!$B$3*(1+D148)^0*D148*'DCF_NKE'!$B$9)/(1+'DCF_NKE'!$B$10)^1+('DCF_NKE'!$B$3*(1+D148)^2*('DCF_NKE'!$B$5*(1-'DCF_NKE'!$B$6)+'DCF_NKE'!$B$7-'DCF_NKE'!$B$8)-'DCF_NKE'!$B$3*(1+D148)^1*D148*'DCF_NKE'!$B$9)/(1+'DCF_NKE'!$B$10)^2+('DCF_NKE'!$B$3*(1+D148)^3*('DCF_NKE'!$B$5*(1-'DCF_NKE'!$B$6)+'DCF_NKE'!$B$7-'DCF_NKE'!$B$8)-'DCF_NKE'!$B$3*(1+D148)^2*D148*'DCF_NKE'!$B$9)/(1+'DCF_NKE'!$B$10)^3+('DCF_NKE'!$B$3*(1+D148)^4*('DCF_NKE'!$B$5*(1-'DCF_NKE'!$B$6)+'DCF_NKE'!$B$7-'DCF_NKE'!$B$8)-'DCF_NKE'!$B$3*(1+D148)^3*D148*'DCF_NKE'!$B$9)/(1+'DCF_NKE'!$B$10)^4+('DCF_NKE'!$B$3*(1+D148)^5*('DCF_NKE'!$B$5*(1-'DCF_NKE'!$B$6)+'DCF_NKE'!$B$7-'DCF_NKE'!$B$8)-'DCF_NKE'!$B$3*(1+D148)^4*D148*'DCF_NKE'!$B$9)/(1+'DCF_NKE'!$B$10)^5+('DCF_NKE'!$B$3*(1+D148)^5*(1+'DCF_NKE'!$B$11)*('DCF_NKE'!$B$5*(1-'DCF_NKE'!$B$6)+'DCF_NKE'!$B$7-'DCF_NKE'!$B$8)-'DCF_NKE'!$B$3*(1+D148)^5*'DCF_NKE'!$B$11*'DCF_NKE'!$B$9)/('DCF_NKE'!$B$10-'DCF_NKE'!$B$11)/(1+'DCF_NKE'!$B$10)^5-'DCF_NKE'!$B$13)/'DCF_NKE'!$B$12))
A149: 13 | B149: =IF($B$5="","",IF(E148<$B$5,D148,B148)) | C149: =IF($B$5="","",IF(E148<$B$5,C148,D148)) | D149: =IF($B$5="","",(B149+C149)/2) | E149: =IF($B$5="","",((('DCF_NKE'!$B$3*(1+D149)^1*('DCF_NKE'!$B$5*(1-'DCF_NKE'!$B$6)+'DCF_NKE'!$B$7-'DCF_NKE'!$B$8)-'DCF_NKE'!$B$3*(1+D149)^0*D149*'DCF_NKE'!$B$9)/(1+'DCF_NKE'!$B$10)^1+('DCF_NKE'!$B$3*(1+D149)^2*('DCF_NKE'!$B$5*(1-'DCF_NKE'!$B$6)+'DCF_NKE'!$B$7-'DCF_NKE'!$B$8)-'DCF_NKE'!$B$3*(1+D149)^1*D149*'DCF_NKE'!$B$9)/(1+'DCF_NKE'!$B$10)^2+('DCF_NKE'!$B$3*(1+D149)^3*('DCF_NKE'!$B$5*(1-'DCF_NKE'!$B$6)+'DCF_NKE'!$B$7-'DCF_NKE'!$B$8)-'DCF_NKE'!$B$3*(1+D149)^2*D149*'DCF_NKE'!$B$9)/(1+'DCF_NKE'!$B$10)^3+('DCF_NKE'!$B$3*(1+D149)^4*('DCF_NKE'!$B$5*(1-'DCF_NKE'!$B$6)+'DCF_NKE'!$B$7-'DCF_NKE'!$B$8)-'DCF_NKE'!$B$3*(1+D149)^3*D149*'DCF_NKE'!$B$9)/(1+'DCF_NKE'!$B$10)^4+('DCF_NKE'!$B$3*(1+D149)^5*('DCF_NKE'!$B$5*(1-'DCF_NKE'!$B$6)+'DCF_NKE'!$B$7-'DCF_NKE'!$B$8)-'DCF_NKE'!$B$3*(1+D149)^4*D149*'DCF_NKE'!$B$9)/(1+'DCF_NKE'!$B$10)^5+('DCF_NKE'!$B$3*(1+D149)^5*(1+'DCF_NKE'!$B$11)*('DCF_NKE'!$B$5*(1-'DCF_NKE'!$B$6)+'DCF_NKE'!$B$7-'DCF_NKE'!$B$8)-'DCF_NKE'!$B$3*(1+D149)^5*'DCF_NKE'!$B$11*'DCF_NKE'!$B$9)/('DCF_NKE'!$B$10-'DCF_NKE'!$B$11)/(1+'DCF_NKE'!$B$10)^5-'DCF_NKE'!$B$13)/'DCF_NKE'!$B$12))
... A196: 60 | B196: =IF($B$5="","",IF(E195<$B$5,D195,B195)) | C196: =IF($B$5="","",IF(E195<$B$5,C195,D195)) | D196: =IF($B$5="","",(B196+C196)/2) | E196: =IF($B$5="","",((('DCF_NKE'!$B$3*(1+D196)^1*('DCF_NKE'!$B$5*(1-'DCF_NKE'!$B$6)+'DCF_NKE'!$B$7-'DCF_NKE'!$B$8)-'DCF_NKE'!$B$3*(1+D196)^0*D196*'DCF_NKE'!$B$9)/(1+'DCF_NKE'!$B$10)^1+('DCF_NKE'!$B$3*(1+D196)^2*('DCF_NKE'!$B$5*(1-'DCF_NKE'!$B$6)+'DCF_NKE'!$B$7-'DCF_NKE'!$B$8)-'DCF_NKE'!$B$3*(1+D196)^1*D196*'DCF_NKE'!$B$9)/(1+'DCF_NKE'!$B$10)^2+('DCF_NKE'!$B$3*(1+D196)^3*('DCF_NKE'!$B$5*(1-'DCF_NKE'!$B$6)+'DCF_NKE'!$B$7-'DCF_NKE'!$B$8)-'DCF_NKE'!$B$3*(1+D196)^2*D196*'DCF_NKE'!$B$9)/(1+'DCF_NKE'!$B$10)^3+('DCF_NKE'!$B$3*(1+D196)^4*('DCF_NKE'!$B$5*(1-'DCF_NKE'!$B$6)+'DCF_NKE'!$B$7-'DCF_NKE'!$B$8)-'DCF_NKE'!$B$3*(1+D196)^3*D196*'DCF_NKE'!$B$9)/(1+'DCF_NKE'!$B$10)^4+('DCF_NKE'!$B$3*(1+D196)^5*('DCF_NKE'!$B$5*(1-'DCF_NKE'!$B$6)+'DCF_NKE'!$B$7-'DCF_NKE'!$B$8)-'DCF_NKE'!$B$3*(1+D196)^4*D196*'DCF_NKE'!$B$9)/(1+'DCF_NKE'!$B$10)^5+('DCF_NKE'!$B$3*(1+D196)^5*(1+'DCF_NKE'!$B$11)*('DCF_NKE'!$B$5*(1-'DCF_NKE'!$B$6)+'DCF_NKE'!$B$7-'DCF_NKE'!$B$8)-'DCF_NKE'!$B$3*(1+D196)^5*'DCF_NKE'!$B$11*'DCF_NKE'!$B$9)/('DCF_NKE'!$B$10-'DCF_NKE'!$B$11)/(1+'DCF_NKE'!$B$10)^5-'DCF_NKE'!$B$13)/'DCF_NKE'!$B$12))

Sheet TECHNICALS
A1: MIRROR X · PRELIMINARY · MX-3777d2e495a9
A2: Ticker | B2: SMA50 | C2: SMA200 | D2: Support | E2: Resistance | F2: Entry | G2: Exit | H2: Reason
A3: ADBE | H3: BLOCKED: no dated OHLCV. Never fabricate levels.
A4: PYPL | H4: BLOCKED: no dated OHLCV. Never fabricate levels.
A5: NKE | H5: BLOCKED: no dated OHLCV. Never fabricate levels.

Sheet RISKS
A1: MIRROR X · PRELIMINARY · MX-3777d2e495a9
A2: Ticker | B2: Risk | C2: Probability | D2: Impact | E2: Invalidation trigger
A3: ADBE | B3: Замещение продукта AI-конкурентами | C3: Средняя — мнение аналитика | D3: Высокое; margin −3 п.п. в Bear | E3: Замедление роста подписок и снижение удержания
A4: ADBE | B4: Высокая чувствительность к ставке | C4: Средняя — сценарий | D4: WACC +1 п.п.; проверить sensitivity | E4: Устойчивое повышение долгосрочной доходности US Treasury
A5: PYPL | B5: Конкуренция в checkout | C5: Высокая — мнение аналитика | D5: Рост выручки −4 п.п. в Bear | E5: Ухудшение branded checkout и платёжной маржи
A6: PYPL | B6: Кредитный риск и BNPL | C6: Средняя — мнение аналитика | D6: Высокое; FCFF требует нормализации | E6: Рост потерь по кредитам или зависимость потока от продажи receivables
A7: NKE | B7: Потребитель и тарифы | C7: Высокая — мнение аналитика | D7: Высокое; margin −3 п.п. в Bear | E7: Рост скидок и отсутствие восстановления валовой маржи
A8: NKE | B8: Затяжное восстановление бренда | C8: Средняя — мнение аналитика | D8: Рост выручки −4 п.п. в Bear | E8: Рост запасов быстрее выручки два квартала подряд

Sheet PORTFOLIO
A1: MIRROR X · PRELIMINARY · MX-3777d2e495a9
A2: Ticker | B2: Status | C2: Close 02 Nov | D2: 12m model target | E2: Upside | F2: Weight | G2: Allocation USD | H2: Fair value today
A3: ADBE | B3: NOT-RATED | D3: ='DCF_ADBE'!B33 -> 266.27206 | E3: =IF(OR(C3="",C3<=0),"N/A",D3/C3-1) -> N/A | F3: 0.4 | G3: =F3*100000 -> 40000 | H3: ='DCF_ADBE'!B32 -> 257.20235
A4: PYPL | B4: NOT-RATED | D4: ='DCF_PYPL'!B33 -> 67.695341 | E4: =IF(OR(C4="",C4<=0),"N/A",D4/C4-1) -> N/A | F4: 0.35 | G4: =F4*100000 -> 35000 | H4: ='DCF_PYPL'!B32 -> 66.028255
A5: NKE | B5: NOT-RATED | D5: ='DCF_NKE'!B33 -> 30.216648 | E5: =IF(OR(C5="",C5<=0),"N/A",D5/C5-1) -> N/A | F5: 0.25 | G5: =F5*100000 -> 25000 | H5: ='DCF_NKE'!B32 -> 29.500029
A6: TOTAL | F6: =SUM(F3:F5) -> 1 | G6: =SUM(G3:G5) -> 100000
A8: Weighted upside | B8: =IF(COUNT(E3:E5)=3,SUMPRODUCT(E3:E5,F3:F5),"N/A") -> N/A

Sheet CHECKS
A1: MIRROR X · PRELIMINARY · MX-3777d2e495a9
A2: Check | B2: Result | C2: Explanation
A3: Sum weights | B3: =IF(ABS(PORTFOLIO!F6-1)<0.0000001,"PASS","FAIL") -> PASS | C3: Exactly 100%
A4: Capital | B4: =IF(ABS(PORTFOLIO!G6-100000)<0.005,"PASS","FAIL") -> PASS | C4: $100,000
A5: 3 reviewed Buy | B5: BLOCKED | C5: No analyst signoff
A6: Close 2026-11-02 | B6: BLOCKED | C6: Future official close unavailable
A7: Eligibility | B7: BLOCKED | C7: Liquidity/history/segment evidence missing
A8: Technical analysis | B8: BLOCKED | C8: No dated OHLCV
A9: FINAL gate | B9: BLOCKED | C9: PRELIMINARY only

Sheet SNAPSHOT
A1: MIRROR X · PRELIMINARY · MX-3777d2e495a9
A2: id | B2: MX-3777d2e495a9
A3: generatedAt | B3: 2026-10-29T07:16:39.360Z
A4: cutoff | B4: 2026-10-29
A5: modelVersion | B5: fcff-drivers-v1
A6: scoreVersion | B6: sector-value-v1
A7: sourceHash | B7: 3777d2e495a9365bcd6998569215112469c5441a1edd9f20eb62512a7fcbf746
A8: status | B8: PRELIMINARY
A9: BLOCKER | B9: До закрытия 02.11.2026 конкурсные цены ещё недоступны.
A10: BLOCKER | B10: Не подтверждены 3-месячная ликвидность, история торгов и доли выручки запрещённых направлений.
A11: BLOCKER | B11: Три основных кандидата выбраны для исследования; нет трёх аналитически подтверждённых Buy.
A12: BLOCKER | B12: Годовые финансовые модели требуют сверки с последними кварталами и нормализации; PayPal BNPL требует отдельной проверки.
A13: BLOCKER | B13: Не загружена актуальная история OHLCV: технический анализ и вход/выход не финализированы.
A14: BLOCKER | B14: Общий набор: котировки без даты; провайдер Open Knowledge Foundation / datasets; upstream Yahoo Finance.
